Workbook
Name ene_25: 'TABLA ESTAD RESUL 2025'!$E$80:$K$80

Sheet ESFA feb 2025
B2: URBANIZACION MONTEVERDI P.H. NIT 900.317.187.5
B4: ESTADO DE LA SITUACION FINANCIERA COMPARATIVO: **ENERO 2025-FEBRERO DE 2025*
B6: ACTIVO | C6: 28/02//2025 | E6: 45688 | G6: DIF. $ | H6: DIF. %
B8: EFECTIVO Y SUS EQUIVALENTES
B9: CAJA MENOR | C9: 200000 | E9: 200000 | G9: =-C9+E9 -> 0 | H9: =+G9/C9 -> 0
B10: BANCOLOMBIA CUENTA DE OPERACIÓN | C10: 17827328 | E10: 18836449 | G10: =-C10+E10 -> 1009121.3 | H10: =+G10/C10 -> 0.056605302
C11: =SUM(C9:C10) -> 18027328 | E11: =SUM(E9:E10) -> 19036449 | G11: =SUM(G9:G10) -> 1009121.3 | H11: =+G11/C11 -> 0.055977308
B13: EFECTIVO RESTRINGIDO
B14: INVERSIONES
B15: INVERSION CDT | C15: 0 | E15: 0
B16: FIDUCUENTA BANCOLOMBIA | C16: 8477538.3 | E16: 8425444.3 | G16: =-C16+E16 -> -52094.04 | H16: =+G16/C16 -> -0.0061449489
C17: =SUM(C15:C16) -> 8477538.3 | E17: =SUM(E15:E16) -> 8425444.3 | G17: =-C17+E17 -> -52094.04 | H17: =+G17/C17 -> -0.0061449489
B19: CUENTAS POR COBRAR
B21: DEUDORES CORRIENTES
B22: COPROPIETARIOS | C22: 5984340 | E22: 4645234 | G22: =+E22-C22 -> -1339106 | H22: =+G22/C22 -> -0.22376837
B23: CONSIGNACIONES POR IDENTIFICAR | C23: 0 | E23: 0 | G23: =+E23-C23 -> 0 | H23: 0
C24: =SUM(C22:C23) -> 5984340 | E24: =SUM(E22:E23) -> 4645234 | G24: =SUM(G22:G23) -> -1339106 | H24: =+G24/C24 -> -0.22376837
B26: ANTICIPO PROVEEDORES | C26: 0 | E26: 0 | G26: =+E26-C26 -> 0 | H26: 0
B27: ANTICIPO OBRA TALUD-TUBERIAS | C27: 0 | E27: 0 | G27: =+E27-C27 -> 0
B28: DEUDORES VARIOS | C28: 50146 | E28: 33310
G29: =+E29-C29 -> 0
B30: GASTOS PAGADOS POR ANTICIPADO
B31: POLIZA SEGURO | C31: 452464 | E31: =+[1]Datos!$D$24/2 -> 1357394 | G31: =+E31-C31 -> 904930 | H31: =+G31/C31 -> 2.0000044
B33: TOTAL ACTIVO | C33: =+C11+C17+C24+C26+C31+C27+C28 -> 32991816 | E33: =+E11+E17+E24+E26+E31+E27+E28 -> 33497832 | G33: =-C33+E33 -> 506015.26 | H33: =+G33/C33 -> 0.015337599
B36: PASIVO
B38: CUENTAS POR PAGAR
B39: COSTOS Y GASTOS POR PAGAR | C39: =973636+471300 -> 1444936 | E39: =541510+488080 -> 1029590 | G39: =+E39-C39 -> -415346 | H39: =+G39/C39 -> -0.28744941
B40: RETENCION IMPUESTOS | C40: 97774.06 | E40: 299010 | G40: =-C40+E40 -> 201235.94 | H40: =+G40/C40 -> 2.0581731
B41: RETEICA | C41: 159977.82 | E41: 75083
C42: =SUM(C39:C41) -> 1702687.9 | E42: =SUM(E39:E41) -> 1403683 | G42: =SUM(G39:G40) -> -214110.06 | H42: =+G42/C42 -> -0.12574827
B43: PASIVOS DIFERIDOS
B44: INGRESOS RECIBIDOS DE TERCEROS
B45: CUOTA EXTRA 2022-RECONOCIMIENTO SEGURO | C45: 7425682 | E45: 7425682
B46: CUOTA EXTRA 2023 | C46: 8550122 | E46: 8550122 | G46: =-C46+E46 -> 0 | H46: =+G46/C46 -> 0
B47: REINVERSIÓN 2023 | C47: 3837291 | E47: 3837291 | G47: =-C47+E47 -> 0 | H47: =+G47/C47 -> 0
B48: CUOTA EXTRA 2024 | C48: =-[1]Datos!$G$61 -> 44870833 | E48: =-[1]Datos!$G$61 -> 44870833 | G48: =-C48+E48 -> 0
B49: TOTAL PASIVOS DIFERIDOS | C49: =SUM(C45:C48) -> 64683928 | E49: =SUM(E45:E48) -> 64683928 | G49: =SUM(G46:G47) -> 0 | H49: =+G49/C49 -> 0
B51: OTROS PASIVOS
B52: PROVISIÓN GASTO VIGILANCIA | C52: 0 | E52: 1598989 | G52: =+E52-C52 -> 1598989 | H52: 0
B53: TOTAL OTROS PASIVOS | C53: =SUM(C52:C52) -> 0 | E53: =SUM(E52:E52) -> 1598989 | G53: =SUM(G52:G52) -> 1598989 | H53: 0
B54: TOTAL PASIVO | C54: =+C42+C49+C53 -> 66386616 | E54: =+E42+E49+E53 -> 67686600 | G54: =+E54-C54 -> 1299984.1 | H54: =+G54/C54 -> 0.019582021
B56: PATRIMONIO
B57: FONDO DE IMPREVISTOS | C57: 8861215.9 | E57: 8574200.9 | G57: =+E57-C57 -> -287015 | H57: =+G57/C57 -> -0.032390025
B58: SUPERAVIT-DEFICIT EJERCIC. ANTER. | C58: 7100905.5 | E58: 7100905.5 | G58: =+E58-C58 -> 0 | H58: =+G58/C58 -> 0
B59: SUPERAVIT-DEFICIT DEL EJERCICIO PPTAL | C59: =+'[2]ESTADO DE RESULTADOS'!R64 -> 563544.11 | E59: 56589.37 | G59: =+E59-C59 -> -506954.74 | H59: =+G59/C59 -> -0.89958307
B60: GASTOS NO PRESUPUESTADOS X DEFINIR TALUD | C60: =-49920464 -> -49920464 | E60: =-49920464 -> -49920464 | H60: =+G60/C60 -> 0
B61: TOTAL PATRIMONIO | C61: =SUM(C57:C60) -> -33394799 | D61: =SUM(D57:D60) -> 0 | E61: =SUM(E57:E60) -> -34188768 | G61: =+E61-C61 -> -793969.74 | H61: =+G61/C61 -> 0.023775252
B63: TOTAL PASIVO Y PATRIMONIO | C63: =+C54+C61 -> 32991817 | D63: =+D54+D61 -> 0 | E63: =+E54+E61 -> 33497832 | G63: =+E63-C63 -> 506014.38 | H63: =+G63/C63 -> 0.015337572
C67: =+C33-C63 -> -0.88 | E67: =+E33-E63 -> 0
B68: TANIA MARIA ANGULO | G68: GABRIELA MUÑOZ MOLINA
B69: Administradora | G69: Contadora
B73: CR URBANIZACION MONTEVERDI P.H. - 900.317.187-5
B74: Balance de Prueba por Cuenta (Normal) Feb-28-2025
B75: Cuenta | C75: Nombre | D75: Saldo Anterior | E75: Débitos | F75: Créditos | G75: Nuevo Saldo
B76: 1 | C76: ACTIVOS | D76: 33497832 | E76: 56324783 | F76: 56830799 | G76: 32991816
B77: 11 | C77: DISPONIBLE | D77: 19036449 | E77: 27458879 | F77: 28468001 | G77: 18027328
B78: 1105 | C78: CAJA | D78: 200000 | E78: 0 | F78: 0 | G78: 200000
B79: 110510 | C79: CAJAS MENORES | D79: 200000 | E79: 0 | F79: 0 | G79: 200000
B80: 1120 | C80: CUENTAS DE AHORRO | D80: 18836449 | E80: 27458879 | F80: 28468001 | G80: 17827328
B81: 112005 | C81: BANCOS | D81: 18836449 | E81: 27458879 | F81: 28468001 | G81: 17827328
B82: 11200501 | C82: BANCOLOMBIA CTA 436-544512-07 | D82: 18836449 | E82: 27458879 | F82: 28468001 | G82: 17827328
B83: 12 | C83: INVERSIONES | D83: 8425444.3 | E83: 52094.04 | F83: 0 | G83: 8477538.3
B84: 1245 | C84: DERECHOS FIDUCIARIOS | D84: 8425444.3 | E84: 52094.04 | F84: 0 | G84: 8477538.3
B85: 124505 | C85: INVERSION MONEDA NACIONAL | D85: 8425444.3 | E85: 52094.04 | F85: 0 | G85: 8477538.3
B86: 13 | C86: DEUDORES | D86: 4678544 | E86: 28813810 | F86: 27457868 | G86: 6034486
B87: 1345 | C87: INGRESOS POR COBRAR | D87: 4645234 | E87: 28796974 | F87: 27457868 | G87: 5984340
... B96: 17052001 | C96: SEGURO ZONAS COMUNES | D96: 1357394 | E96: 0 | F96: 904930 | G96: 452464
B97: 2 | D97: -67686601 | E97: 3108959 | F97: 1808974 | G97: -66386616
B98: 23 | C98: CUENTAS POR PAGAR | D98: -1403683.9 | E98: 1509970 | F98: 1808974 | G98: -1702687.9
B99: 2335 | C99: COSTOS Y GASTOS POR PAGAR | D99: -1029590 | E99: 1212970 | F99: 1628316 | G99: -1444936
B100: 233525 | C100: HONORARIOS | D100: -488080 | E100: 976160 | F100: 488080 | G100: 0
B101: 23352501 | C101: HONORARIOS | D101: -488080 | E101: 976160 | F101: 488080 | G101: 0
B102: 233550 | C102: SERVICIOS PUBLICOS | D102: 0 | E102: 0 | F102: 973636 | G102: -973636
B103: 23355001 | C103: SERVICIOS PUBLICOS | D103: 0 | E103: 0 | F103: 973636 | G103: -973636
B104: 233595 | C104: OTROS | D104: -541510 | E104: 236810 | F104: 166600 | G104: -471300
B105: 23359501 | C105: OTROS | D105: -541510 | E105: 236810 | F105: 166600 | G105: -471300
B106: 2365 | C106: RETENCION EN LA FUENTE | D106: -299010.06 | E106: 297000 | F106: 95764 | G106: -97774.06
B107: 236515 | C107: RET FTE POR PAGAR HONORARIOS | D107: -22203 | E107: 0 | F107: 18802 | G107: -41005
B108: 23651502 | C108: RETE FUENTE HONORARIOS 11% | D108: -22203 | E108: 0 | F108: 18802 | G108: -41005
B109: 236525 | C109: RET FTE POR PAGAR SERVICIOS | D109: -275562 | E109: 0 | F109: 76962 | G109: -352524
... B130: 28150524 | C130: CUOTA EXTRA AÑO 2024 | D130: -44870833 | E130: 0 | F130: 0 | G130: -44870833
B131: 3 | D131: 34245358 | E131: 0 | F131: 287015 | G131: 33958343
B132: 33 | C132: RESERVAS | D132: -8574200.9 | E132: 0 | F132: 287015 | G132: -8861215.9
B133: 3305 | C133: RESERVAS OBLIGATORIAS | D133: -8574200.9 | E133: 0 | F133: 287015 | G133: -8861215.9
B134: 330595 | C134: OTRAS RESERVAS | D134: -8574200.9 | E134: 0 | F134: 287015 | G134: -8861215.9
B135: 33059501 | C135: FONDO IMPREVISTOS LEY 675 | D135: -8574200.9 | E135: 0 | F135: 287015 | G135: -8861215.9
B136: 36 | C136: RESULTADOS DEL EJERCICIO | D136: 42819559 | E136: 0 | F136: 0 | G136: 42819559
B137: 3605 | C137: EXCEDENTES DEL EJERCICIO | D137: 42819559 | E137: 0 | F137: 0 | G137: 42819559
B138: 360505 | C138: EXEDENTES DEL EJERCICO | D138: 42819559 | E138: 0 | F138: 0 | G138: 42819559
B139: 36050501 | C139: EXEDENTES DEL EJERCICIO | D139: 42819559 | E139: 0 | F139: 0 | G139: 42819559
B140: 37 | C140: RESULTADOS DE EJERC ANTERIORES | D140: -9.3132257e-10 | E140: 0 | F140: 0 | G140: -9.3132257e-10
B141: 3705 | C141: UTILIDADES O EXCED ACUMULADOS | D141: -9.3132257e-10 | E141: 0 | F141: 0 | G141: -9.3132257e-10
B142: 370505 | C142: UTILIDADES O EXCEDEN ACUMULADO | D142: -9.3132257e-10 | E142: 0 | F142: 0 | G142: -9.3132257e-10
B143: 37050501 | C143: UTILIDADES O EXCED ACUMULADOS | D143: -9.3132257e-10 | E143: 0 | F143: 0 | G143: -9.3132257e-10
... B206: 53050503 | C206: MANEJO SUCURSAL VIRTUAL | D206: 96548 | E206: 101058 | F206: 0 | G206: 197606

Sheet ESFA abril 2025
B2: URBANIZACION MONTEVERDI P.H. NIT 900.317.187.5
B4: ESTADO DE LA SITUACION FINANCIERA COMPARATIVO: *MARZO 2025-ABRIL 2025*
B6: ACTIVO | C6: 28/04//2025 | E6: 28/03//2025 | G6: DIF. $ | H6: DIF. %
B8: EFECTIVO Y SUS EQUIVALENTES
B9: CAJA MENOR | C9: 200000 | E9: 200000 | G9: =-C9+E9 -> 0 | H9: =+G9/C9 -> 0
B10: BANCOLOMBIA CUENTA DE OPERACIÓN | C10: 16236254 | E10: 16432366 | G10: =-C10+E10 -> 196112.1 | H10: =+G10/C10 -> 0.012078654
C11: =SUM(C9:C10) -> 16436254 | E11: =SUM(E9:E10) -> 16632366 | G11: =SUM(G9:G10) -> 196112.1 | H11: =+G11/C11 -> 0.011931679
B12: EFECTIVO RESTRINGIDO
B13: INVERSIONES
B14: INVERSION CDT | C14: 0 | E14: 0
B15: FIDUCUENTA BANCOLOMBIA | C15: 8594287.8 | E15: 8534559.7 | G15: =-C15+E15 -> -59728.13 | H15: =+G15/C15 -> -0.0069497475
C16: =SUM(C14:C15) -> 8594287.8 | E16: =SUM(E14:E15) -> 8534559.7 | G16: =-C16+E16 -> -59728.13 | H16: =+G16/C16 -> -0.0069497475
B18: CUENTAS POR COBRAR
B20: DEUDORES CORRIENTES
B21: COPROPIETARIOS | C21: 4269712 | E21: 4129452 | G21: =+E21-C21 -> -140260 | H21: =+G21/C21 -> -0.032849991
B22: CONSIGNACIONES POR IDENTIFICAR | C22: 0 | E22: 0 | G22: =+E22-C22 -> 0 | H22: 0
C23: =SUM(C21:C22) -> 4269712 | E23: =SUM(E21:E22) -> 4129452 | G23: =SUM(G21:G22) -> -140260 | H23: =+G23/C23 -> -0.032849991
B25: ANTICIPO PROVEEDORES | C25: 0 | E25: 0 | G25: =+E25-C25 -> 0 | H25: 0
B26: ANTICIPO OBRA TALUD-TUBERIAS | C26: 0 | E26: 0 | G26: =+E26-C26 -> 0
B27: DEUDORES VARIOS | C27: 440118 | E27: 38070
G28: =+E28-C28 -> 0
B29: GASTOS PAGADOS POR ANTICIPADO
B30: POLIZA SEGURO | C30: 15358191 | E30: 16844468 | G30: =+E30-C30 -> 1486277 | H30: =+G30/C30 -> 0.096774223
B32: TOTAL ACTIVO | C32: =+C11+C16+C23+C25+C30+C26+C27 -> 45098563 | E32: =+E11+E16+E23+E25+E30+E26+E27 -> 46178916 | G32: =-C32+E32 -> 1080353 | H32: =+G32/C32 -> 0.023955375
C33: 28/04//2025 | E33: 28/03//2025 | G33: DIF. $ | H33: DIF. %
B34: PASIVO
B36: CUENTAS POR PAGAR
B37: COSTOS Y GASTOS POR PAGAR | C37: =-1359+6715424 -> 6714065 | E37: 14432437 | G37: =+E37-C37 -> 7718372 | H37: =+G37/C37 -> 1.1495826
B38: RETENCION IMPUESTOS | C38: 63720.06 | E38: 90156.56 | G38: =-C38+E38 -> 26436.5 | H38: =+G38/C38 -> 0.41488505
B39: RETEICA | C39: 103730.82 | E39: 47884.82
C40: =SUM(C37:C39) -> 6881515.9 | E40: =SUM(E37:E39) -> 14570478 | G40: =SUM(G37:G38) -> 7744808.5 | H40: =+G40/C40 -> 1.1254509
B41: PASIVOS DIFERIDOS
B42: INGRESOS RECIBIDOS DE TERCEROS
B43: CUOTA EXTRA 2022-RECONOCIMIENTO SEGURO | C43: 0 | E43: 7425682
B44: CUOTA EXTRA 2023 | C44: 0 | E44: 8550122 | G44: =-C44+E44 -> 8550122 | H44: NA
B45: REINVERSIÓN 2023 | C45: 0 | E45: 3837291 | G45: =-C45+E45 -> 3837291 | H45: NA
B46: CUOTA EXTRA 2024 | C46: 21864370 | E46: =-[1]Datos!$G$61 -> 44870833 | G46: =-C46+E46 -> 23006464
B47: TOTAL PASIVOS DIFERIDOS | C47: =SUM(C43:C46) -> 21864370 | E47: =SUM(E43:E46) -> 64683928 | G47: =SUM(G44:G45) -> 12387413 | H47: =+G47/C47 -> 0.56655706
B49: OTROS PASIVOS
B50: PROVISIÓN GASTO VIGILANCIA | C50: 0 | E50: 0 | G50: =+E50-C50 -> 0 | H50: 0
B51: TOTAL OTROS PASIVOS | C51: =SUM(C50:C50) -> 0 | E51: =SUM(E50:E50) -> 0 | G51: =SUM(G50:G50) -> 0 | H51: 0
B52: TOTAL PASIVO | C52: =+C40+C47+C51 -> 28745885 | E52: =+E40+E47+E51 -> 79254406 | G52: =+E52-C52 -> 50508521 | H52: =+G52/C52 -> 1.7570696
B54: PATRIMONIO
B55: FONDO DE IMPREVISTOS | C55: 9476606.9 | E55: 9148230.1 | G55: =+E55-C55 -> -328376.8 | H55: =+G55/C55 -> -0.034651305
B56: SUPERAVIT-DEFICIT EJERCIC. ANTER. | C56: 0 | E56: 7100905.5 | G56: =+E56-C56 -> 7100905.5 | H56: NA
B57: SUPERAVIT-DEFICIT DEL EJERCICIO PPTAL | C57: 6876070.4 | E57: 595837.69 | G57: =+E57-C57 -> -6280232.7 | H57: =+G57/C57 -> -0.91334619
B58: GASTOS NO PRESUPUESTADOS X DEFINIR TALUD | C58: 0 | E58: =-49920464 -> -49920464 | H58: NA
B59: TOTAL PATRIMONIO | C59: =SUM(C55:C58) -> 16352677 | D59: =SUM(D55:D58) -> 0 | E59: =SUM(E55:E58) -> -33075491 | G59: =+E59-C59 -> -49428168 | H59: =+G59/C59 -> -3.0226346
B61: TOTAL PASIVO Y PATRIMONIO | C61: =+C52+C59 -> 45098563 | D61: =+D52+D59 -> 0 | E61: =+E52+E59 -> 46178916 | G61: =+E61-C61 -> 1080353 | H61: =+G61/C61 -> 0.023955375
C63: =+C32-C61 -> 0 | E63: =+E32-E61 -> 0
B66: TANIA MARIA ANGULO | G66: GABRIELA MUÑOZ MOLINA
B67: Administradora | G67: Contadora
B70: DECISIONES ASAMBLEA
B71: GASTOS NO PRESUPUESTADOS X DEFINIR TALUD | C71: =-49920464 -> -49920464
B72: DEFICIT PPTAL 2023 | C72: -893269.33
B73: TOTAL A CUBRIR | C73: =SUM(C71:C72) -> -50813733
B74: CUBRIR ASI SEGÚN DECISIÓN ASAMBLEA
B75: CUOTA EXTRA 2022-RECONOCIMIENTO SEGURO | C75: 7425682
B76: CUOTA EXTRA 2023 | C76: 8550122
B77: REINVERSIÓN 2023 | C77: 3837291
B78: CUOTA EXTRA 2024 | C78: 23006464
B79: RESULTADOS DE 2024 | C79: 7994163.1
B80: total disposicion de fondos para cubrir | C80: =SUM(C75:C79) -> 50813722
B89: CR URBANIZACION MONTEVERDI P.H. - 900.317.187-5
B90: Balance de Prueba por Cuenta (Normal) Abr-30-2025
B91: Cuenta | C91: Nombre | D91: Saldo Anterior | E91: Débitos | F91: Créditos | G91: Nuevo Saldo
B92: 1 | C92: ACTIVOS | D92: 46178915 | E92: 66778860 | F92: 67859212 | G92: 45098563
B93: 11 | C93: DISPONIBLE | D93: 16632365 | E93: 33083828 | F93: 33279939 | G93: 16436254
B94: 1105 | C94: CAJA | D94: 200000 | E94: 0 | F94: 0 | G94: 200000
B95: 110510 | C95: CAJAS MENORES | D95: 200000 | E95: 0 | F95: 0 | G95: 200000
B96: 1120 | C96: CUENTAS DE AHORRO | D96: 16432365 | E96: 33083828 | F96: 33279939 | G96: 16236254
B97: 112005 | C97: BANCOS | D97: 16432365 | E97: 33083828 | F97: 33279939 | G97: 16236254
B98: 11200501 | C98: BANCOLOMBIA CTA 436-544512-07 | D98: 16432365 | E98: 33083828 | F98: 33279939 | G98: 16236254
B99: 12 | C99: INVERSIONES | D99: 8534559.7 | E99: 59728.13 | F99: 0 | G99: 8594287.8
B100: 1245 | C100: DERECHOS FIDUCIARIOS | D100: 8534559.7 | E100: 59728.13 | F100: 0 | G100: 8594287.8
B101: 124505 | C101: INVERSION MONEDA NACIONAL | D101: 8534559.7 | E101: 59728.13 | F101: 0 | G101: 8594287.8
B102: 13 | C102: DEUDORES | D102: 4167522 | E102: 33635304 | F102: 33092996 | G102: 4709830
B103: 1345 | C103: INGRESOS POR COBRAR | D103: 4129452 | E103: 33222945 | F103: 33082685 | G103: 4269712
... B112: 17052001 | C112: SEGURO ZONAS COMUNES | D112: 16844468 | E112: 0 | F112: 1486277 | G112: 15358191
B113: 2 | D113: -79254406 | E113: 8577331 | F113: 888369 | G113: -71565444
B114: 23 | C114: CUENTAS POR PAGAR | D114: -14570478 | E114: 8577331 | F114: 888369 | G114: -6881515.9
B115: 2335 | C115: COSTOS Y GASTOS POR PAGAR | D115: -14432437 | E115: 8487331 | F115: 768959 | G115: -6714065
B116: 233525 | C116: HONORARIOS | D116: -627190 | E116: 627190 | F116: 534352 | G116: -534352
B117: 23352501 | C117: HONORARIOS | D117: -627190 | E117: 627190 | F117: 534352 | G117: -534352
B118: 233595 | C118: OTROS | D118: -13805247 | E118: 7860141 | F118: 234607 | G118: -6179713
B119: 23359501 | C119: OTROS | D119: -13805247 | E119: 7860141 | F119: 234607 | G119: -6179713
B120: 2365 | C120: RETENCION EN LA FUENTE | D120: -90156.06 | E120: 90000 | F120: 63564 | G120: -63720.06
B121: 236515 | C121: RET FTE POR PAGAR HONORARIOS | D121: -59808 | E121: 0 | F121: 18802 | G121: -78610
B122: 23651502 | C122: RETE FUENTE HONORARIOS 11% | D122: -59808 | E122: 0 | F122: 18802 | G122: -78610
B123: 236525 | C123: RET FTE POR PAGAR SERVICIOS | D123: -409286 | E123: 0 | F123: 44762 | G123: -454048
B124: 23652502 | C124: RET FTE POR PAG ASEO Y VIGILAN | D124: -19476 | E124: 0 | F124: 6492 | G124: -25968
B125: 23652504 | C125: RET FTE POR PAGAR SERVIC 4% | D125: -130400 | E125: 0 | F125: 35200 | G125: -165600
... B143: 28150524 | C143: CUOTA EXTRA AÑO 2024 | D143: -44870833 | E143: 0 | F143: 0 | G143: -44870833
B144: 3 | D144: 33671328 | E144: 0 | F144: 328376 | G144: 33342952
B145: 33 | C145: RESERVAS | D145: -9148230.9 | E145: 0 | F145: 328376 | G145: -9476606.9
B146: 3305 | C146: RESERVAS OBLIGATORIAS | D146: -9148230.9 | E146: 0 | F146: 328376 | G146: -9476606.9
B147: 330595 | C147: OTRAS RESERVAS | D147: -9148230.9 | E147: 0 | F147: 328376 | G147: -9476606.9
B148: 33059501 | C148: FONDO IMPREVISTOS LEY 675 | D148: -9148230.9 | E148: 0 | F148: 328376 | G148: -9476606.9
B149: 36 | C149: RESULTADOS DEL EJERCICIO | D149: 42819559 | E149: 0 | F149: 0 | G149: 42819559
B150: 3605 | C150: EXCEDENTES DEL EJERCICIO | D150: 42819559 | E150: 0 | F150: 0 | G150: 42819559
...

Sheet GRAFICOS ESFA 2025

Sheet ESFA AGOST 2025
B2: URBANIZACION MONTEVERDI P.H. NIT 900.317.187.5
B4: ESTADO DE LA SITUACION FINANCIERA COMPARATIVO: *AGOSTO 2025-JULIO*
B6: ACTIVO | C6: 45900 | E6: 31/07//2025 | G6: DIF. $ | H6: DIF. %
B8: EFECTIVO Y SUS EQUIVALENTES
B9: CAJA MENOR | C9: 200000 | E9: 200000 | G9: =-C9+E9 -> 0 | H9: =+G9/C9 -> 0
B10: BANCOLOMBIA CUENTA DE OPERACIÓN | C10: =+V41 -> 50572213 | E10: 50775681 | G10: =-C10+E10 -> 203467.92 | H10: =+G10/C10 -> 0.0040233145
C11: =SUM(C9:C10) -> 50772213 | E11: 50975681 | G11: =SUM(G9:G10) -> 203467.92 | H11: =+G11/C11 -> 0.0040074661
B12: EFECTIVO RESTRINGIDO
B13: INVERSIONES
B14: INVERSION CDT | C14: 0 | E14: 0
B15: FIDUCUENTA BANCOLOMBIA | C15: =+V42 -> 10916890 | E15: 10852428 | G15: =-C15+E15 -> -64462.02 | H15: =+G15/C15 -> -0.0059047971
C16: =SUM(C14:C15) -> 10916890 | E16: 10852428 | G16: =-C16+E16 -> -64462.02 | H16: =+G16/C16 -> -0.0059047971
B18: CUENTAS POR COBRAR
B20: DEUDORES CORRIENTES
B21: COPROPIETARIOS | C21: =+V51 -> 14428308 | E21: 8689091 | G21: =+E21-C21 -> -5739217 | H21: =+G21/C21 -> -0.39777478 | R21: =+C32-V35 -> 0
B22: CONSIGNACIONES POR IDENTIFICAR | C22: =-408000 -> -408000 | E22: -408000 | G22: =+E22-C22 -> 0 | H22: 0
C23: =SUM(C21:C22) -> 14020308 | E23: 8281091 | G23: =SUM(G21:G22) -> -5739217 | H23: =+G23/C23 -> -0.40935028
B25: ANTICIPO PROVEEDORES | C25: 0 | E25: 0 | G25: =+E25-C25 -> 0 | H25: 0
B26: ANTICIPO OBRA TALUD-TUBERIAS | C26: 0 | E26: 0 | G26: =+E26-C26 -> 0
B27: DEUDORES VARIOS | C27: =+V47 -> 6688000 | E27: 3232000
G28: =+E28-C28 -> 0
B29: GASTOS PAGADOS POR ANTICIPADO
B30: POLIZA SEGURO | C30: =+V54 -> 9541969 | E30: 10985284 | G30: =+E30-C30 -> 1443315 | H30: =+G30/C30 -> 0.15125966
B32: TOTAL ACTIVO | C32: =+C11+C16+C23+C25+C30+C26+C27 -> 91939380 | E32: 84326484 | G32: =-C32+E32 -> -7612896.1 | H32: =+G32/C32 -> -0.082803431 | Q32: CR URBANIZACION MONTEVERDI P.H. - 900.317.187-5
Q33: Balance de Prueba por Cuenta (Normal) Ago-31-2025
B34: PASIVO | Q34: Cuenta | R34: Nombre | S34: Saldo Anterior | T34: Débitos | U34: Créditos | V34: Nuevo Saldo
Q35: 1 | R35: ACTIVOS | S35: 84326484 | T35: 73041704 | U35: 65428808 | V35: 91939380
B36: CUENTAS POR PAGAR | Q36: 11 | R36: DISPONIBLE | S36: 50567681 | T36: 32097502 | U36: 31892970 | V36: 50772213
B37: COSTOS Y GASTOS POR PAGAR | C37: =-V59 -> 677548 | E37: 677548 | G37: =+E37-C37 -> 0 | H37: =+G37/C37 -> 0 | Q37: 1105 | R37: CAJA | S37: 200000 | T37: 0 | U37: 0 | V37: 200000
B38: RETENCION IMPUESTOS | C38: =-V64 -> 135159.06 | E38: 274160.06 | G38: =-C38+E38 -> 139001 | H38: =+G38/C38 -> 1.0284253 | Q38: 110510 | R38: CAJAS MENORES | S38: 200000 | T38: 0 | U38: 0 | V38: 200000
B39: RETEICA | C39: 0 | E39: 0 | Q39: 1120 | R39: CUENTAS DE AHORRO | S39: 50367681 | T39: 32097502 | U39: 31892970 | V39: 50572213
C40: =SUM(C37:C39) -> 812707.06 | E40: 951708.06 | G40: =SUM(G37:G38) -> 139001 | H40: =+G40/C40 -> 0.17103457 | Q40: 112005 | R40: BANCOS | S40: 50367681 | T40: 32097502 | U40: 31892970 | V40: 50572213
B41: PASIVOS DIFERIDOS | Q41: 11200501 | R41: BANCOLOMBIA CTA 436-544512-07 | S41: 50367681 | T41: 32097502 | U41: 31892970 | V41: 50572213
B42: INGRESOS RECIBIDOS DE TERCEROS | J42: DECISIONES ASAMBLEA | Q42: 12 | R42: INVERSIONES | S42: 10852428 | T42: 64462.02 | U42: 0 | V42: 10916890
B43: CUOTA EXTRA 2022-RECONOCIMIENTO SEGURO | C43: 0 | E43: 0 | J43: GASTOS NO PRESUPUESTADOS X DEFINIR TALUD | K43: =-49920464 -> -49920464 | M43: 31805050 | Q43: 1245 | R43: DERECHOS FIDUCIARIOS | S43: 10852428 | T43: 64462.02 | U43: 0 | V43: 10916890
B44: CUOTA EXTRA 2023 | C44: 8550122 | E44: 8550122 | G44: =-C44+E44 -> 0 | H44: NA | J44: DEFICIT PPTAL 2023 | K44: -893269.33 | M44: -248452.74 | Q44: 124505 | R44: INVERSION MONEDA NACIONAL | S44: 10852428 | T44: 64462.02 | U44: 0 | V44: 10916890
B45: REINVERSIÓN 2023 | C45: 0 | E45: 0 | G45: =-C45+E45 -> 0 | H45: NA | J45: TOTAL A CUBRIR | K45: =SUM(K43:K44) -> -50813733 | M45: -8550122 | Q45: 13 | R45: DEUDORES | S45: 11921091 | T45: 40879740 | U45: 32092523 | V45: 20708308
B46: CUOTA EXTRA 2024 | C46: 44870845 | E46: 44870845 | G46: =-C46+E46 -> 0 | J46: CUBRIR ASI SEGÚN DECISIÓN ASAMBLEA | M46: =SUM(M43:M45) -> 23006475 | N46: =+M46+E46 -> 67877320 | Q46: 1330 | R46: ANTICIPOS Y AVANCES A CONTRATI | S46: 3232000 | T46: 3456000 | U46: 0 | V46: 6688000
B47: CUOTA EXTRA 2025 | C47: =-V86 -> 14999996 | E47: 7500003 | G47: =-C47+E47 -> -7499993 | J47: CUOTA EXTRA 2022-RECONOCIMIENTO SEGURO | K47: 7425682 | Q47: 133010 | R47: A CONTRATISTAS | S47: 3232000 | T47: 3456000 | U47: 0 | V47: 6688000
B48: TOTAL PASIVOS DIFERIDOS | C48: =SUM(C43:C47) -> 68420963 | E48: 60920970 | G48: =SUM(G44:G45) -> 0 | H48: =+G48/C48 -> 0 | J48: CUOTA EXTRA 2023 | K48: 8550122 | Q48: 13301005 | R48: CONTRATOS ZONAS COMUNES | S48: 3232000 | T48: 3456000 | U48: 0 | V48: 6688000
J49: REINVERSIÓN 2023 | K49: 3837291 | Q49: 1345 | R49: INGRESOS POR COBRAR | S49: 8689091 | T49: 37423740 | U49: 32092523 | V49: 14020308
B50: OTROS PASIVOS | J50: CUOTA EXTRA 2024 | K50: 23006464 | Q50: 134595 | R50: OTROS | S50: 8689091 | T50: 37423740 | U50: 32092523 | V50: 14020308
B51: PROVISIÓN GASTO VIGILANCIA | C51: 0 | E51: 0 | G51: =+E51-C51 -> 0 | H51: 0 | J51: RESULTADOS DE 2024 | K51: 7994163.1 | Q51: 13459501 | R51: CUOTAS DE ADMINISTRACION | S51: 8689091 | T51: 37423740 | U51: 31684523 | V51: 14428308
B52: TOTAL OTROS PASIVOS | C52: =SUM(C51:C51) -> 0 | E52: 0 | G52: =SUM(G51:G51) -> 0 | H52: 0 | J52: total disposicion de fondos para cubrir | K52: =SUM(K47:K51) -> 50813722 | M52: 31805050 | N52: 32115455 | Q52: 13459505 | R52: CONSIGNAC PEND POR IDENTIFICAR | S52: 0 | T52: 0 | U52: 408000 | V52: -408000
B53: TOTAL PASIVO | C53: =+C40+C48+C52 -> 69233670 | E53: 61872678 | G53: =+E53-C53 -> -7360992 | H53: =+G53/C53 -> -0.10632099 | M53: -8550122 | N53: -8550122 | Q53: 17 | R53: DIFERIDOS | S53: 10985284 | T53: 0 | U53: 1443315 | V53: 9541969
J54: REALIDAD DE LA APICACION | M54: -248452.74 | N54: -23006475 | Q54: 1705 | R54: GASTOS PAGADOS POR ANTICIPADO | S54: 10985284 | T54: 0 | U54: 1443315 | V54: 9541969
B55: PATRIMONIO | J55: GASTOS NO PRESUPUESTADOS X DEFINIR TALUD | K55: =-49920464 -> -49920464 | M55: =SUM(M52:M54) -> 23006475 | N55: =SUM(N52:N54) -> 558857.57 | Q55: 170520 | R55: SEGUROS Y FIANZAS | S55: 10985284 | T55: 0 | U55: 1443315 | V55: 9541969
B56: FONDO DE IMPREVISTOS | C56: =-V87 -> 10648444 | E56: 10351088 | G56: =+E56-C56 -> -297356 | H56: =+G56/C56 -> -0.027924831 | J56: DEFICIT PPTAL 2023 | K56: -893269.33 | M56: -23006373 | Q56: 17052001 | R56: SEGURO ZONAS COMUNES | S56: 10985284 | T56: 0 | U56: 1443315 | V56: 9541969
B57: SUPERAVIT-DEFICIT EJERCIC. ANTER. | C57: 0 | E57: 0 | G57: =+E57-C57 -> 0 | H57: NA | J57: TOTAL A CUBRIR | K57: =SUM(K55:K56) -> -50813733 | M57: =+M55+M56 -> 101.88 | Q57: 2 | S57: -61872678 | T57: 808452 | U57: 8169444 | V57: -69233670
B58: SUPERAVIT-DEFICIT DEL EJERCICIO PPTAL | C58: =+'[3]ESTADO DE RESULTADOS'!L68-C59+0.12 -> 11808814 | E58: 11854266 | G58: =+E58-C58 -> 45451.9 | H58: =+G58/C58 -> 0.0038489808 | J58: CUBRIR ASI SEGÚN DECISIÓN ASAMBLEA | Q58: 23 | R58: CUENTAS POR PAGAR | S58: -951708.06 | T58: 808452 | U58: 669451 | V58: -812707.06
B59: EXCEDENTE DE RECONOCIIENTO TALUD | C59: =248452.74-0.88 -> 248451.86 | E59: 248451.86 | H59: NA | J59: CUOTA EXTRA 2022-RECONOCIMIENTO SEGURO | K59: 7425682 | Q59: 2335 | R59: COSTOS Y GASTOS POR PAGAR | S59: -677548 | T59: 534452 | U59: 534452 | V59: -677548
B60: TOTAL PATRIMONIO | C60: =SUM(C56:C59) -> 22705710 | E60: 22453806 | G60: =+E60-C60 -> -251904.1 | H60: =+G60/C60 -> -0.011094306 | J60: CUOTA EXTRA 2023 | K60: 0 | Q60: 233525 | R60: HONORARIOS | S60: -534252 | T60: 534452 | U60: 534452 | V60: -534252
J61: REINVERSIÓN 2023 | K61: 3837291 | Q61: 23352501 | R61: HONORARIOS | S61: -534252 | T61: 534452 | U61: 534452 | V61: -534252
B62: TOTAL PASIVO Y PATRIMONIO | C62: =+C53+C60 -> 91939380 | E62: 84326484 | G62: =+E62-C62 -> -7612896.1 | H62: =+G62/C62 -> -0.082803431 | J62: CUOTA EXTRA 2024 | K62: 0 | M62: 31805050 | Q62: 233595 | R62: OTROS | S62: -143296 | T62: 0 | U62: 0 | V62: -143296
J63: RESULTADOS DE 2024 | K63: 7994163.1 | M63: -248452.74 | Q63: 23359501 | R63: OTROS | S63: -143296 | T63: 0 | U63: 0 | V63: -143296
C64: =+C32-C62 -> 0 | E64: =+E32-E62 -> 0 | J64: total disposicion de fondos para cubrir | K64: =SUM(K59:K63) -> 19257136 | Q64: 2365 | R64: RETENCION EN LA FUENTE | S64: -274160.06 | T64: 274000 | U64: 134999 | V64: -135159.06
J65: RECIBIDO | K65: 31805050 | Q65: 236515 | R65: RET FTE POR PAGAR HONORARIOS | S65: -135016 | T65: 0 | U65: 18803 | V65: -153819
J66: TOTAL PREVISTO PARA TALUD Y DEFIT | K66: =+K64+K65 -> 51062186 | Q66: 23651502 | R66: RETE FUENTE HONORARIOS 11% | S66: -135016 | T66: 0 | U66: 18803 | V66: -153819
B67: TANIA MARIA ANGULO | G67: GABRIELA MUÑOZ MOLINA | J67: DIFERECNIA | K67: =+K57+K66 -> 248452.74 | Q67: 236525 | R67: RET FTE POR PAGAR SERVICIOS | S67: -838082 | T67: 0 | U67: 116196 | V67: -954278
B68: Administradora | G68: Contadora | Q68: 23652502 | R68: RET FTE POR PAG ASEO Y VIGILAN | S68: -45588 | T68: 0 | U68: 6492 | V68: -52080
Q69: 23652504 | R69: RET FTE POR PAGAR SERVIC 4% | S69: -457874 | T69: 0 | U69: 106634 | V69: -564508
Q70: 23652505 | R70: RETEFUENTE SERV 1% | S70: -18420 | T70: 0 | U70: 3070 | V70: -21490
B71: DECISIONES ASAMBLEA | K71: 31805050 | Q71: 23652506 | R71: RET FTE POR PAG SERVICIOS 6% | S71: -316200 | T71: 0 | U71: 0 | V71: -316200
B72: GASTOS NO PRESUPUESTADOS X DEFINIR TALUD | C72: =-49920464 -> -49920464 | K72: -248452.74 | Q72: 236530 | R72: RET FTE POR PAG ARRENDAMIENTOS | S72: -9817 | T72: 0 | U72: 0 | V72: -9817
B73: DEFICIT PPTAL 2023 | C73: -893269.33 | K73: -8550122 | Q73: 23653004 | R73: RET FTE X P ARR BIEN MUEB 4% | S73: -9817 | T73: 0 | U73: 0 | V73: -9817
B74: TOTAL A CUBRIR | C74: =SUM(C72:C73) -> -50813733 | K74: =SUM(K71:K73) -> 23006475 | Q74: 236598 | R74: RETEFUENTE POR PAGAR | S74: 708754.94 | T74: 274000 | U74: 0 | V74: 982754.94
B75: CUBRIR ASI SEGÚN DECISIÓN ASAMBLEA | K75: =+G46 -> 0 | Q75: 2368 | R75: IMPTO IND Y CCIO RETENIDO | S75: 1.7462298e-10 | T75: 0 | U75: 0 | V75: 1.7462298e-10
B76: CUOTA EXTRA 2022-RECONOCIMIENTO SEGURO | C76: 7425682 | K76: =SUM(K74:K75) -> 23006475 | Q76: 236801 | R76: IMPTO RETENIDO RETE ICA | S76: -273219.18 | T76: 0 | U76: 0 | V76: -273219.18
B77: CUOTA EXTRA 2023 | C77: 8550122 | Q77: 23680101 | R77: RETEICA OCHO POR MIL | S77: -163461.18 | T77: 0 | U77: 0 | V77: -163461.18
B78: REINVERSIÓN 2023 | C78: 3837291 | Q78: 23680103 | R78: RETEICA 10 POR MIL | S78: -85815 | T78: 0 | U78: 0 | V78: -85815
B79: CUOTA EXTRA 2024 | C79: 23006464 | Q79: 23680104 | R79: RETEICA 9POR MIL | S79: -23943 | T79: 0 | U79: 0 | V79: -23943
B80: RESULTADOS DE 2024 | C80: 7994163.1 | Q80: 236898 | R80: PAGO RETE ICA | S80: 273219.18 | T80: 0 | U80: 0 | V80: 273219.18
B81: total disposicion de fondos para cubrir | C81: =SUM(C76:C80) -> 50813722 | Q81: 28 | R81: OTROS PASIVOS | S81: -60920970 | T81: 0 | U81: 7499993 | V81: -68420963
Q82: 2815 | R82: INGRESOS RECIBIDOS PARA TERC | S82: -60920970 | T82: 0 | U82: 7499993 | V82: -68420963
Q83: 281505 | R83: VALORES RECIB PARA TERCEROS | S83: -60920970 | T83: 0 | U83: 7499993 | V83: -68420963
B84: REALIDAD DE LA APICACION | Q84: 28150523 | R84: CUOTA EXTRA 2023-MURO Y CCTV | S84: -8550122 | T84: 0 | U84: 0 | V84: -8550122
B85: GASTOS NO PRESUPUESTADOS X DEFINIR TALUD | C85: =-49920464 -> -49920464 | Q85: 28150524 | R85: CUOTA EXTRA AÑO 2024 | S85: -44870845 | T85: 0 | U85: 0 | V85: -44870845
B86: DEFICIT PPTAL 2023 | C86: -893269.33 | Q86: 28150525 | R86: CUOTA EAXTRA 2025 | S86: -7500003 | T86: 0 | U86: 7499993 | V86: -14999996
B87: TOTAL A CUBRIR | C87: =SUM(C85:C86) -> -50813733 | Q87: 3 | S87: -10351088 | T87: 0 | U87: 297356 | V87: -10648444
B88: CUBRIR ASI SEGÚN DECISIÓN ASAMBLEA | Q88: 33 | R88: RESERVAS | S88: -10351088 | T88: 0 | U88: 297356 | V88: -10648444
B89: CUOTA EXTRA 2022-RECONOCIMIENTO SEGURO | C89: 7425682 | Q89: 3305 | R89: RESERVAS OBLIGATORIAS | S89: -10351088 | T89: 0 | U89: 297356 | V89: -10648444
B90: CUOTA EXTRA 2023 | C90: 0 | Q90: 330595 | R90: OTRAS RESERVAS | S90: -10351088 | T90: 0 | U90: 297356 | V90: -10648444
B91: REINVERSIÓN 2023 | C91: 3837291 | Q91: 33059501 | R91: FONDO IMPREVISTOS LEY 675 | S91: -10351088 | T91: 0 | U91: 297356 | V91: -10648444
B92: CUOTA EXTRA 2024 | C92: 0 | Q92: 36 | R92: RESULTADOS DEL EJERCICIO | S92: 7.4505806e-09 | T92: 0 | U92: 0 | V92: 7.4505806e-09
B93: RESULTADOS DE 2024 | C93: 7994163.1 | Q93: 3605 | R93: EXCEDENTES DEL EJERCICIO | S93: 7.4505806e-09 | T93: 0 | U93: 0 | V93: 7.4505806e-09
B94: total disposicion de fondos para cubrir | C94: =SUM(C89:C93) -> 19257136 | Q94: 360505 | R94: EXEDENTES DEL EJERCICO | S94: 7.4505806e-09 | T94: 0 | U94: 0 | V94: 7.4505806e-09
B95: RECIBIDO | C95: 31805050 | Q95: 36050501 | R95: EXEDENTES DEL EJERCICIO | S95: 7.4505806e-09 | T95: 0 | U95: 0 | V95: 7.4505806e-09
B96: TOTAL PREVISTO PARA TALUD Y DEFIT | C96: =+C94+C95 -> 51062186 | Q96: 37 | R96: RESULTADOS DE EJERC ANTERIORES | S96: -9.3132257e-10 | T96: 0 | U96: 0 | V96: -9.3132257e-10
B97: DIFERECNIA | C97: =+C87+C96 -> 248452.74 | Q97: 3705 | R97: UTILIDADES O EXCED ACUMULADOS | S97: -9.3132257e-10 | T97: 0 | U97: 0 | V97: -9.3132257e-10
Q98: 370505 | R98: UTILIDADES O EXCEDEN ACUMULADO | S98: -9.3132257e-10 | T98: 0 | U98: 0 | V98: -9.3132257e-10
Q99: 37050501 | R99: UTILIDADES O EXCED ACUMULADOS | S99: -9.3132257e-10 | T99: 0 | U99: 0 | V99: -9.3132257e-10

Sheet TABLA ESFA 2025
A1: CR URBANIZACION MONTEVERDI P.H. - 900.317.187-5
A2: ESTADO DE SITUACION FINANCIERA AÑO 2025
A3: ACTIVOS
B4: Enero | C4: Febrero | D4: Marzo | E4: Abril | G4: Mayo | I4: Junio | K4: Julio | M4: Agosto | N4: Septiembre | O4: Octubre | P4: Noviembre | Q4: Diciembre
A5: Efectivo y sus equivalentes | B5: ='ESFA feb 2025'!E11 -> 19036449 | C5: ='ESFA feb 2025'!C11 -> 18027328 | D5: ='ESFA abril 2025'!E11 -> 16632366 | E5: ='ESFA abril 2025'!C11 -> 16436254 | G5: ='ESFA MAY 2025'!C11 -> 52872061 | I5: ='ESFA JUN 2025'!C11 -> 48166179 | K5: ='ESFA JUL 2025'!C11 -> 50975681 | M5: ='ESFA AGOST 2025'!C11 -> 50772213
A7: Fiducuenta Bancolombia | B7: ='ESFA feb 2025'!E16 -> 8425444.3 | C7: ='ESFA feb 2025'!C17 -> 8477538.3 | D7: ='ESFA abril 2025'!E16 -> 8534559.7 | E7: ='ESFA abril 2025'!C15 -> 8594287.8 | G7: ='ESFA MAY 2025'!C15 -> 8658779.9 | I7: ='ESFA JUN 2025'!C15 -> 10764304 | K7: ='ESFA JUL 2025'!C16 -> 10852428 | M7: ='ESFA AGOST 2025'!C16 -> 10916890
A9: CXC Administración | B9: ='ESFA feb 2025'!E22 -> 4645234 | C9: ='ESFA feb 2025'!C22 -> 5984340 | D9: ='ESFA abril 2025'!E23 -> 4129452 | E9: ='ESFA abril 2025'!C21 -> 4269712 | G9: ='ESFA MAY 2025'!C21 -> 3942142 | I9: ='ESFA JUN 2025'!C21 -> 11341985 | K9: ='ESFA JUL 2025'!C21 -> 8689091 | M9: ='ESFA AGOST 2025'!C21 -> 14428308
A11: Pagos sin identificar | B11: -503652 | C11: =[4]ESFA!E22 -> -503652 | D11: 0 | E11: 0 | K11: ='ESFA JUL 2025'!C22 -> -408000 | M11: ='ESFA AGOST 2025'!C22 -> -408000
A13: Deudores varios | B13: ='ESFA feb 2025'!E28 -> 33310 | C13: ='ESFA feb 2025'!C28 -> 50146 | D13: ='ESFA abril 2025'!E27 -> 38070 | E13: ='ESFA abril 2025'!C27 -> 440118 | G13: ='ESFA MAY 2025'!C27 -> 0 | K13: ='ESFA JUL 2025'!C27 -> 3232000 | M13: ='ESFA AGOST 2025'!C27 -> 6688000
A15: Gasto por anticipado póliza seguros | B15: ='ESFA feb 2025'!E31 -> 1357394 | C15: ='ESFA feb 2025'!C31 -> 452464 | D15: ='ESFA abril 2025'!E30 -> 16844468 | E15: ='ESFA abril 2025'!C30 -> 15358191 | G15: ='ESFA MAY 2025'!C30 -> 13871914 | I15: ='ESFA JUN 2025'!C30 -> 12428599 | K15: ='ESFA JUL 2025'!C30 -> 10985284 | M15: ='ESFA AGOST 2025'!C30 -> 9541969
E16: =SUM(E5:E16) -> 0
A17: TOTAL ACTIVO | B17: =SUM(B5:B15) -> 32994180 | C17: =SUM(C5:C16) -> 32488164 | D17: =SUM(D5:D16) -> 46178916 | E17: =E5+E7+E9+E13+E15 -> 45098563 | G17: =G5+G7+G9+G13+G15 -> 79344897 | I17: ='ESFA JUN 2025'!C32 -> 82701066 | K17: ='ESFA JUL 2025'!C32 -> 84326484 | M17: =++M5+M7+M9+M11 -> 75709411
A21: PASIVOS
B22: Enero | C22: Febrero | D22: Marzo | E22: Abril | G22: Mayo | I22: Junio | K22: Julio | M22: Agosto
A23: CXP Gastos | B23: ='ESFA feb 2025'!E39 -> 1029590 | C23: ='ESFA feb 2025'!C39 -> 1444936 | D23: ='ESFA abril 2025'!E37 -> 14432437 | E23: ='ESFA abril 2025'!C37 -> 6714065 | G23: ='ESFA MAY 2025'!C37 -> 534252 | I23: ='ESFA JUN 2025'!C37 -> 727051 | K23: ='ESFA JUL 2025'!C37 -> 677548 | M23: ='ESFA AGOST 2025'!C37 -> 677548
A25: CXP | C25: 0 | D25: 0
A27: CXP Impuestos | B27: ='ESFA feb 2025'!E40+'ESFA feb 2025'!E41 -> 374093 | C27: ='ESFA feb 2025'!C40+'ESFA feb 2025'!C41 -> 257751.88 | D27: ='ESFA abril 2025'!E38+'ESFA abril 2025'!E39 -> 138041.38 | E27: ='ESFA abril 2025'!C38+'ESFA abril 2025'!C39 -> 167450.88 | G27: ='ESFA MAY 2025'!C38 -> 102902.06 | I27: ='ESFA JUN 2025'!C38 -> 62996.27 | K27: ='ESFA JUL 2025'!C38 -> 274160.06 | M27: ='ESFA AGOST 2025'!C38 -> 135159.06
A29: Reclamación Seguro | B29: 7425682 | C29: 7425682 | E29: ='ESFA abril 2025'!C43 -> 0
A31: Cuotas extras 2023 | B31: 8549190 | C31: 9715856 | D31: ='ESFA abril 2025'!E44 -> 8550122 | E31: ='ESFA abril 2025'!C44 -> 0 | I31: ='ESFA JUL 2025'!E44 -> 8550122 | K31: ='ESFA JUL 2025'!C44 -> 8550122 | M31: ='ESFA AGOST 2025'!C44 -> 8550122
A33: Inversiòn vigilancia | B33: 3837291 | C33: 3837291 | D33: 3837291 | E33: 0
A35: Cuota extra 2024 | B35: ='ESFA feb 2025'!E48 -> 44870833 | C35: ='ESFA feb 2025'!C48 -> 44870833 | D35: ='ESFA abril 2025'!C46 -> 21864370 | E35: ='ESFA abril 2025'!E46 -> 44870833 | G35: ='ESFA MAY 2025'!C46 -> 45463373 | I35: ='ESFA JUL 2025'!E46 -> 44870845 | K35: ='ESFA JUL 2025'!C46 -> 44870845 | M35: ='ESFA AGOST 2025'!C46 -> 44870845
A36: Cuota extra 2025 | G36: ='ESFA MAY 2025'!C47 -> 7500003 | I36: ='ESFA JUL 2025'!E47 -> 7500003 | K36: ='ESFA JUL 2025'!C47 -> 7500003 | M36: ='ESFA AGOST 2025'!C47 -> 14999996
A37: TOTAL PASIVOS | B37: =SUM(B23:B36) -> 66086679 | C37: =SUM(C23:C36) -> 67552350 | D37: =[5]ESFA!E51 -> 29813541 | E37: =[5]ESFA!C51 -> 25473877 | G37: =[5]ESFA!E51 -> 29813541 | I37: =SUM(I23:I36) -> 61711017 | K37: ='ESFA JUL 2025'!C53 -> 61872678 | M37: ='ESFA AGOST 2025'!C48 -> 68420963
A39: PATRIMONIO
B40: Enero | C40: Febrero | D40: Marzo | E40: Abril | G40: Mayo | I40: Junio | K40: Julio | M40: Agosto
A41: Reserva de ley 675 2001 | B41: ='ESFA feb 2025'!C57 -> 8861215.9 | C41: ='ESFA feb 2025'!E57 -> 8574200.9 | D41: ='ESFA abril 2025'!E55 -> 9148230.1 | E41: ='ESFA abril 2025'!C55 -> 9476606.9 | G41: ='ESFA MAY 2025'!C56 -> 9773964.9 | I41: ='ESFA JUN 2025'!C56 -> 10053730 | K41: ='ESFA JUL 2025'!C56 -> 10351088 | M41: ='ESFA AGOST 2025'!C56 -> 10648444
A43: Resultados del presente ejercicio | B43: ='ESFA feb 2025'!C59 -> 563544.11 | C43: ='ESFA feb 2025'!E59 -> 56589.37 | D43: ='ESFA abril 2025'!E57 -> 595837.69 | E43: ='ESFA abril 2025'!C57 -> 6876070.4 | G43: ='ESFA MAY 2025'!C58 -> 7171827.1 | I43: ='ESFA JUN 2025'!C58 -> 10687867 | K43: ='ESFA JUL 2025'!C58 -> 11854266 | M43: ='ESFA AGOST 2025'!C58 -> 11808814
A45: Excedente- reconocimiento talud | B45: ='ESFA feb 2025'!E58 -> 7100905.5 | C45: ='ESFA feb 2025'!C58 -> 7100905.5 | D45: ='ESFA abril 2025'!E58 -> -49920464 | E45: ='ESFA abril 2025'!C56 -> 0 | G45: ='ESFA MAY 2025'!C59 -> 248452.74 | I45: ='ESFA JUN 2025'!C59 -> 248452.74 | K45: ='ESFA JUL 2025'!C59 -> 248451.86 | M45: ='ESFA AGOST 2025'!C59 -> 248451.86
A46: TOTAL PATRIMONIO | E46: =E41+E43+E45 -> 16352677 | G46: =G41+G43+G45 -> 17194245 | I46: =SUM(I41:I45) -> 20990049 | K46: ='ESFA JUL 2025'!C60 -> 22453806 | M46: ='ESFA AGOST 2025'!C60 -> 22705710
B47: =SUM(B41:B45) -> 16525665 | C47: =SUM(C41:C45) -> 15731696 | D47: =SUM(D41:D45) -> -40176396
E50: 45748 | G50: 45778 | I50: 45809 | K50: 45839 | M50: 45870
A51: Activo | E51: =E17 -> 45098563 | G51: =G17 -> 79344897 | I51: =I17 -> 82701066 | K51: =K17 -> 84326484 | M51: ='ESFA AGOST 2025'!C32 -> 91939380
A52: Pasivo | E52: =E37 -> 25473877 | G52: =G37 -> 29813541 | I52: =I37 -> 61711017 | K52: =K37 -> 61872678 | M52: ='ESFA AGOST 2025'!C53 -> 69233670
A53: Patrimonio | E53: =E46 -> 16352677 | G53: =G46 -> 17194245 | I53: =I46 -> 20990049 | K53: =K46 -> 22453806 | M53: ='ESFA AGOST 2025'!C60 -> 22705710
A55: IINDICADOR LIQUIDEZ | G55: 45778 | I55: 45809 | K55: 45839 | M55: 45870
A56: Activo cte | G56: =G51 -> 79344897 | I56: =I51 -> 82701066 | K56: =K51 -> 84326484 | M56: =M51 -> 91939380
A57: Pasivo cte | G57: =G52 -> 29813541 | I57: =I52 -> 61711017 | K57: =K52 -> 61872678 | M57: =M52 -> 69233670
A58: Indice de liquidez | G58: =G56/G57 -> 2.6613711 | I58: =I56/I57 -> 1.3401346 | K58: =K56/K57 -> 1.3629034 | M58: =M56/M57 -> 1.3279576
A59: Indice base | G59: 1 | I59: 1 | K59: 1 | M59: 1

Sheet ESFA JUL 2025
B2: URBANIZACION MONTEVERDI P.H. NIT 900.317.187.5
B4: ESTADO DE LA SITUACION FINANCIERA COMPARATIVO: *JUNIO 2025-JULIO 2025*
B6: ACTIVO | C6: 28/07//2025 | E6: 28/06//2025 | G6: DIF. $ | H6: DIF. %
B8: EFECTIVO Y SUS EQUIVALENTES
B9: CAJA MENOR | C9: 200000 | E9: 200000 | G9: =-C9+E9 -> 0 | H9: =+G9/C9 -> 0
B10: BANCOLOMBIA CUENTA DE OPERACIÓN | C10: =408000+50367680.84 -> 50775681 | E10: 47966179 | G10: =-C10+E10 -> -2809502.2 | H10: =+G10/C10 -> -0.05533165
C11: =SUM(C9:C10) -> 50975681 | E11: =SUM(E9:E10) -> 48166179 | G11: =SUM(G9:G10) -> -2809502.2 | H11: =+G11/C11 -> -0.05511456
B12: EFECTIVO RESTRINGIDO
B13: INVERSIONES
B14: INVERSION CDT | C14: 0 | E14: 0
B15: FIDUCUENTA BANCOLOMBIA | C15: 10852428 | E15: 10764304 | G15: =-C15+E15 -> -88124.35 | H15: =+G15/C15 -> -0.0081202428
C16: =SUM(C14:C15) -> 10852428 | E16: =SUM(E14:E15) -> 10764304 | G16: =-C16+E16 -> -88124.35 | H16: =+G16/C16 -> -0.0081202428
B18: CUENTAS POR COBRAR
B20: DEUDORES CORRIENTES
B21: COPROPIETARIOS | C21: 8689091 | E21: 11341985 | G21: =+E21-C21 -> 2652894 | H21: =+G21/C21 -> 0.30531318
B22: CONSIGNACIONES POR IDENTIFICAR | C22: -408000 | E22: 0 | G22: =+E22-C22 -> 408000 | H22: 0
C23: =SUM(C21:C22) -> 8281091 | E23: =SUM(E21:E22) -> 11341985 | G23: =SUM(G21:G22) -> 3060894 | H23: =+G23/C23 -> 0.36962449
B25: ANTICIPO PROVEEDORES | C25: 0 | E25: 0 | G25: =+E25-C25 -> 0 | H25: 0
B26: ANTICIPO OBRA TALUD-TUBERIAS | C26: 0 | E26: 0 | G26: =+E26-C26 -> 0
B27: DEUDORES VARIOS | C27: 3232000 | E27: 0
G28: =+E28-C28 -> 0
B29: GASTOS PAGADOS POR ANTICIPADO
B30: POLIZA SEGURO | C30: 10985284 | E30: 12428599 | G30: =+E30-C30 -> 1443315 | H30: =+G30/C30 -> 0.13138623
B32: TOTAL ACTIVO | C32: =+C11+C16+C23+C25+C30+C26+C27 -> 84326484 | E32: =+E11+E16+E23+E25+E30+E26+E27 -> 82701066 | G32: =-C32+E32 -> -1625417.6 | H32: =+G32/C32 -> -0.019275291
B34: PASIVO
B36: CUENTAS POR PAGAR
B37: COSTOS Y GASTOS POR PAGAR | C37: =-142800+820348 -> 677548 | E37: 727051 | G37: =+E37-C37 -> 49503 | H37: =+G37/C37 -> 0.073061982
B38: RETENCION IMPUESTOS | C38: 274160.06 | E38: =0.21+62996.06 -> 62996.27 | G38: =-C38+E38 -> -211163.79 | H38: =+G38/C38 -> -0.77022083
B39: RETEICA | C39: 0 | E39: 0
C40: =SUM(C37:C39) -> 951708.06 | E40: =SUM(E37:E39) -> 790047.27 | G40: =SUM(G37:G38) -> -161660.79 | H40: =+G40/C40 -> -0.16986384
B41: PASIVOS DIFERIDOS
B42: INGRESOS RECIBIDOS DE TERCEROS | J42: DECISIONES ASAMBLEA
B43: CUOTA EXTRA 2022-RECONOCIMIENTO SEGURO | C43: 0 | E43: 0 | J43: GASTOS NO PRESUPUESTADOS X DEFINIR TALUD | K43: =-49920464 -> -49920464 | M43: 31805050
B44: CUOTA EXTRA 2023 | C44: 8550122 | E44: 8550122 | G44: =-C44+E44 -> 0 | H44: NA | J44: DEFICIT PPTAL 2023 | K44: -893269.33 | M44: -248452.74
B45: REINVERSIÓN 2023 | C45: 0 | E45: 0 | G45: =-C45+E45 -> 0 | H45: NA | J45: TOTAL A CUBRIR | K45: =SUM(K43:K44) -> -50813733 | M45: -8550122
B46: CUOTA EXTRA 2024 | C46: 44870845 | E46: 44870845 | G46: =-C46+E46 -> 0 | J46: CUBRIR ASI SEGÚN DECISIÓN ASAMBLEA | M46: =SUM(M43:M45) -> 23006475 | N46: =+M46+E46 -> 67877320
B47: CUOTA EXTRA 2025 | C47: 7500003 | E47: 7500003 | G47: =-C47+E47 -> 0 | J47: CUOTA EXTRA 2022-RECONOCIMIENTO SEGURO | K47: 7425682
B48: TOTAL PASIVOS DIFERIDOS | C48: =SUM(C43:C47) -> 60920970 | E48: =SUM(E43:E47) -> 60920970 | G48: =SUM(G44:G45) -> 0 | H48: =+G48/C48 -> 0 | J48: CUOTA EXTRA 2023 | K48: 8550122
J49: REINVERSIÓN 2023 | K49: 3837291
B50: OTROS PASIVOS | J50: CUOTA EXTRA 2024 | K50: 23006464
B51: PROVISIÓN GASTO VIGILANCIA | C51: 0 | E51: 0 | G51: =+E51-C51 -> 0 | H51: 0 | J51: RESULTADOS DE 2024 | K51: 7994163.1
B52: TOTAL OTROS PASIVOS | C52: =SUM(C51:C51) -> 0 | E52: =SUM(E51:E51) -> 0 | G52: =SUM(G51:G51) -> 0 | H52: 0 | J52: total disposicion de fondos para cubrir | K52: =SUM(K47:K51) -> 50813722 | M52: 31805050 | N52: 32115455
B53: TOTAL PASIVO | C53: =+C40+C48+C52 -> 61872678 | E53: =+E40+E48+E52 -> 61711017 | G53: =+E53-C53 -> -161660.79 | H53: =+G53/C53 -> -0.0026127977 | M53: -8550122 | N53: -8550122
J54: REALIDAD DE LA APICACION | M54: -248452.74 | N54: -23006475
B55: PATRIMONIO | J55: GASTOS NO PRESUPUESTADOS X DEFINIR TALUD | K55: =-49920464 -> -49920464 | M55: =SUM(M52:M54) -> 23006475 | N55: =SUM(N52:N54) -> 558857.57
B56: FONDO DE IMPREVISTOS | C56: 10351088 | E56: 10053730 | G56: =+E56-C56 -> -297358 | H56: =+G56/C56 -> -0.028727222 | J56: DEFICIT PPTAL 2023 | K56: -893269.33 | M56: -23006373
B57: SUPERAVIT-DEFICIT EJERCIC. ANTER. | C57: 0 | E57: 0 | G57: =+E57-C57 -> 0 | H57: NA | J57: TOTAL A CUBRIR | K57: =SUM(K55:K56) -> -50813733 | M57: =+M55+M56 -> 101.88
B58: SUPERAVIT-DEFICIT DEL EJERCICIO PPTAL | C58: =+'[6]ESTADO DE RESULTADOS'!K68-'[6]ESTADO DE RESULTADOS'!Q65 -> 11854266 | E58: 10687867 | G58: =+E58-C58 -> -1166399.6 | H58: =+G58/C58 -> -0.098394925 | J58: CUBRIR ASI SEGÚN DECISIÓN ASAMBLEA
B59: EXCEDENTE DE RECONOCIIENTO TALUD | C59: =248452.74-0.88 -> 248451.86 | E59: 248452.74 | H59: NA | J59: CUOTA EXTRA 2022-RECONOCIMIENTO SEGURO | K59: 7425682
B60: TOTAL PATRIMONIO | C60: =SUM(C56:C59) -> 22453806 | E60: =SUM(E56:E59) -> 20990049 | G60: =+E60-C60 -> -1463756.8 | H60: =+G60/C60 -> -0.065189695 | J60: CUOTA EXTRA 2023 | K60: 0
J61: REINVERSIÓN 2023 | K61: 3837291
B62: TOTAL PASIVO Y PATRIMONIO | C62: =+C53+C60 -> 84326484 | E62: =+E53+E60 -> 82701066 | G62: =+E62-C62 -> -1625417.5 | H62: =+G62/C62 -> -0.019275291 | J62: CUOTA EXTRA 2024 | K62: 0 | M62: 31805050
J63: RESULTADOS DE 2024 | K63: 7994163.1 | M63: -248452.74
C64: =+C32-C62 -> 0 | E64: =+E32-E62 -> 0 | J64: total disposicion de fondos para cubrir | K64: =SUM(K59:K63) -> 19257136
J65: RECIBIDO | K65: 31805050
J66: TOTAL PREVISTO PARA TALUD Y DEFIT | K66: =+K64+K65 -> 51062186
B67: TANIA MARIA ANGULO | G67: GABRIELA MUÑOZ MOLINA | J67: DIFERECNIA | K67: =+K57+K66 -> 248452.74
B68: Administradora | G68: Contadora
C69: =+'[6]ESTADO DE RESULTADOS'!K68 -> 12102719
C70: =+C58-C69 -> -248452.74
B71: DECISIONES ASAMBLEA | K71: 31805050
B72: GASTOS NO PRESUPUESTADOS X DEFINIR TALUD | C72: =-49920464 -> -49920464 | K72: -248452.74
B73: DEFICIT PPTAL 2023 | C73: -893269.33 | K73: -8550122
B74: TOTAL A CUBRIR | C74: =SUM(C72:C73) -> -50813733 | K74: =SUM(K71:K73) -> 23006475
B75: CUBRIR ASI SEGÚN DECISIÓN ASAMBLEA | K75: =+G46 -> 0
B76: CUOTA EXTRA 2022-RECONOCIMIENTO SEGURO | C76: 7425682 | K76: =SUM(K74:K75) -> 23006475
B77: CUOTA EXTRA 2023 | C77: 8550122
B78: REINVERSIÓN 2023 | C78: 3837291
B79: CUOTA EXTRA 2024 | C79: 23006464
B80: RESULTADOS DE 2024 | C80: 7994163.1
B81: total disposicion de fondos para cubrir | C81: =SUM(C76:C80) -> 50813722
B84: REALIDAD DE LA APICACION
B85: GASTOS NO PRESUPUESTADOS X DEFINIR TALUD | C85: =-49920464 -> -49920464
B86: DEFICIT PPTAL 2023 | C86: -893269.33
B87: TOTAL A CUBRIR | C87: =SUM(C85:C86) -> -50813733
B88: CUBRIR ASI SEGÚN DECISIÓN ASAMBLEA
B89: CUOTA EXTRA 2022-RECONOCIMIENTO SEGURO | C89: 7425682
B90: CUOTA EXTRA 2023 | C90: 0
B91: REINVERSIÓN 2023 | C91: 3837291
B92: CUOTA EXTRA 2024 | C92: 0
B93: RESULTADOS DE 2024 | C93: 7994163.1
B94: total disposicion de fondos para cubrir | C94: =SUM(C89:C93) -> 19257136
B95: RECIBIDO | C95: 31805050
B96: TOTAL PREVISTO PARA TALUD Y DEFIT | C96: =+C94+C95 -> 51062186
B97: DIFERECNIA | C97: =+C87+C96 -> 248452.74

Sheet ESFA JUN 2025
B2: URBANIZACION MONTEVERDI P.H. NIT 900.317.187.5
B4: ESTADO DE LA SITUACION FINANCIERA COMPARATIVO: *MAYO 2025-JUNIO 2025*
B6: ACTIVO | C6: 28/06//2025 | E6: 28/05//2025 | G6: DIF. $ | H6: DIF. %
B8: EFECTIVO Y SUS EQUIVALENTES
B9: CAJA MENOR | C9: 200000 | E9: 200000 | G9: =-C9+E9 -> 0 | H9: =+G9/C9 -> 0
B10: BANCOLOMBIA CUENTA DE OPERACIÓN | C10: 47966179 | E10: 52672061 | G10: =-C10+E10 -> 4705882.1 | H10: =+G10/C10 -> 0.098108339
C11: =SUM(C9:C10) -> 48166179 | E11: =SUM(E9:E10) -> 52872061 | G11: =SUM(G9:G10) -> 4705882.1 | H11: =+G11/C11 -> 0.097700965
B12: EFECTIVO RESTRINGIDO
B13: INVERSIONES
B14: INVERSION CDT | C14: 0 | E14: 0
B15: FIDUCUENTA BANCOLOMBIA | C15: 10764304 | E15: 8658779.9 | G15: =-C15+E15 -> -2105523.7 | H15: =+G15/C15 -> -0.19560241
C16: =SUM(C14:C15) -> 10764304 | E16: =SUM(E14:E15) -> 8658779.9 | G16: =-C16+E16 -> -2105523.7 | H16: =+G16/C16 -> -0.19560241
B18: CUENTAS POR COBRAR
B20: DEUDORES CORRIENTES
B21: COPROPIETARIOS | C21: 11341985 | E21: 3942142 | G21: =+E21-C21 -> -7399843 | H21: =+G21/C21 -> -0.65242927
B22: CONSIGNACIONES POR IDENTIFICAR | C22: 0 | E22: 0 | G22: =+E22-C22 -> 0 | H22: 0
C23: =SUM(C21:C22) -> 11341985 | E23: =SUM(E21:E22) -> 3942142 | G23: =SUM(G21:G22) -> -7399843 | H23: =+G23/C23 -> -0.65242927
B25: ANTICIPO PROVEEDORES | C25: 0 | E25: 0 | G25: =+E25-C25 -> 0 | H25: 0
B26: ANTICIPO OBRA TALUD-TUBERIAS | C26: 0 | E26: 0 | G26: =+E26-C26 -> 0
B27: DEUDORES VARIOS | C27: 0 | E27: 0
G28: =+E28-C28 -> 0
B29: GASTOS PAGADOS POR ANTICIPADO
B30: POLIZA SEGURO | C30: 12428599 | E30: 13871914 | G30: =+E30-C30 -> 1443315 | H30: =+G30/C30 -> 0.11612854
B32: TOTAL ACTIVO | C32: =+C11+C16+C23+C25+C30+C26+C27 -> 82701066 | E32: =+E11+E16+E23+E25+E30+E26+E27 -> 79344897 | G32: =-C32+E32 -> -3356169.6 | H32: =+G32/C32 -> -0.040581938
B34: PASIVO
B36: CUENTAS POR PAGAR
B37: COSTOS Y GASTOS POR PAGAR | C37: 727051 | E37: 534252 | G37: =+E37-C37 -> -192799 | H37: =+G37/C37 -> -0.26517947
B38: RETENCION IMPUESTOS | C38: =0.21+62996.06 -> 62996.27 | E38: =-0.09+102902.06 -> 102901.97 | G38: =-C38+E38 -> 39905.7 | H38: =+G38/C38 -> 0.63346131
B39: RETEICA | C39: 0 | E39: 0
C40: =SUM(C37:C39) -> 790047.27 | E40: =SUM(E37:E39) -> 637153.97 | G40: =SUM(G37:G38) -> -152893.3 | H40: =+G40/C40 -> -0.19352424
B41: PASIVOS DIFERIDOS
B42: INGRESOS RECIBIDOS DE TERCEROS | J42: DECISIONES ASAMBLEA
B43: CUOTA EXTRA 2022-RECONOCIMIENTO SEGURO | C43: 0 | E43: 0 | J43: GASTOS NO PRESUPUESTADOS X DEFINIR TALUD | K43: =-49920464 -> -49920464 | M43: 31805050
B44: CUOTA EXTRA 2023 | C44: 8550122 | E44: 8550122 | G44: =-C44+E44 -> 0 | H44: NA | J44: DEFICIT PPTAL 2023 | K44: -893269.33 | M44: -248452.74
B45: REINVERSIÓN 2023 | C45: 0 | E45: 0 | G45: =-C45+E45 -> 0 | H45: NA | J45: TOTAL A CUBRIR | K45: =SUM(K43:K44) -> -50813733 | M45: -8550122
B46: CUOTA EXTRA 2024 | C46: 44870845 | E46: 45463373 | G46: =-C46+E46 -> 592528.12 | J46: CUBRIR ASI SEGÚN DECISIÓN ASAMBLEA | M46: =SUM(M43:M45) -> 23006475 | N46: =+M46+E46 -> 68469848
B47: CUOTA EXTRA 2025 | C47: 7500003 | E47: 7500003 | G47: =-C47+E47 -> 0 | J47: CUOTA EXTRA 2022-RECONOCIMIENTO SEGURO | K47: 7425682
B48: TOTAL PASIVOS DIFERIDOS | C48: =SUM(C43:C47) -> 60920970 | E48: =SUM(E43:E47) -> 61513498 | G48: =SUM(G44:G45) -> 0 | H48: =+G48/C48 -> 0 | J48: CUOTA EXTRA 2023 | K48: 8550122
J49: REINVERSIÓN 2023 | K49: 3837291
B50: OTROS PASIVOS | J50: CUOTA EXTRA 2024 | K50: 23006464
B51: PROVISIÓN GASTO VIGILANCIA | C51: 0 | E51: 0 | G51: =+E51-C51 -> 0 | H51: 0 | J51: RESULTADOS DE 2024 | K51: 7994163.1
B52: TOTAL OTROS PASIVOS | C52: =SUM(C51:C51) -> 0 | E52: =SUM(E51:E51) -> 0 | G52: =SUM(G51:G51) -> 0 | H52: 0 | J52: total disposicion de fondos para cubrir | K52: =SUM(K47:K51) -> 50813722 | M52: 31805050 | N52: 32115455
B53: TOTAL PASIVO | C53: =+C40+C48+C52 -> 61711017 | E53: =+E40+E48+E52 -> 62150652 | G53: =+E53-C53 -> 439634.82 | H53: =+G53/C53 -> 0.0071240897 | M53: -8550122 | N53: -8550122
J54: REALIDAD DE LA APICACION | M54: -248452.74 | N54: -23006475
B55: PATRIMONIO | J55: GASTOS NO PRESUPUESTADOS X DEFINIR TALUD | K55: =-49920464 -> -49920464 | M55: =SUM(M52:M54) -> 23006475 | N55: =SUM(N52:N54) -> 558857.57
B56: FONDO DE IMPREVISTOS | C56: 10053730 | E56: 9773964.9 | G56: =+E56-C56 -> -279765 | H56: =+G56/C56 -> -0.027826986 | J56: DEFICIT PPTAL 2023 | K56: -893269.33 | M56: -23006373
B57: SUPERAVIT-DEFICIT EJERCIC. ANTER. | C57: 0 | E57: 0 | G57: =+E57-C57 -> 0 | H57: NA | J57: TOTAL A CUBRIR | K57: =SUM(K55:K56) -> -50813733 | M57: =+M55+M56 -> 101.88
B58: SUPERAVIT-DEFICIT DEL EJERCICIO PPTAL | C58: =+'[7]ESTADO DE RESULTADOS'!Q66-0.88 -> 10687867 | E58: =+'[8]ESTADO DE RESULTADOS'!T65 -> 7171827.2 | G58: =+E58-C58 -> -3516039.4 | H58: =+G58/C58 -> -0.32897486 | J58: CUBRIR ASI SEGÚN DECISIÓN ASAMBLEA
B59: EXCEDENTE DE RECONOCIIENTO TALUD | C59: 248452.74 | E59: 248452.74 | H59: NA | J59: CUOTA EXTRA 2022-RECONOCIMIENTO SEGURO | K59: 7425682
B60: TOTAL PATRIMONIO | C60: =SUM(C56:C59) -> 20990049 | E60: =SUM(E56:E59) -> 17194245 | G60: =+E60-C60 -> -3795804.4 | H60: =+G60/C60 -> -0.18083828 | J60: CUOTA EXTRA 2023 | K60: 0
J61: REINVERSIÓN 2023 | K61: 3837291
B62: TOTAL PASIVO Y PATRIMONIO | C62: =+C53+C60 -> 82701066 | E62: =+E53+E60 -> 79344897 | G62: =+E62-C62 -> -3356169.6 | H62: =+G62/C62 -> -0.040581938 | J62: CUOTA EXTRA 2024 | K62: 0 | M62: 31805050
J63: RESULTADOS DE 2024 | K63: 7994163.1 | M63: -248452.74
C64: =+C32-C62 -> 0 | E64: =+E32-E62 -> 0.0024999827 | J64: total disposicion de fondos para cubrir | K64: =SUM(K59:K63) -> 19257136
J65: RECIBIDO | K65: 31805050
J66: TOTAL PREVISTO PARA TALUD Y DEFIT | K66: =+K64+K65 -> 51062186
B67: TANIA MARIA ANGULO | G67: GABRIELA MUÑOZ MOLINA | J67: DIFERECNIA | K67: =+K57+K66 -> 248452.74
B68: Administradora | G68: Contadora
B71: DECISIONES ASAMBLEA | K71: 31805050
B72: GASTOS NO PRESUPUESTADOS X DEFINIR TALUD | C72: =-49920464 -> -49920464 | K72: -248452.74
B73: DEFICIT PPTAL 2023 | C73: -893269.33 | K73: -8550122
B74: TOTAL A CUBRIR | C74: =SUM(C72:C73) -> -50813733 | K74: =SUM(K71:K73) -> 23006475
B75: CUBRIR ASI SEGÚN DECISIÓN ASAMBLEA | K75: =+G46 -> 592528.12
B76: CUOTA EXTRA 2022-RECONOCIMIENTO SEGURO | C76: 7425682 | K76: =SUM(K74:K75) -> 23599003
B77: CUOTA EXTRA 2023 | C77: 8550122
B78: REINVERSIÓN 2023 | C78: 3837291
B79: CUOTA EXTRA 2024 | C79: 23006464
B80: RESULTADOS DE 2024 | C80: 7994163.1
B81: total disposicion de fondos para cubrir | C81: =SUM(C76:C80) -> 50813722
B84: REALIDAD DE LA APICACION
B85: GASTOS NO PRESUPUESTADOS X DEFINIR TALUD | C85: =-49920464 -> -49920464
B86: DEFICIT PPTAL 2023 | C86: -893269.33
B87: TOTAL A CUBRIR | C87: =SUM(C85:C86) -> -50813733
B88: CUBRIR ASI SEGÚN DECISIÓN ASAMBLEA
B89: CUOTA EXTRA 2022-RECONOCIMIENTO SEGURO | C89: 7425682
B90: CUOTA EXTRA 2023 | C90: 0
B91: REINVERSIÓN 2023 | C91: 3837291
B92: CUOTA EXTRA 2024 | C92: 0
B93: RESULTADOS DE 2024 | C93: 7994163.1
B94: total disposicion de fondos para cubrir | C94: =SUM(C89:C93) -> 19257136
B95: RECIBIDO | C95: 31805050
B96: TOTAL PREVISTO PARA TALUD Y DEFIT | C96: =+C94+C95 -> 51062186
B97: DIFERECNIA | C97: =+C87+C96 -> 248452.74

Sheet ESFA JUN GRAF 2025
A1: CR URBANIZACION MONTEVERDI P.H. - 900.317.187-5
A2: ESTADO DE SITUACION FINANCIERA AÑO 2025
A3: ACTIVOS
B4: Enero | C4: Febrero | D4: Marzo | E4: Abril | G4: Mayo | I4: Junio | K4: Julio | L4: Agosto
A5: Efectivo y sus equivalentes | B5: ='ESFA feb 2025'!E11 -> 19036449 | C5: ='ESFA feb 2025'!C11 -> 18027328 | D5: ='ESFA abril 2025'!E11 -> 16632366 | E5: ='ESFA abril 2025'!C11 -> 16436254 | G5: ='ESFA MAY 2025'!C11 -> 52872061 | I5: ='ESFA JUN 2025'!C11 -> 48166179
A7: Fiducuenta Bancolombia | B7: ='ESFA feb 2025'!E16 -> 8425444.3 | C7: ='ESFA feb 2025'!C17 -> 8477538.3 | D7: ='ESFA abril 2025'!E16 -> 8534559.7 | E7: ='ESFA abril 2025'!C15 -> 8594287.8 | G7: ='ESFA MAY 2025'!C15 -> 8658779.9 | I7: ='ESFA JUN 2025'!C15 -> 10764304
A9: CXC Administración | B9: ='ESFA feb 2025'!E22 -> 4645234 | C9: ='ESFA feb 2025'!C22 -> 5984340 | D9: ='ESFA abril 2025'!E23 -> 4129452 | E9: ='ESFA abril 2025'!C21 -> 4269712 | G9: ='ESFA MAY 2025'!C21 -> 3942142 | I9: ='ESFA JUN 2025'!C21 -> 11341985
A11: Pagos sin identificar | B11: -503652 | C11: =[4]ESFA!E22 -> -503652 | D11: 0 | E11: 0
A13: Reclamaciones a proveedores | B13: ='ESFA feb 2025'!E28 -> 33310 | C13: ='ESFA feb 2025'!C28 -> 50146 | D13: ='ESFA abril 2025'!E27 -> 38070 | E13: ='ESFA abril 2025'!C27 -> 440118 | G13: ='ESFA MAY 2025'!C27 -> 0
A15: Gasto por anticipado póliza seguros | B15: ='ESFA feb 2025'!E31 -> 1357394 | C15: ='ESFA feb 2025'!C31 -> 452464 | D15: ='ESFA abril 2025'!E30 -> 16844468 | E15: ='ESFA abril 2025'!C30 -> 15358191 | G15: ='ESFA MAY 2025'!C30 -> 13871914 | I15: ='ESFA JUN 2025'!C30 -> 12428599
E16: =SUM(E5:E16) -> 0
A17: TOTAL ACTIVO | B17: =SUM(B5:B15) -> 32994180 | C17: =SUM(C5:C16) -> 32488164 | D17: =SUM(D5:D16) -> 46178916 | E17: =E5+E7+E9+E13+E15 -> 45098563 | G17: =G5+G7+G9+G13+G15 -> 79344897 | I17: ='ESFA JUN 2025'!C32 -> 82701066 | L17: =++L5+L7+L9+L11 -> 0
A21: PASIVOS
B22: Enero | C22: Febrero | D22: Marzo | E22: Abril | G22: Mayo | I22: Junio | K22: Julio | L22: Agosto
A23: CXP honorarios | B23: ='ESFA feb 2025'!E39 -> 1029590 | C23: ='ESFA feb 2025'!C39 -> 1444936 | D23: ='ESFA abril 2025'!E37 -> 14432437 | E23: ='ESFA abril 2025'!C37 -> 6714065 | G23: ='ESFA MAY 2025'!C37 -> 534252 | I23: ='ESFA JUN 2025'!C37 -> 727051
A25: CXP | C25: 0 | D25: 0
A27: CXP Impuestos | B27: ='ESFA feb 2025'!E40+'ESFA feb 2025'!E41 -> 374093 | C27: ='ESFA feb 2025'!C40+'ESFA feb 2025'!C41 -> 257751.88 | D27: ='ESFA abril 2025'!E38+'ESFA abril 2025'!E39 -> 138041.38 | E27: ='ESFA abril 2025'!C38+'ESFA abril 2025'!C39 -> 167450.88 | G27: ='ESFA MAY 2025'!C38 -> 102902.06 | I27: ='ESFA JUN 2025'!C38 -> 62996.27
A29: Reclamación Seguro | B29: 7425682 | C29: 7425682 | E29: ='ESFA abril 2025'!C43 -> 0
A31: Cuotas extras 2023 | B31: 8549190 | C31: 9715856 | D31: ='ESFA abril 2025'!E44 -> 8550122 | E31: ='ESFA abril 2025'!C44 -> 0
A33: Saldo Inversión vigilancia | B33: 3837291 | C33: 3837291 | D33: 3837291 | E33: 0
A35: Cuota extra 2024 | B35: ='ESFA feb 2025'!E48 -> 44870833 | C35: ='ESFA feb 2025'!C48 -> 44870833 | D35: ='ESFA abril 2025'!C46 -> 21864370 | E35: ='ESFA abril 2025'!E46 -> 44870833 | G35: ='ESFA MAY 2025'!C46 -> 45463373 | I35: ='ESFA JUN 2025'!C46 -> 44870845
A36: Cuota extra 2025 | G36: ='ESFA MAY 2025'!C47 -> 7500003 | I36: ='ESFA JUN 2025'!C47 -> 7500003
B37: =SUM(B23:B36) -> 66086679 | C37: =SUM(C23:C36) -> 67552350 | D37: =[5]ESFA!E51 -> 29813541 | E37: =[5]ESFA!C51 -> 25473877 | G37: =[5]ESFA!E51 -> 29813541 | I37: =SUM(I23:I36) -> 53160895
A39: PATRIMONIO
B40: Enero | C40: Febrero | D40: Marzo | E40: Abril | G40: Mayo | I40: Junio | K40: Julio | L40: Agosto
A41: Reserva de ley 675 2001 | B41: ='ESFA feb 2025'!C57 -> 8861215.9 | C41: ='ESFA feb 2025'!E57 -> 8574200.9 | D41: ='ESFA abril 2025'!E55 -> 9148230.1 | E41: ='ESFA abril 2025'!C55 -> 9476606.9 | G41: ='ESFA MAY 2025'!C56 -> 9773964.9 | I41: ='ESFA JUN 2025'!C56 -> 10053730
A43: Resultados del presente ejercicio | B43: ='ESFA feb 2025'!C59 -> 563544.11 | C43: ='ESFA feb 2025'!E59 -> 56589.37 | D43: ='ESFA abril 2025'!E57 -> 595837.69 | E43: ='ESFA abril 2025'!C57 -> 6876070.4 | G43: ='ESFA MAY 2025'!C58 -> 7171827.1 | I43: ='ESFA JUN 2025'!C58 -> 10687867
A45: Excedente- reconocimiento talud | B45: ='ESFA feb 2025'!E58 -> 7100905.5 | C45: ='ESFA feb 2025'!C58 -> 7100905.5 | D45: ='ESFA abril 2025'!E58 -> -49920464 | E45: ='ESFA abril 2025'!C56 -> 0 | G45: ='ESFA MAY 2025'!C59 -> 248452.74 | I45: ='ESFA JUN 2025'!C59 -> 248452.74
E46: =E41+E43+E45 -> 16352677 | G46: =G41+G43+G45 -> 17194245 | I46: =SUM(I41:I45) -> 20990049
B47: =SUM(B41:B45) -> 16525665 | C47: =SUM(C41:C45) -> 15731696 | D47: =SUM(D41:D45) -> -40176396
E50: 45748 | G50: 45778 | I50: 45809
A51: ACTIVO | E51: =E17 -> 45098563 | G51: =G17 -> 79344897 | I51: =I17 -> 82701066
A52: PASIVO | E52: =E37 -> 25473877 | G52: =G37 -> 29813541 | I52: =I37 -> 53160895
A53: PATRIMONIO | E53: =E46 -> 16352677 | G53: =G46 -> 17194245 | I53: =I46 -> 20990049

Sheet ESTAD RESUL JUN
B1: URBANIZACION MONTEVERDI P.H. NIT 900.317.187.5
B3: ESTADO INTEGRAL DE RESULTADOS A 31 DEJUNIO DE 2025
A5: 1 | B5: 6 | C5: PPTO ANUAL2025 | D5: PTTO.2025 | E5: REAL ENE. | F5: REAL FEB | G5: REAL MARZO | H5: REAL ABR | I5: REAL MAY | J5: REAL JUN | K5: REAL JUL | L5: REAL AGO | M5: REAL SEP | N5: REAL OCT | O5: REAL NOV | P5: REAL DIC | Q5: EJECUTADO ACUMUL. | R5: PTTO. ACUMUL. | S5: SOBRE O SUBEJECUCION | T5: VARIACION
B6: CUOTAS DE ADMINISTRACION | C6: 353308839 | D6: =+C6/12 -> 29442403 | E6: =-287015+28701567 -> 28414552 | F6: 28414552 | G6: 28414552 | H6: =+H8-H7 -> 32509259 | I6: =29735584-I7 -> 29438226 | J6: =+J8-J7 -> 29438226 | Q6: =SUM(E6:P6) -> 176629367 | R6: =+D6*$B$5 -> 1.7665442e+08 | S6: =+R6-Q6 -> 25052.5 | T6: =+R6-Q6 -> 25052.5
B7: Ing x Fondo imprevistos | C7: 3533088 | D7: =+C7/12 -> 294424 | E7: 287015 | F7: 287015 | G7: 287015 | H7: 328376 | I7: 297358 | J7: 297358 | Q7: =SUM(E7:P7) -> 1784137 | R7: =+D7*$B$5 -> 1766544 | S7: =+R7-Q7 -> -17593 | T7: =+R7-Q7 -> -17593
B8: TOTAL INGRESO OPERACIONAL | C8: =+C6+C7 -> 356841927 | D8: =SUM(D6:D7) -> 29736827 | E8: =SUM(E6:E7) -> 28701567 | F8: =SUM(F6:F7) -> 28701567 | G8: =SUM(G6:G7) -> 28701567 | H8: 32837635 | I8: =+I6+I7 -> 29735584 | J8: 29735584 | K8: =SUM(K6:K7) -> 0 | L8: 27282827 | M8: =SUM(M6:M7) -> 0 | N8: =SUM(N6:N7) -> 0 | O8: =SUM(O6:O7) -> 0 | P8: =SUM(P6:P7) -> 0 | Q8: =SUM(Q6:Q7) -> 178413504 | R8: =+D8*$B$5 -> 1.7842096e+08 | S8: =+R8-Q8 -> 7459.5 | T8: =+R8-Q8 -> 7459.5
B9: Gastos Operacionales
B10: Mantenimiento (Infraestructura)
B11: Aseo Y Piscina (Personal) | C11: 33199438 | D11: =+C11/12 -> 2766619.9 | E11: 2766619 | F11: 2766619 | G11: 2766619 | H11: 2766619 | I11: 2827988 | J11: 2766620 | Q11: =SUM(E11:P11) -> 16661084 | R11: =+D11*$B$5 -> 16599719 | S11: =+R11-Q11 -> -61364.84 | T11: =+R11-Q11 -> -61364.84
B12: Aseo (Insumos) | C12: 1260000 | D12: =+C12/12 -> 105000 | E12: 143550 | F12: 235199 | G12: 220474 | H12: 175110 | I12: 120400 | J12: 95350 | Q12: =SUM(E12:P12) -> 990083 | R12: =+D12*$B$5 -> 630000 | S12: =+R12-Q12 -> -360083 | T12: =+R12-Q12 -> -360083
B13: Zonas Comunes General | C13: 10500000 | D13: =+C13/12 -> 875000 | E13: 1581421 | F13: 0 | G13: =196100+277737+50000 -> 523837 | H13: 338825 | I13: =-111750+278850 -> 167100 | J13: 1050763 | Q13: =SUM(E13:P13) -> 3661946 | R13: =+D13*$B$5 -> 5250000 | S13: =+R13-Q13 -> 1588054 | T13: =+R13-Q13 -> 1588054
B14: Mantenimento Electrico | C14: 1800000 | D14: =+C14/12 -> 150000 | E14: 229300 | F14: 104000 | G14: 366738 | I14: 6000 | J14: 122000 | Q14: =SUM(E14:P14) -> 828038 | R14: =+D14*$B$5 -> 900000 | S14: =+R14-Q14 -> 71962 | T14: =+R14-Q14 -> 71962
B15: Piscina-Zona Húmeda-Turco | C15: 11900000 | D15: =+C15/12 -> 991666.67 | E15: 823302 | F15: 1301779 | G15: 611281 | H15: 203409 | I15: 984464 | J15: 203409 | Q15: =SUM(E15:P15) -> 4127644 | R15: =+D15*$B$5 -> 5950000 | S15: =+R15-Q15 -> 1822356 | T15: =+R15-Q15 -> 1822356
B16: Puerta Vehicular Y Peatonal | C16: 590000 | D16: =+C16/12 -> 49166.667 | E16: 0 | F16: 140000 | G16: 0 | Q16: =SUM(E16:P16) -> 140000 | R16: =+D16*$B$5 -> 295000 | S16: =+R16-Q16 -> 155000 | T16: =+R16-Q16 -> 155000
B17: Gimnasio | C17: 2429980 | D17: =+C17/12 -> 202498.33 | E17: 246330 | F17: 0 | G17: 749700 | I17: 246330 | J17: 0 | Q17: =SUM(E17:P17) -> 1242360 | R17: =+D17*$B$5 -> 1214990 | S17: =+R17-Q17 -> -27370 | T17: =+R17-Q17 -> -27370
B18: Dotacion | C18: 0 | D18: =+C18/12 -> 0 | E18: 0 | F18: 350000 | Q18: =SUM(E18:P18) -> 350000 | R18: =+D18*$B$5 -> 0 | S18: =+R18-Q18 -> -350000 | T18: =+R18-Q18 -> -350000
B19: Total Mantenimiento Y Mejoras | C19: =SUM(C11:C18) -> 61679418 | D19: =SUM(D11:D18) -> 5139951.5 | E19: =SUM(E11:E18) -> 5790522 | F19: =SUM(F11:F18) -> 4897597 | G19: =SUM(G11:G18) -> 5238649 | H19: =SUM(H11:H18) -> 3483963 | I19: =SUM(I11:I18) -> 4352282 | J19: =SUM(J11:J17) -> 4238142 | K19: =SUM(K11:K17) -> 0 | L19: =SUM(L11:L17) -> 0 | M19: =SUM(M11:M17) -> 0 | N19: =SUM(N11:N17) -> 0 | O19: =SUM(O11:O17) -> 0 | P19: =SUM(P11:P17) -> 0 | Q19: =SUM(Q11:Q18) -> 28001155 | R19: =+D19*$B$5 -> 30839709 | S19: =SUM(S11:S17) -> 3188554.2 | T19: =+R19-Q19 -> 2838554.2
B20: Seguridad | D20: =+C20/12 -> 0
B21: Vigilancia Privada | C21: 1.5883039e+08 | D21: =+C21/12 -> 13235866 | E21: 13136493 | F21: 13136493 | G21: 13136494 | H21: 13136494 | I21: 13136494 | J21: 13136493 | Q21: =SUM(E21:P21) -> 78818961 | R21: =+D21*$B$5 -> 79415196 | S21: =+R21-Q21 -> 596235.08 | T21: =+R21-Q21 -> 596235.08
B22: Refuerzo Vigilancia | C22: =1751531+2225540 -> 3977071 | D22: =+C22/12 -> 331422.58 | F22: 1751531 | Q22: =SUM(E22:P22) -> 1751531 | R22: =+D22*$B$5 -> 1988535.5 | T22: =+R22-Q22 -> 237004.5
B23: Seguro Zonas Comunes | C23: 17577558 | D23: =+C23/12 -> 1464796.5 | E23: 1357394 | F23: 904930 | G23: 1443315 | H23: 1486277 | I23: 1486277 | J23: 1443315 | Q23: =SUM(E23:P23) -> 8121508 | R23: =+D23*$B$5 -> 8788779 | S23: =+R23-Q23 -> 667271 | T23: =+R23-Q23 -> 667271
B24: Sistema De Seguridad Prev | C24: 1341006.2 | D24: =+C24/12 -> 111750.52 | E24: 640110 | F24: 111750 | G24: 111750 | H24: 111750 | I24: 111750 | J24: 111750 | Q24: =SUM(E24:P24) -> 1198860 | R24: =+D24*$B$5 -> 670503.12 | S24: =+R24-Q24 -> -528356.88 | T24: =+R24-Q24 -> -528356.88
B25: Sistema De Seg.Repuestos | C25: 1950000 | D25: =+C25/12 -> 162500 | E25: 0 | F25: 0 | G25: 0 | I25: 555730 | J25: 142800 | Q25: =SUM(E25:P25) -> 698530 | R25: =+D25*$B$5 -> 975000 | T25: =+R25-Q25 -> 276470
B26: Sg-Sst, Requisto De Ley | C26: 1910000 | D26: =+C26/12 -> 159166.67 | E26: 0 | F26: 0 | G26: 288000 | H26: 50000 | I26: 305387 | Q26: =SUM(E26:P26) -> 643387 | R26: =+D26*$B$5 -> 955000 | S26: =+R26-Q26 -> 311613 | T26: =+R26-Q26 -> 311613
B27: Extintores (Recarga) | C27: 372000 | D27: =+C27/12 -> 31000 | E27: 0 | F27: 0 | G27: 0 | Q27: =SUM(E27:P27) -> 0 | R27: =+D27*$B$5 -> 186000 | S27: =+#REF!-#REF! -> #REF! | T27: =+R27-Q27 -> 186000
B28: Planes De Ley Emerg, Trat Datos | C28: 740000 | D28: =+C28/12 -> 61666.667 | F28: 138500 | G28: 0 | Q28: =SUM(E28:P28) -> 138500 | R28: =+D28*$B$5 -> 370000 | S28: =+R28-Q28 -> 231500 | T28: =+R28-Q28 -> 231500
B29: Reserva Estatutaria 1% Del Ppto (De Ley) | C29: 3533088 | D29: =+C29/12 -> 294424 | E29: =+E7 -> 287015 | F29: 287015 | G29: 287015 | H29: 328376 | I29: =-14659+297358 -> 282699 | J29: =11725+282699 -> 294424 | Q29: =SUM(E29:P29) -> 1766544 | R29: =+D29*$B$5 -> 1766544 | S29: =+R29-Q29 -> 0 | T29: =+R29-Q29 -> 0
B30: Total Riesgos Y Seguridad | C30: =SUM(C21:C29) -> 1.9023112e+08 | D30: =+C30/12 -> 15852593 | E30: =SUM(E21:E29) -> 15421012 | F30: =SUM(F21:F29) -> 16330219 | G30: =SUM(G21:G29) -> 15266574 | H30: =SUM(H21:H29) -> 15112897 | I30: =SUM(I21:I29) -> 15878337 | J30: =SUM(J21:J29) -> 15128782 | K30: =SUM(K21:K29) -> 0 | L30: =SUM(L21:L29) -> 0 | ... Q30: =SUM(Q21:Q29) -> 93137821 | R30: =+D30*$B$5 -> 95115558 | S30: =SUM(S21:S29) -> #REF! | T30: =+R30-Q30 -> 1977736.7
B31: Convivencia | D31: =+C31/12 -> 0
B32: Celebraciones -Navidad | C32: 0 | D32: =+C32/12 -> 0 | E32: =+D32/12 -> 0 | F32: 0 | G32: 0 | H32: 0 | I32: 0 | J32: 179214 | K32: 0 | Q32: =SUM(E32:P32) -> 179214 | R32: =+D32*$B$5 -> 0 | S32: =+R32-Q32 -> -179214 | T32: =+R32-Q32 -> -179214
B33: Asamblea (Ley) | C33: 0 | D33: =+C33/12 -> 0 | E33: =+D33/12 -> 0 | F33: 0 | G33: =46000+17700+274950 -> 338650 | H33: 0 | I33: 176715 | J33: 0 | K33: 0 | L33: 0 | M33: 0 | N33: 0 | O33: 0 | P33: 0 | Q33: =SUM(E33:P33) -> 515365 | R33: =+D33*$B$5 -> 0 | S33: =+R33-Q33 -> -515365 | T33: =+R33-Q33 -> -515365
B34: Total Convivencia | C34: =SUM(C32:C33) -> 0 | D34: =+C34/12 -> 0 | E34: =SUM(E32:E33) -> 0 | F34: =SUM(F32:F33) -> 0 | G34: =SUM(G32:G33) -> 338650 | H34: =SUM(H32:H33) -> 0 | I34: =SUM(I32:I33) -> 176715 | J34: =SUM(J32:J33) -> 179214 | K34: =SUM(K32:K33) -> 0 | L34: =SUM(L32:L33) -> 0 | ... P34: =SUM(P32:P33) -> 0 | Q34: =SUM(E34:P34) -> 694579 | R34: =SUM(R32:R33) -> 0 | S34: =SUM(S32:S33) -> -694579 | T34: =+R34-Q34 -> -694579
B35: Ambiental | D35: =+C35/12 -> 0
B36: Fumigación | C36: 2568001.5 | D36: =+C36/12 -> 214000.12 | E36: 0 | F36: 0 | G36: 595450 | H36: 0 | I36: 781652 | Q36: =SUM(E36:P36) -> 1377102 | R36: =+D36*$B$5 -> 1284000.8 | S36: =+R36-Q36 -> -93101.25 | T36: =+R36-Q36 -> -93101.25
B37: Energía | C37: =33250000*1.15 -> 38237500 | D37: =+C37/12 -> 3186458.3 | E37: 3189683.9 | F37: 2628727 | G37: 2554892 | H37: 2640861 | I37: 3098024 | J37: 2908845 | Q37: =SUM(E37:P37) -> 17021033 | R37: =+D37*$B$5 -> 19118750 | S37: =+R37-Q37 -> 2097717.1 | T37: =+R37-Q37 -> 2097717.1
B38: Acueducto Y Alcantarillado | C38: 3500000 | D38: =+C38/12 -> 291666.67 | E38: 129706 | F38: 233099 | G38: 303870 | H38: 205744 | I38: 217588 | J38: 249565 | Q38: =SUM(E38:P38) -> 1339572 | R38: =+D38*$B$5 -> 1750000 | S38: =+R38-Q38 -> 410428 | T38: =+R38-Q38 -> 410428
B39: Tasa De Aseo | C39: 604000 | D39: =+C39/12 -> 50333.333 | E39: 50100 | F39: 50115 | G39: 56102 | H39: 56070 | I39: 56076 | J39: 55806 | Q39: =SUM(E39:P39) -> 324269 | R39: =+D39*$B$5 -> 302000 | S39: =+R39-Q39 -> -22269 | T39: =+R39-Q39 -> -22269
B40: SGIRS Pemirs Ley | C40: =100988*12 -> 1211856 | D40: =+C40/12 -> 100988 | E40: 0 | F40: 0 | G40: 55250 | H40: 0 | I40: 0 | Q40: =SUM(E40:P40) -> 55250 | R40: =+D40*$B$5 -> 605928 | T40: =+R40-Q40 -> 550678
B41: Telefonía E Internet | C41: 800000 | D41: =+C41/12 -> 66666.667 | E41: 87582 | F41: 100988 | G41: 100988 | H41: 100988 | I41: 100988 | J41: 100988 | Q41: =SUM(E41:P41) -> 592522 | R41: =+D41*$B$5 -> 400000 | S41: =+R41-Q41 -> -192522 | T41: =+R41-Q41 -> -192522
B42: Corte Cesped Y Mto Jardines Z. Comun | C42: =(1187000+167200)*12 -> 16250400 | D42: =+C42/12 -> 1354200 | E42: 1354200 | F42: 1354200 | G42: 1354200 | H42: 1354200 | I42: 1354200 | Q42: =SUM(E42:P42) -> 6771000 | R42: =+D42*$B$5 -> 8125200 | S42: =+R42-Q42 -> 1354200 | T42: =+R42-Q42 -> 1354200
B43: Tasa de seguridad | I43: 472500 | Q43: =SUM(E43:P43) -> 472500 | R43: =+D43*$B$5 -> 0 | T43: =+R43-Q43 -> -472500
B44: Total Ambiental | C44: =SUM(C36:C42) -> 63171758 | D44: =+C44/12 -> 5264313.1 | E44: =SUM(E36:E42) -> 4811271.9 | F44: =SUM(F36:F42) -> 4367129 | G44: =SUM(G36:G42) -> 5020752 | H44: =SUM(H36:H42) -> 4357863 | I44: =SUM(I36:I43) -> 6081028 | J44: =SUM(J36:J42) -> 3315204 | K44: =SUM(K36:K42) -> 0 | L44: =SUM(L36:L42) -> 0 | M44: =SUM(M36:M42) -> 0 | N44: =SUM(N36:N42) -> 0 | O44: =SUM(O36:O42) -> 0 | P44: =SUM(P36:P42) -> 0 | Q44: =SUM(Q36:Q43) -> 27953248 | R44: =+D44*$B$5 -> 31585879 | S44: =SUM(S36:S42) -> 3554452.9 | T44: =+R44-Q44 -> 3632630.9
B45: Administrativos | S45: =+F45+G45+E45 -> 0
B46: Administración | C46: 30797847 | D46: =+C46/12 -> 2566487.2 | E46: 2343824 | F46: 2343824 | G46: 2343824 | H46: 3235079 | I46: 2566487 | J46: 2566487 | Q46: =SUM(E46:P46) -> 15399525 | R46: =+D46*$B$5 -> 15398924 | S46: =+R46-Q46 -> -601.5 | T46: =+R46-Q46 -> -601.5
B47: Contabilidad | C47: 6413421 | D47: =+C47/12 -> 534451.75 | E47: 488080 | F47: 488080 | G47: 627190 | H47: 534352 | I47: 534352 | J47: 534352 | Q47: =SUM(E47:P47) -> 3206406 | R47: =+D47*$B$5 -> 3206710.5 | S47: =+R47-Q47 -> 304.5 | T47: =+R47-Q47 -> 304.5
B48: Informacion Exogena Y Niff | C48: 534465 | D48: =+C48/12 -> 44538.75 | E48: 0 | F48: 0 | G48: 0 | H48: 0 | I48: 0 | J48: 534565 | Q48: =SUM(E48:P48) -> 534565 | R48: =+D48*$B$5 -> 267232.5 | S48: =+R48-Q48 -> -267332.5 | T48: =+R48-Q48 -> -267332.5
B49: Facturación | C49: 603903 | D49: =+C49/12 -> 50325.25 | E49: 50344 | F49: 50344 | G49: 50344 | H49: 50344 | I49: 50344 | J49: 50344 | Q49: =SUM(E49:P49) -> 302064 | R49: =+D49*$B$5 -> 301951.5 | S49: =+R49-Q49 -> -112.5 | T49: =+R49-Q49 -> -112.5
B50: Útiles,Papelería -Comunicación | C50: 200000 | D50: =+C50/12 -> 16666.667 | E50: 0 | F50: 0 | G50: 10000 | H50: 10000 | I50: 0 | J50: 0 | Q50: =SUM(E50:P50) -> 20000 | R50: =+D50*$B$5 -> 100000 | S50: =+R50-Q50 -> 80000 | T50: =+R50-Q50 -> 80000
B51: Cafeteria | C51: 360000 | D51: =+C51/12 -> 30000 | E51: 0 | F51: 0 | G51: 26640 | H51: 4390 | I51: 27030 | J51: 0 | Q51: =SUM(E51:P51) -> 58060 | R51: =+D51*$B$5 -> 180000 | S51: =+R51-Q51 -> 121940 | T51: =+R51-Q51 -> 121940
B52: Transporte Trámites | C52: 150000 | D52: =+C52/12 -> 12500 | E52: 0 | F52: 0 | G52: 4500 | H52: 0 | I52: 0 | J52: 0 | Q52: =SUM(E52:P52) -> 4500 | R52: =+D52*$B$5 -> 75000 | S52: =+R52-Q52 -> 70500 | T52: =+R52-Q52 -> 70500
B53: Gastos Bancarios | C53: 2700000 | D53: =+C53/12 -> 225000 | E53: 191152.44 | F53: 189522.6 | G53: 196603.1 | H53: 179705.1 | I53: 225057.48 | J53: 101784 | Q53: =SUM(E53:P53) -> 1083824.7 | R53: =+D53*$B$5 -> 1350000 | S53: =+R53-Q53 -> 266175.28 | T53: =+R53-Q53 -> 266175.28
B54: Ajuste Al Peso | C54: 0 | D54: =+C54/12 -> 0 | E54: 0 | F54: 0 | G54: 1227 | H54: 5 | I54: -1887 | Q54: =SUM(E54:P54) -> -655 | R54: =+D54*$B$5 -> 0 | S54: =+#REF!-#REF! -> #REF! | T54: =+R54-Q54 -> 655
B55: Impuestos Asumidos | C55: 0 | D55: =+C55/12 -> 0 | Q55: =SUM(E55:P55) -> 0 | R55: =+D55*$B$5 -> 0 | S55: =+R55-Q55 -> 0 | T55: =+R55-Q55 -> 0
B56: Total Administrativos | C56: =SUM(C46:C55) -> 41759636 | D56: =SUM(D46:D55) -> 3479969.7 | E56: =SUM(E46:E55) -> 3073400.4 | F56: =SUM(F46:F55) -> 3071770.6 | G56: =SUM(G46:G55) -> 3260328.1 | H56: =SUM(H46:H55) -> 4013875.1 | I56: =SUM(I46:I55) -> 3401383.5 | J56: =SUM(J46:J55) -> 3787532 | Q56: =SUM(Q46:Q55) -> 20608290 | R56: =+D56*$B$5 -> 20879818 | S56: =SUM(S46:S55) -> #REF! | T56: =+R56-Q56 -> 271528.28
B57: Total Egresos Operacionales Mes | C57: =+C56+C44+C30+C34+C19 -> 3.5684193e+08 | D57: =+D56+D44+D30+D19 -> 29736827 | E57: =+E56+E44+E30+E34+E19 -> 29096206 | F57: =+F56+F44+F30+F34+F19 -> 28666716 | G57: =+G56+G44+G30+G34+G19 -> 29124953 | H57: =+H56+H44+H30+H34+H19 -> 26968598 | I57: =+I56+I44+I30+I34+I19 -> 29889745 | J57: =+J56+J44+J30+J34+J19 -> 26648874 | K57: =+K56+K44+K30+K34+K19 -> 0 | L57: =+L56+L44+L30+L34+L19 -> 0 | ... Q57: =+Q56+Q44+Q30+Q34+Q19 -> 1.7039509e+08 | R57: =+D57*$B$5 -> 1.7842096e+08 | S57: =+S56+S44+S30+S34+S19 -> #REF! | T57: =+T56+T44+T30+T34+T19 -> 8025871
B59: OTROS INGRESOS MARGINALES | C59: =SUM(C60:C64) -> 0 | E59: =SUM(E60:E65) -> 451228.69 | F59: =SUM(F60:F64) -> 472103.34 | G59: =SUM(G60:G64) -> 455679.26 | H59: =SUM(H60:H64) -> 411197.13 | I59: =SUM(I60:I65) -> 713029.05 | J59: =SUM(J60:J65) -> 414671.36 | K59: =SUM(K60:K64) -> 0 | L59: =SUM(L60:L64) -> 0 | M59: =SUM(M60:M64) -> 0 | N59: =SUM(N60:N64) -> 0 | O59: =SUM(O60:O64) -> 0 | P59: =SUM(P60:P64) -> 0 | Q59: =SUM(Q60:Q64) -> 2669456.1 | R59: =SUM(R60:R64) -> 0 | S59: =SUM(S60:S64) -> -2669456.1 | T59: =+Q59 -> 2669456.1
B60: Interes de Mora | E60: 69013 | F60: 95407 | G60: 139518 | H60: 92495 | I60: 136086 | J60: 108094 | Q60: =SUM(E60:P60) -> 640613 | R60: 0 | S60: =+R60-Q60 -> -640613
B61: Intereses Financieros | E61: =669.24+123715.45 -> 124384.69 | F61: =52094.04+1011.3 -> 53105.34 | G61: =57021.36+1056.9 -> 58078.26 | H61: =1143+59728.13 -> 60871.13 | I61: 67835.31 | J61: 48746.36 | Q61: =SUM(E61:P61) -> 413021.09 | R61: 0 | S61: =+R61-Q61 -> -413021.09
B62: Salon social | F62: 0 | I62: 0 | J62: 0 | K62: 0 | Q62: =SUM(E62:P62) -> 0 | R62: 0 | S62: =+R62-Q62 -> 0
B63: Dto pronto Pago | E63: 257831 | F63: 323591 | G63: 257831 | H63: 257831 | I63: 257831 | J63: 257831 | Q63: =SUM(E63:P63) -> 1612746 | R63: 0 | S63: =+R63-Q63 -> -1612746
B64: Aprovechamientos | G64: 252 | I64: =2321+503 -> 2824 | J64: 0 | Q64: =SUM(E64:P64) -> 3076 | R64: 0 | S64: =+R64-Q64 -> -3076
B65: Saldo reclamcion talud | I65: 248452.74 | J65: 0
B66: RESULTADO PRESUPUESTAL MES/AÑO | C66: =+C8-C57 -> -0.21000004 | D66: =+D8-D57 -> -0.017500002 | E66: =+E8-E57+E59 -> 56589.37 | F66: =+F8-F57+F59 -> 506954.74 | G66: =+G8-G57+G59 -> 32293.16 | H66: =+H8-H57+H59 -> 6280234 | I66: =+I8-I57+I59 -> 558867.57 | J66: =+J8-J57+J59 -> 3501381.4 | K66: =+K8-K57+K59 -> 0 | M66: =+M8-M57+M59 -> 0 | N66: =+N8-N57+N59 -> 0 | O66: =+O8-O57+O59 -> 0 | P66: =+P8-P57+P59 -> 0 | Q66: =+Q8-Q57+Q59 -> 10687867 | R66: 0 | S66: =+S8-S57+S59 -> #REF! | T66: =+T57-T8+T59 -> 10687868
F67: =SUM(E66:F66) -> 563544.11 | G67: =SUM(E66:G66) -> 595837.27 | H67: =SUM(E66:H66) -> 6876071.3 | I67: =SUM(E66:I66) -> 7434938.9
I68: =SUM(E66:I66) -> 7434938.9 | J68: =SUM(E66:J66) -> 10936320 | S68: =+Q66+S66 -> #REF!
B69: TANIA MARIA ANGULO | F69: GABRIELA MUÑOZ MOLINA | K69: GABRIELA MUÑOZ MOLINA
B70: Administradora | F70: Contadora | K70: Contadora
J74: -3501381.4
J75: =+J66+J74 -> 0
B76: DECISIONES ASAMBLEA
B77: GASTOS NO PRESUPUESTADOS X DEFINIR TALUD | C77: =-49920464 -> -49920464
B78: DEFICIT PPTAL 2023 | C78: -893269.33
B79: TOTAL A CUBRIR | C79: =SUM(C77:C78) -> -50813733
B80: CUBRIR ASI SEGÚN DECISIÓN ASAMBLEA
B81: CUOTA EXTRA 2022-RECONOCIMIENTO SEGURO | C81: 7425682
B82: CUOTA EXTRA 2023 | C82: 8550122
B83: REINVERSIÓN 2023 | C83: 3837291
B84: CUOTA EXTRA 2024 | C84: 23006464
B85: RESULTADOS DE 2024 | C85: 7994163.1
B86: total disposicion de fondos para cubrir | C86: =SUM(C81:C85) -> 50813722
B89: DECISIONES ASAMBLEA
B90: GASTOS NO PRESUPUESTADOS X DEFINIR TALUD | C90: =-49920464 -> -49920464
B91: DEFICIT PPTAL 2023 | C91: -893269.33
B92: TOTAL A CUBRIR | C92: =SUM(C90:C91) -> -50813733
B93: CUBRIR ASI SEGÚN DECISIÓN ASAMBLEA
B94: CUOTA EXTRA 2022-RECONOCIMIENTO SEGURO | C94: 7425682
B95: CUOTA EXTRA 2023 | C95: 0
B96: REINVERSIÓN 2023 | C96: 3837291
B97: CUOTA EXTRA 2024 | C97: 0
B98: RESULTADOS DE 2024 | C98: 7994163.1
B99: total disposicion de fondos para cubrir | C99: =SUM(C94:C98) -> 19257136
B101: RECIBIDO | C101: 31805050

Sheet ESFA GRAF 2025
A1: CR URBANIZACION MONTEVERDI P.H. - 900.317.187-5
A2: ESTADO DE SITUACION FINANCIERA AÑO 2025
A3: ACTIVOS
B4: Enero | C4: Febrero | D4: Marzo | E4: Abril | G4: Mayo | I4: Junio | K4: Julio | L4: Agosto
A5: Efectivo y sus equivalentes | B5: ='ESFA feb 2025'!E11 -> 19036449 | C5: ='ESFA feb 2025'!C11 -> 18027328 | D5: ='ESFA abril 2025'!E11 -> 16632366 | E5: ='ESFA abril 2025'!C11 -> 16436254 | G5: ='ESFA MAY 2025'!C11 -> 52872061 | I5: ='ESFA JUN 2025'!C11 -> 48166179
A7: Fiducuenta Bancolombia | B7: ='ESFA feb 2025'!E16 -> 8425444.3 | C7: ='ESFA feb 2025'!C17 -> 8477538.3 | D7: ='ESFA abril 2025'!E16 -> 8534559.7 | E7: ='ESFA abril 2025'!C15 -> 8594287.8 | G7: ='ESFA MAY 2025'!C15 -> 8658779.9 | I7: ='ESFA JUN 2025'!C15 -> 10764304
A9: CXC Administración | B9: ='ESFA feb 2025'!E22 -> 4645234 | C9: ='ESFA feb 2025'!C22 -> 5984340 | D9: ='ESFA abril 2025'!E23 -> 4129452 | E9: ='ESFA abril 2025'!C21 -> 4269712 | G9: ='ESFA MAY 2025'!C21 -> 3942142 | I9: ='ESFA JUN 2025'!C21 -> 11341985
A11: Pagos sin identificar | B11: -503652 | C11: =[4]ESFA!E22 -> -503652 | D11: 0 | E11: 0
A13: Reclamaciones a proveedores | B13: ='ESFA feb 2025'!E28 -> 33310 | C13: ='ESFA feb 2025'!C28 -> 50146 | D13: ='ESFA abril 2025'!E27 -> 38070 | E13: ='ESFA abril 2025'!C27 -> 440118 | G13: ='ESFA MAY 2025'!C27 -> 0
A15: Gasto por anticipado póliza seguros | B15: ='ESFA feb 2025'!E31 -> 1357394 | C15: ='ESFA feb 2025'!C31 -> 452464 | D15: ='ESFA abril 2025'!E30 -> 16844468 | E15: ='ESFA abril 2025'!C30 -> 15358191 | G15: ='ESFA MAY 2025'!C30 -> 13871914 | I15: ='ESFA JUN 2025'!C30 -> 12428599
E16: =SUM(E5:E16) -> 0
A17: TOTAL ACTIVO | B17: =SUM(B5:B15) -> 32994180 | C17: =SUM(C5:C16) -> 32488164 | D17: =SUM(D5:D16) -> 46178916 | E17: =E5+E7+E9+E13+E15 -> 45098563 | G17: =G5+G7+G9+G13+G15 -> 79344897 | I17: ='ESFA JUN 2025'!C32 -> 82701066 | L17: =++L5+L7+L9+L11 -> 0
A21: PASIVOS
B22: Enero | C22: Febrero | D22: Marzo | E22: Abril | G22: Mayo | I22: Junio | K22: Julio | L22: Agosto
A23: CXP honorarios | B23: ='ESFA feb 2025'!E39 -> 1029590 | C23: ='ESFA feb 2025'!C39 -> 1444936 | D23: ='ESFA abril 2025'!E37 -> 14432437 | E23: ='ESFA abril 2025'!C37 -> 6714065 | G23: ='ESFA MAY 2025'!C37 -> 534252 | I23: ='ESFA JUN 2025'!C37 -> 727051
A25: CXP | C25: 0 | D25: 0
A27: CXP Impuestos | B27: ='ESFA feb 2025'!E40+'ESFA feb 2025'!E41 -> 374093 | C27: ='ESFA feb 2025'!C40+'ESFA feb 2025'!C41 -> 257751.88 | D27: ='ESFA abril 2025'!E38+'ESFA abril 2025'!E39 -> 138041.38 | E27: ='ESFA abril 2025'!C38+'ESFA abril 2025'!C39 -> 167450.88 | G27: ='ESFA MAY 2025'!C38 -> 102902.06 | I27: ='ESFA JUN 2025'!C38 -> 62996.27
A29: Reclamación Seguro | B29: 7425682 | C29: 7425682 | E29: ='ESFA abril 2025'!C43 -> 0
A31: Cuotas extras 2023 | B31: 8549190 | C31: 9715856 | D31: ='ESFA abril 2025'!E44 -> 8550122 | E31: ='ESFA abril 2025'!C44 -> 0
A33: Saldo Inversión vigilancia | B33: 3837291 | C33: 3837291 | D33: 3837291 | E33: 0
A35: Cuota extra 2024 | B35: ='ESFA feb 2025'!E48 -> 44870833 | C35: ='ESFA feb 2025'!C48 -> 44870833 | D35: ='ESFA abril 2025'!C46 -> 21864370 | E35: ='ESFA abril 2025'!E46 -> 44870833 | G35: ='ESFA MAY 2025'!C46 -> 45463373 | I35: ='ESFA JUN 2025'!C46 -> 44870845
A36: Cuota extra 2025 | G36: ='ESFA MAY 2025'!C47 -> 7500003 | I36: ='ESFA JUN 2025'!C47 -> 7500003
B37: =SUM(B23:B36) -> 66086679 | C37: =SUM(C23:C36) -> 67552350 | D37: =[5]ESFA!E51 -> 29813541 | E37: =[5]ESFA!C51 -> 25473877 | G37: =[5]ESFA!E51 -> 29813541 | I37: =SUM(I23:I36) -> 53160895
A39: PATRIMONIO
B40: Enero | C40: Febrero | D40: Marzo | E40: Abril | G40: Mayo | I40: Junio | K40: Julio | L40: Agosto
A41: Reserva de ley 675 2001 | B41: ='ESFA feb 2025'!C57 -> 8861215.9 | C41: ='ESFA feb 2025'!E57 -> 8574200.9 | D41: ='ESFA abril 2025'!E55 -> 9148230.1 | E41: ='ESFA abril 2025'!C55 -> 9476606.9 | G41: ='ESFA MAY 2025'!C56 -> 9773964.9 | I41: ='ESFA JUN 2025'!C56 -> 10053730
A43: Resultados del presente ejercicio | B43: ='ESFA feb 2025'!C59 -> 563544.11 | C43: ='ESFA feb 2025'!E59 -> 56589.37 | D43: ='ESFA abril 2025'!E57 -> 595837.69 | E43: ='ESFA abril 2025'!C57 -> 6876070.4 | G43: ='ESFA MAY 2025'!C58 -> 7171827.1 | I43: ='ESFA JUN 2025'!C58 -> 10687867
A45: Excedente- reconocimiento talud | B45: ='ESFA feb 2025'!E58 -> 7100905.5 | C45: ='ESFA feb 2025'!C58 -> 7100905.5 | D45: ='ESFA abril 2025'!E58 -> -49920464 | E45: ='ESFA abril 2025'!C56 -> 0 | G45: ='ESFA MAY 2025'!C59 -> 248452.74 | I45: ='ESFA JUN 2025'!C59 -> 248452.74
E46: =E41+E43+E45 -> 16352677 | G46: =G41+G43+G45 -> 17194245 | I46: =SUM(I41:I45) -> 20990049
B47: =SUM(B41:B45) -> 16525665 | C47: =SUM(C41:C45) -> 15731696 | D47: =SUM(D41:D45) -> -40176396
E50: 45748 | G50: 45778 | I50: 45809
A51: ACTIVO | E51: =E17 -> 45098563 | G51: =G17 -> 79344897 | I51: =I17 -> 82701066
A52: PASIVO | E52: =E37 -> 25473877 | G52: =G37 -> 29813541 | I52: =I37 -> 53160895
A53: PATRIMONIO | E53: =E46 -> 16352677 | G53: =G46 -> 17194245 | I53: =I46 -> 20990049

Sheet GRAF ESTAD RESUL2025

Sheet Sub-Sobre ejec agost 2025
B1: URBANIZACION MONTEVERDI P.H. NIT 900.317.187.5
B3: ESTADO INTEGRAL DE RESULTADOS A 31 DEAGOSTO DE 2025
A5: 1 | B5: 8 | C5: PPTO ANUAL2025 | D5: PTTO.2025 | E5: REAL ENE. | F5: REAL FEB | G5: REAL MARZO | H5: REAL ABR | I5: REAL MAY | J5: REAL JUN | K5: REAL JUL | L5: REAL AGO | M5: REAL SEP | N5: REAL OCT | O5: REAL NOV | P5: REAL DIC | Q5: EJECUTADO ACUMUL. | R5: PTTO. ACUMUL. | S5: SOBRE O SUBEJECUCION | T5: VARIACION
B6: Aseo Y Piscina (Personal) | C6: 33199438 | D6: 2766619.9 | E6: 2766619 | F6: 2766619 | G6: 2766619 | H6: 2766619 | I6: 2827988 | J6: 2766620 | K6: 2766620 | L6: 2766620 | Q6: 22194324 | R6: 22132959 | S6: -61365.12 | T6: -61365.12 | V6: 41701001 | W6: CUOTAS DE ADMINISTRACION | X6: -208149088 | Y6: 0 | Z6: 29735584 | AA6: -237884672
B7: Aseo (Insumos) | C7: 1260000 | D7: 105000 | E7: 143550 | F7: 235199 | G7: 220474 | H7: 175110 | I7: 120400 | J7: 95350 | K7: 115100 | L7: 77500 | Q7: 1182683 | R7: 840000 | S7: -342683 | T7: -342683 | V7: 42 | W7: NO OPERACIONALES | X7: -3520084.6 | Y7: 0 | Z7: 519706.7 | AA7: -4039791.3
B8: Dotacion | C8: 0 | D8: 0 | E8: 0 | F8: 350000 | Q8: 350000 | R8: 0 | S8: -350000 | T8: -350000 | V8: 42104001 | W8: DESCUENTO POR PRONTO PAGO | X8: -1872704 | Y8: 0 | Z8: 262103 | AA8: -2134807
B9: Sistema De Seguridad Prev | C9: 1341006.2 | D9: 111750.52 | E9: 640110 | F9: 111750 | G9: 111750 | H9: 111750 | I9: 111750 | J9: 111750 | K9: 111750 | L9: 111750 | Q9: 1422360 | R9: 894004.16 | S9: -528355.84 | T9: -528355.84 | V9: 42950502 | W9: AJUSTE AL PESO | X9: -755 | Y9: 0 | Z9: 0 | AA9: -755
B10: Reserva Estatutaria 1% Del Ppto (De Ley) | C10: 3533088 | D10: 294424 | E10: 287015 | F10: 287015 | G10: 287015 | H10: 328376 | I10: 282699 | J10: 294424 | K10: 297358 | L10: 297356 | Q10: 2361258 | R10: 2355392 | S10: -5866 | T10: -5866 | V10: 511030 | W10: ASESORIA FINANCIERA | X10: 4275423 | Y10: 534452 | Z10: 0 | AA10: 4809875
B11: Celebraciones -Navidad | C11: 0 | D11: 0 | E11: 0 | F11: 0 | G11: 0 | H11: 0 | I11: 0 | J11: 179214 | K11: 0 | L11: 0 | Q11: 179214 | R11: 0 | S11: -179214 | T11: -179214 | V11: 511515 | W11: A LA PROPIEDAD RAIZ | X11: 1001500 | Y11: 0 | Z11: 0 | AA11: 1001500
B12: Asamblea (Ley) | C12: 0 | D12: 0 | E12: 0 | F12: 0 | G12: 338650 | H12: 0 | I12: 176715 | J12: 0 | K12: 0 | L12: 0 | M12: 0 | N12: 0 | O12: 0 | P12: 0 | Q12: 515365 | R12: 0 | S12: -515365 | T12: -515365 | V12: 51151502 | W12: TASA SEGURIDAD | X12: 1001500 | Y12: 0 | Z12: 0 | AA12: 1001500
B13: Total Convivencia | C13: 0 | D13: 0 | E13: 0 | F13: 0 | G13: 338650 | H13: 0 | I13: 176715 | J13: 179214 | K13: 0 | L13: 0 | M13: 0 | N13: 0 | O13: 0 | P13: 0 | Q13: 694579 | R13: 0 | S13: -694579 | T13: -694579 | V13: 5130 | W13: SEGUROS | X13: 9564823 | Y13: 1443315 | Z13: 0 | AA13: 11008138
B14: Fumigación | C14: 2568001.5 | D14: 214000.12 | E14: 0 | F14: 0 | G14: 595450 | H14: 0 | I14: 781652 | L14: 781652 | Q14: 2158754 | R14: 1712001 | S14: -446753 | T14: -446753 | V14: 51302501 | W14: SEGURO ZONAS COMUNES | X14: 9564823 | Y14: 1443315 | Z14: 0 | AA14: 11008138
B15: Acueducto Y Alcantarillado | C15: 3500000 | D15: 291666.67 | E15: 129706 | F15: 233099 | G15: 303870 | H15: 205744 | I15: 217588 | J15: 249565 | K15: 956190 | L15: 380094 | Q15: 2675856 | R15: 2333333.3 | S15: -342522.67 | T15: -342522.67 | V15: 513505 | W15: ASEO Y VIGILANCIA | X15: 113623094 | Y15: 16176904 | Z15: 0 | AA15: 129799998
B16: Tasa De Aseo | C16: 604000 | D16: 50333.333 | E16: 50100 | F16: 50115 | G16: 56102 | H16: 56070 | I16: 56076 | J16: 55806 | K16: 55760 | L16: 56144 | Q16: 436173 | R16: 402666.67 | S16: -33506.333 | T16: -33506.333 | V16: 51350501 | W16: SERVICIOS DE VIGILANCIA | X16: 93815361 | Y16: 13354140 | Z16: 0 | AA16: 107169501
B17: Telefonía E Internet | C17: 800000 | D17: 66666.667 | E17: 87582 | F17: 100988 | G17: 100988 | H17: 100988 | I17: 100988 | J17: 100988 | K17: 100988 | L17: 100988 | Q17: 794498 | R17: 533333.33 | S17: -261164.67 | T17: -261164.67 | V17: 51350503 | W17: RECOLECCION DE BASURAS | X17: 380029 | Y17: 56144 | Z17: 0 | AA17: 436173
B18: Tasa de seguridad | I18: 472500 | K18: 529000 | L18: 0 | Q18: 1001500 | R18: 0 | T18: -1001500 | V18: 51351501 | W18: SERVICIOS DE ADMINISTRACION | X18: 17966012 | Y18: 2566487 | Z18: 0 | AA18: 20532499
B19: Administración | C19: 30797847 | D19: 2566487.2 | E19: 2343824 | F19: 2343824 | G19: 2343824 | H19: 3235079 | I19: 2566487 | J19: 2566487 | K19: 2566487 | L19: 2566487 | Q19: 20532499 | R19: 20531898 | S19: -601 | T19: -601 | V19: 513521 | W19: SISTEMA SS-SGT | X19: 346700 | Y19: 0 | Z19: 0 | AA19: 346700
B20: Informacion Exogena Y Niff | C20: 534465 | D20: 44538.75 | E20: 0 | F20: 0 | G20: 0 | H20: 0 | I20: 0 | J20: 534565 | K20: 0 | L20: 0 | Q20: 534565 | R20: 356310 | S20: -178255 | T20: -178255 | V20: 513525 | W20: ACUEDUCTO Y ALCANTARILLADO | X20: 2296612 | Y20: 380094 | Z20: 0 | AA20: 2676706
B21: Facturación | C21: 603903 | D21: 50325.25 | E21: 50344 | F21: 50344 | G21: 50344 | H21: 50344 | I21: 50344 | J21: 50344 | K21: 50344 | L21: 50344 | Q21: 402752 | R21: 402602 | S21: -150 | T21: -150 | V21: 51352501 | W21: ACUEDUCTO Y ALCANTARILLADO | X21: 2296612 | Y21: 380094 | Z21: 0 | AA21: 2676706
F22: GABRIELA MUÑOZ MOLINA | V22: 519525 | W22: ELEMENTOS DE ASEO Y CAFETERIA | X22: 1238793 | Y22: 77500 | Z22: 0 | AA22: 1316293
B23: 8 | C23: PPTO ANUAL2025 | D23: PTTO.2025 | E23: REAL ENE. | F23: REAL FEB | G23: REAL MARZO | H23: REAL ABR | I23: REAL MAY | J23: REAL JUN | K23: REAL JUL | L23: REAL AGO | M23: REAL SEP | N23: REAL OCT | O23: REAL NOV | P23: REAL DIC | Q23: EJECUTADO ACUMUL. | R23: PTTO. ACUMUL. | S23: SOBRE O SUBEJECUCION | T23: VARIACION
B24: Zonas Comunes General | C24: 10500000 | D24: 875000 | E24: 1581421 | F24: 0 | G24: 523837 | H24: 338825 | I24: 167100 | J24: 1050763 | K24: 1107390 | L24: 1519560 | Q24: 6288896 | R24: 7000000 | S24: 711104 | T24: 711104 | V24: 519550 | W24: IMPLEMENTACION | X24: 837137 | Y24: 200687 | Z24: 0 | AA24: 1037824
B25: Mantenimento Electrico | C25: 1800000 | D25: 150000 | E25: 229300 | F25: 104000 | G25: 366738 | I25: 6000 | J25: 122000 | K25: 0 | L25: 80000 | Q25: 908038 | R25: 1200000 | S25: 291962 | T25: 291962 | V25: 51955001 | W25: IMPLEMENTACION SS-SSGT | X25: 781887 | Y25: 200687 | Z25: 0 | AA25: 982574
B26: Piscina-Zona Húmeda-Turco | C26: 11900000 | D26: 991666.67 | E26: 823302 | F26: 1301779 | G26: 611281 | H26: 203409 | I26: 984464 | J26: 203409 | K26: 203409 | L26: 801889 | Q26: 5132942 | R26: 7933333.3 | S26: 2800391.3 | T26: 2800391.3 | V26: 51955003 | W26: PEMIRS | X26: 55250 | Y26: 0 | Z26: 0 | AA26: 55250
B27: Puerta Vehicular Y Peatonal | C27: 590000 | D27: 49166.667 | E27: 0 | F27: 140000 | G27: 0 | L27: 140000 | Q27: 280000 | R27: 393333.33 | S27: 113333.33 | T27: 113333.33 | V27: 519595 | W27: OTROS | X27: 692698.88 | Y27: 0 | Z27: 0 | AA27: 692698.88
B28: Gimnasio | C28: 2429980 | D28: 202498.33 | E28: 246330 | F28: 0 | G28: 749700 | I28: 246330 | J28: 0 | K28: 238000 | L28: 0 | Q28: 1480360 | R28: 1619986.7 | S28: 139626.67 | T28: 139626.67 | V28: 51959503 | W28: GASTOS ASAMBLEA | X28: 338650 | Y28: 0 | Z28: 0 | AA28: 338650
B29: Vigilancia Privada | C29: 1.5883039e+08 | D29: 13235866 | E29: 13136493 | F29: 13136493 | G29: 13136494 | H29: 13136494 | I29: 13136494 | J29: 13136493 | K29: 13244869 | L29: 13354140 | Q29: 105417970 | R29: 1.0588693e+08 | S29: 468958.1 | T29: 468958.1 | V29: 519920 | W29: FONDO DE IMPREVISTOS | X29: 2063902 | Y29: 297356 | Z29: 0 | AA29: 2361258
B30: Refuerzo Vigilancia | C30: 3977071 | D30: 331422.58 | F30: 1751531 | Q30: 1751531 | R30: 2651380.7 | T30: 899849.67 | V30: 51992001 | W30: FONDO IMPREV LEY 675 | X30: 2063902 | Y30: 297356 | Z30: 0 | AA30: 2361258
B31: Seguro Zonas Comunes | C31: 17577558 | D31: 1464796.5 | E31: 1357394 | F31: 904930 | G31: 1443315 | H31: 1486277 | I31: 1486277 | J31: 1443315 | K31: 1443315 | L31: 1443315 | Q31: 11008138 | R31: 11718372 | S31: 710234 | T31: 710234 | V31: 53 | W31: NO OPERACIONALES | X31: 1193975.7 | Y31: 206789.6 | Z31: 0 | AA31: 1400765.3
B32: Sistema De Seg.Repuestos | C32: 1950000 | D32: 162500 | E32: 0 | F32: 0 | G32: 0 | I32: 555730 | J32: 142800 | K32: 0 | L32: 0 | Q32: 698530 | R32: 1300000 | T32: 601470 | V32: 530505 | W32: GASTOS BANCARIOS | X32: 1187594.5 | Y32: 206789.6 | Z32: 0 | AA32: 1394384.1
B33: Sg-Sst, Requisto De Ley | C33: 1910000 | D33: 159166.67 | E33: 0 | F33: 0 | G33: 288000 | H33: 50000 | I33: 305387 | K33: 346700 | L33: 200687 | Q33: 1190774 | R33: 1273333.3 | S33: 82559.333 | T33: 82559.333 | V33: 53050501 | W33: COBRO SERVICIOS DE RECAUDO | X33: 658414.54 | Y33: 22193.5 | Z33: 0 | AA33: 680608.04
B34: Extintores (Recarga) | C34: 372000 | D34: 31000 | E34: 0 | F34: 0 | G34: 0 | K34: 0 | L34: 0 | Q34: 0 | R34: 248000 | S34: #REF! | T34: 248000 | V34: 53050502 | W34: COMISION PAGO A PROVEEDORES | X34: 0 | Y34: 83538 | Z34: 0 | AA34: 83538
B35: Planes De Ley Emerg, Trat Datos | C35: 740000 | D35: 61666.667 | F35: 138500 | G35: 0 | L35: 0 | Q35: 138500 | R35: 493333.33 | S35: 354833.33 | T35: 354833.33 | V35: 53050503 | W35: MANEJO SUCURSAL VIRTUAL | X35: 529180 | Y35: 101058.1 | Z35: 0 | AA35: 630238.1
B36: Energía | C36: 38237500 | D36: 3186458.3 | E36: 3189683.9 | F36: 2628727 | G36: 2554892 | H36: 2640861 | I36: 3098024 | J36: 2908845 | K36: 2964954 | L36: 2551875 | Q36: 22537862 | R36: 25491667 | S36: 2953804.8 | T36: 2953804.8
B37: SGIRS Pmirs Ley | C37: 1211856 | D37: 100988 | E37: 0 | F37: 0 | G37: 55250 | H37: 0 | I37: 0 | Q37: 55250 | R37: 807904 | T37: 752654
B38: Corte Cesped Y Mto Jardines Z. Comun | C38: 16250400 | D38: 1354200 | E38: 1354200 | F38: 1354200 | G38: 1354200 | H38: 1354200 | I38: 1354200 | K38: 1354200 | L38: 2279100 | Q38: 10404300 | R38: 10833600 | S38: 429300 | T38: 429300
B39: Contabilidad | C39: 6413421 | D39: 534451.75 | E39: 488080 | F39: 488080 | G39: 627190 | H39: 534352 | I39: 534352 | J39: 534352 | K39: 534452 | L39: 534452 | Q39: 4275310 | R39: 4275614 | S39: 304 | T39: 304
B40: Útiles,Papelería -Comunicación | C40: 200000 | D40: 16666.667 | E40: 0 | F40: 0 | G40: 10000 | H40: 10000 | I40: 0 | J40: 0 | K40: 0 | L40: 0 | Q40: 20000 | R40: 133333.33 | S40: 113333.33 | T40: 113333.33
B41: Cafeteria | C41: 360000 | D41: 30000 | E41: 0 | F41: 0 | G41: 26640 | H41: 4390 | I41: 27030 | J41: 0 | K41: 75550 | L41: 0 | Q41: 133610 | R41: 240000 | S41: 106390 | T41: 106390
B42: Transporte Trámites | C42: 150000 | D42: 12500 | E42: 0 | F42: 0 | G42: 4500 | H42: 0 | I42: 0 | J42: 0 | K42: 0 | L42: 0 | Q42: 4500 | R42: 100000 | S42: 95500 | T42: 95500
B43: Gastos Bancarios | C43: 2700000 | D43: 225000 | E43: 191152.44 | F43: 189522.6 | G43: 196603.1 | H43: 179705.1 | I43: 225057.48 | J43: 101784 | K43: 108924 | L43: 206789.6 | Q43: 1399538.3 | R43: 1800000 | S43: 400461.68 | T43: 400461.68
B44: Ajuste Al Peso | C44: 0 | D44: 0 | E44: 0 | F44: 0 | G44: 1227 | H44: 5 | I44: -1887 | K44: 1 | L44: 1 | Q44: -653 | R44: 0 | S44: #REF! | T44: 653
B47: DECISIONES ASAMBLEA
B48: GASTOS NO PRESUPUESTADOS X DEFINIR TALUD | C48: =-49920464 -> -49920464
B49: DEFICIT PPTAL 2023 | C49: -893269.33
B50: TOTAL A CUBRIR | C50: =SUM(C48:C49) -> -50813733
B51: CUBRIR ASI SEGÚN DECISIÓN ASAMBLEA
B52: CUOTA EXTRA 2022-RECONOCIMIENTO SEGURO | C52: 7425682
B53: CUOTA EXTRA 2023 | C53: 8550122
B54: REINVERSIÓN 2023 | C54: 3837291
B55: CUOTA EXTRA 2024 | C55: 23006464
B56: RESULTADOS DE 2024 | C56: 7994163.1
B57: total disposicion de fondos para cubrir | C57: =SUM(C52:C56) -> 50813722
B60: DECISIONES ASAMBLEA
B61: GASTOS NO PRESUPUESTADOS X DEFINIR TALUD | C61: =-49920464 -> -49920464
B62: DEFICIT PPTAL 2023 | C62: -893269.33
B63: TOTAL A CUBRIR | C63: =SUM(C61:C62) -> -50813733
B64: CUBRIR ASI SEGÚN DECISIÓN ASAMBLEA
B65: CUOTA EXTRA 2022-RECONOCIMIENTO SEGURO | C65: 7425682
B66: CUOTA EXTRA 2023 | C66: 0
B67: REINVERSIÓN 2023 | C67: 3837291
B68: CUOTA EXTRA 2024 | C68: 0
B69: RESULTADOS DE 2024 | C69: 7994163.1
B70: total disposicion de fondos para cubrir | C70: =SUM(C65:C69) -> 19257136
B72: RECIBIDO | C72: 31805050

Sheet Sobre-sub ejecuciones
B1: URBANIZACION MONTEVERDI P.H. NIT 900.317.187.5
B3: ESTADO INTEGRAL DE RESULTADOS A 31 DE ABRIL DE 2025
A5: 12 | B5: 7 | C5: PPTO ANUAL2025 | D5: PTTO.2025 | E5: REAL ENE. | F5: REAL FEB | G5: REAL MARZO | H5: REAL ABR | I5: REAL MAY | J5: REAL JUN | K5: REAL JUL | L5: REAL AGO | M5: REAL SEP | N5: REAL OCT | O5: REAL NOV | P5: REAL DIC | Q5: PTTO. ACUMUL. | R5: EJECUTADO ACUMUL. | S5: SOBRE O SUBEJECUCION | T5: VARIACION
B6: CUOTAS DE ADMINISTRACION | C6: 353308839 | D6: =+C6/12 -> 29442403 | E6: =-287015+28701567 -> 28414552 | F6: 28414552 | G6: 28414552 | H6: =+H8-H7 -> 32509259 | I6: =29735584-I7 -> 29438226 | J6: =+J8-J7 -> 29438226 | K6: ='ESTAD RESUL JULIO 2025'!K6 -> 29438226 | Q6: =+D6*$B$5 -> 2.0609682e+08 | R6: =SUM(E6:P6) -> 206067593 | S6: =+Q6-R6 -> 29229.75 | T6: =+Q6-R6 -> 29229.75
B7: Ing x Fondo imprevistos | C7: 3533088 | D7: =+C7/12 -> 294424 | E7: 287015 | F7: 287015 | G7: 287015 | H7: 328376 | I7: 297358 | J7: 297358 | K7: ='ESTAD RESUL JULIO 2025'!K7 -> 297358 | Q7: =+D7*$B$5 -> 2060968 | R7: =SUM(E7:P7) -> 2081495 | S7: =+Q7-R7 -> -20527 | T7: =+Q7-R7 -> -20527 | AB7: Presupuesto ordinario acumulado
B8: TOTAL INGRESO OPERACIONAL | C8: =+C6+C7 -> 356841927 | D8: =SUM(D6:D7) -> 29736827 | E8: =SUM(E6:E7) -> 28701567 | F8: =SUM(F6:F7) -> 28701567 | G8: =SUM(G6:G7) -> 28701567 | H8: 32837635 | I8: =+I6+I7 -> 29735584 | J8: 29735584 | K8: ='ESTAD RESUL JULIO 2025'!K8 -> 29735584 | L8: 0 | M8: =SUM(M6:M7) -> 0 | N8: =SUM(N6:N7) -> 0 | O8: =SUM(O6:O7) -> 0 | P8: =SUM(P6:P7) -> 0 | Q8: =+D8*$B$5 -> 2.0815779e+08 | R8: =SUM(R6:R7) -> 208149088 | S8: =+Q8-R8 -> 8702.75 | T8: =+Q8-R8 -> 8702.75 | AG8: =281797442-AD10 -> 73639651
B9: Gastos Operacionales
B10: Mantenimiento (Infraestructura) | AB10: Ingresos presupuestados | AD10: =Q8 -> 2.0815779e+08 | AI10: Egresos operacionales presupuestados | AL10: =Q57 -> 2.0815779e+08
B11: Aseo Y Piscina (Personal) | C11: 33199438 | D11: 2766619.9 | E11: 2766619 | F11: 2766619 | G11: 2766619 | H11: 2766619 | I11: 2827988 | J11: 2766620 | K11: 2766620 | Q11: 19366339 | R11: 19427704 | S11: -61364.98 | T11: -61364.98 | U11: Transporte hidrolavadora | AB11: Ingresos ejecutados | AD11: =R8 -> 208149088 | AI11: Egresos operacionales reales | AL11: =R57 -> 1.9956645e+08
B12: Aseo (Insumos) | C12: 1260000 | D12: 105000 | E12: 143550 | F12: 235199 | G12: 220474 | H12: 175110 | I12: 120400 | J12: 95350 | K12: 115100 | Q12: 735000 | R12: 1105183 | S12: -370183 | T12: -370183 | U12: Insumos para recuperar cancha squash | AB12: Ingresos marginales | AD12: =AD10-AD11 -> 8702.75 | AI12: Diferencia | AL12: =AL10-AL11 -> 8591337.3
B13: Zonas Comunes General | C13: 10500000 | D13: 875000 | E13: 1581421 | F13: 0 | G13: 523837 | H13: 338825 | I13: 167100 | J13: 1050763 | K13: 1107390 | Q13: 6125000 | R13: 4769336 | S13: 1355664 | T13: 1355664
B14: Mantenimento Electrico | C14: 1800000 | D14: 150000 | E14: 229300 | F14: 104000 | G14: 366738 | I14: 6000 | J14: 122000 | K14: 0 | Q14: 1050000 | R14: 828038 | S14: 221962 | T14: 221962 | U14: Se ejecuta en la medida que se van necesitando cambiar bombillas
B15: Piscina-Zona Húmeda-Turco | C15: 11900000 | D15: 991666.67 | E15: 823302 | F15: 1301779 | G15: 611281 | H15: 203409 | I15: 984464 | J15: 203409 | K15: 203409 | Q15: 6941666.7 | R15: 4331053 | S15: 2610613.7 | T15: 2610613.7 | U15: Compra de insumos cada 3 meses | AA15: 1 | AI15: 2
B16: Puerta Vehicular Y Peatonal | C16: 590000 | D16: 49166.667 | E16: 0 | F16: 140000 | G16: 0 | K16: 0 | Q16: 344166.67 | R16: 140000 | S16: 204166.67 | T16: 204166.67 | U16: Se realizò mto en agosto
B17: Gimnasio | C17: 2429980 | D17: 202498.33 | E17: 246330 | F17: 0 | G17: 749700 | I17: 246330 | J17: 0 | K17: 238000 | Q17: 1417488.3 | R17: 1480360 | S17: -62871.667 | T17: -62871.667 | U17: cumpliendo
B18: Dotacion | C18: 0 | D18: 0 | E18: 0 | F18: 350000 | K18: 0 | Q18: 0 | R18: 350000 | S18: -350000 | T18: -350000
B19: Total Mantenimiento Y Mejoras | C19: 61679418 | D19: 5139951.5 | E19: 5790522 | F19: 4897597 | G19: 5238649 | H19: 3483963 | I19: 4352282 | J19: 4238142 | K19: 4430519 | L19: 0 | M19: 0 | N19: 0 | O19: 0 | P19: 0 | Q19: 35979661 | R19: 32431674 | S19: 3897986.7 | T19: 3547986.7
B20: Seguridad | D20: 0 | K20: 0
B21: Vigilancia Privada | C21: 1.5883039e+08 | D21: 13235866 | E21: 13136493 | F21: 13136493 | G21: 13136494 | H21: 13136494 | I21: 13136494 | J21: 13136493 | K21: 13244869 | Q21: 92651062 | R21: 92063830 | S21: 587232.09 | T21: 587232.09 | U21: En agosto se inicia otro incremento por disminucion de jornada laboral
B22: Refuerzo Vigilancia | C22: 3977071 | D22: 331422.58 | F22: 1751531 | K22: 0 | Q22: 2319958.1 | R22: 1751531 | T22: 568427.08
B23: Seguro Zonas Comunes | C23: 17577558 | D23: 1464796.5 | E23: 1357394 | F23: 904930 | G23: 1443315 | H23: 1486277 | I23: 1486277 | J23: 1443315 | K23: 1443315 | Q23: 10253576 | R23: 9564823 | S23: 688752.5 | T23: 688752.5 | U23: Se realizò pago total y se amortiza mensulmente
B24: Sistema De Seguridad Prev | C24: 1341006.2 | D24: 111750.52 | E24: 640110 | F24: 111750 | G24: 111750 | H24: 111750 | I24: 111750 | J24: 111750 | K24: 111750 | Q24: 782253.64 | R24: 1310610 | S24: -528356.36 | T24: -528356.36 | U24: Gabriela debe reclasificar el matenimiento correccivo incluido en el preventivo
B25: Sistema De Seg.Repuestos | C25: 1950000 | D25: 162500 | E25: 0 | F25: 0 | G25: 0 | I25: 555730 | J25: 142800 | K25: 0 | Q25: 1137500 | R25: 698530 | T25: 438970
B26: Sg-Sst, Requisto De Ley | C26: 1910000 | D26: 159166.67 | E26: 0 | F26: 0 | G26: 288000 | H26: 50000 | I26: 305387 | K26: 346700 | Q26: 1114166.7 | R26: 990087 | S26: 124079.67 | T26: 124079.67
B27: Extintores (Recarga) | C27: 372000 | D27: 31000 | E27: 0 | F27: 0 | G27: 0 | K27: 0 | Q27: 217000 | R27: 0 | S27: 217000 | T27: 217000
B28: Planes De Ley Emerg, Trat Datos | C28: 740000 | D28: 61666.667 | F28: 138500 | G28: 0 | K28: 0 | Q28: 431666.67 | R28: 138500 | S28: 293166.67 | T28: 293166.67
B29: Reserva Estatutaria 1% Del Ppto (De Ley) | C29: 3533088 | D29: 294424 | E29: 287015 | F29: 287015 | G29: 287015 | H29: 328376 | I29: 282699 | J29: 294424 | K29: 297358 | Q29: 2060968 | R29: 2063902 | S29: -2934 | T29: -2934
B30: Total Riesgos Y Seguridad | C30: 1.9023112e+08 | D30: 15852593 | E30: 15421012 | F30: 16330219 | G30: 15266574 | H30: 15112897 | I30: 15878337 | J30: 15128782 | K30: 15443992 | L30: 0 | M30: 0 | N30: 0 | O30: 0 | P30: 0 | Q30: 1.1096815e+08 | R30: 108581813 | S30: 1378940.6 | T30: 2386337.6
B31: Convivencia | D31: 0 | K31: 0
B32: Celebraciones -Navidad | C32: 0 | D32: 0 | E32: 0 | F32: 0 | G32: 0 | H32: 0 | I32: 0 | J32: 179214 | K32: 0 | Q32: 0 | R32: 179214 | S32: -179214 | T32: -179214 | AA32: 3 | AB32: Seguridad | AC32: =Q30 -> 1.1096815e+08
B33: Asamblea (Ley) | C33: 0 | D33: 0 | E33: 0 | F33: 0 | G33: 338650 | H33: 0 | I33: 176715 | J33: 0 | K33: 0 | L33: 0 | M33: 0 | N33: 0 | O33: 0 | P33: 0 | Q33: 0 | R33: 515365 | S33: -515365 | T33: -515365 | AB33: Seguridad Ejecutada | AC33: =R30 -> 108581813
B34: Total Convivencia | C34: 0 | D34: 0 | E34: 0 | F34: 0 | G34: 338650 | H34: 0 | I34: 176715 | J34: 179214 | K34: 0 | L34: 0 | M34: 0 | N34: 0 | O34: 0 | P34: 0 | Q34: 0 | R34: 694579 | S34: -694579 | T34: -694579 | AB34: Diferencia | AC34: =AC32-AC33 -> 2386337.6
B35: Ambiental | D35: 0 | K35: 0
B36: Fumigación | C36: 2568001.5 | D36: 214000.12 | E36: 0 | F36: 0 | G36: 595450 | H36: 0 | I36: 781652 | K36: 0 | Q36: 1498000.9 | R36: 1377102 | S36: 120898.88 | T36: 120898.88 | AB36: Mantenimiento Ppto | AC36: =Q19 -> 35979661
B37: Energía | C37: 38237500 | D37: 3186458.3 | E37: 3189683.9 | F37: 2628727 | G37: 2554892 | H37: 2640861 | I37: 3098024 | J37: 2908845 | K37: 2964954 | Q37: 22305208 | R37: 19985987 | S37: 2319221.5 | T37: 2319221.5 | AB37: Mantenimiento Ejecutado | AC37: =R19 -> 32431674
B38: Acueducto Y Alcantarillado | C38: 3500000 | D38: 291666.67 | E38: 129706 | F38: 233099 | G38: 303870 | H38: 205744 | I38: 217588 | J38: 249565 | K38: 956190 | Q38: 2041666.7 | R38: 2295762 | S38: -254095.33 | T38: -254095.33 | AB38: Diferencia | AC38: =AC36-AC37 -> 3547986.7
B39: Tasa De Aseo | C39: 604000 | D39: 50333.333 | E39: 50100 | F39: 50115 | G39: 56102 | H39: 56070 | I39: 56076 | J39: 55806 | K39: 55760 | Q39: 352333.33 | R39: 380029 | S39: -27695.667 | T39: -27695.667
B40: SGIRS Pemirs Ley | C40: 1211856 | D40: 100988 | E40: 0 | F40: 0 | G40: 55250 | H40: 0 | I40: 0 | K40: 0 | Q40: 706916 | R40: 55250 | T40: 651666 | AB40: Ambiental Ppto | AC40: =Q44 -> 36850192
B41: Telefonía E Internet | C41: 800000 | D41: 66666.667 | E41: 87582 | F41: 100988 | G41: 100988 | H41: 100988 | I41: 100988 | J41: 100988 | K41: 100988 | Q41: 466666.67 | R41: 693510 | S41: -226843.33 | T41: -226843.33 | AB41: Ambiental Ejecutada | AC41: =R44 -> 33914340
B42: Corte Cesped Y Mto Jardines Z. Comun | C42: 16250400 | D42: 1354200 | E42: 1354200 | F42: 1354200 | G42: 1354200 | H42: 1354200 | I42: 1354200 | K42: 1354200 | Q42: 9479400 | R42: 8125200 | S42: 1354200 | T42: 1354200 | AB42: Diferencia | AC42: =AC40-AC41 -> 2935852
B43: Tasa de seguridad | I43: 472500 | K43: 529000 | Q43: 0 | R43: 1001500 | T43: -1001500
B44: Total Ambiental | C44: 63171758 | D44: 5264313.1 | E44: 4811271.9 | F44: 4367129 | G44: 5020752 | H44: 4357863 | I44: 6081028 | J44: 3315204 | K44: 5961092 | L44: 0 | M44: 0 | N44: 0 | O44: 0 | P44: 0 | Q44: 36850192 | R44: 33914340 | S44: 3285686 | T44: 2935852 | AB44: Administrativos Ppto | AC44: =Q56 -> 24359788
B45: Administrativos | K45: 0 | S45: 0 | AB45: Administrativo Ejectutado | AC45: =R56 -> 23944048
B46: Administración | C46: 30797847 | D46: 2566487.2 | E46: 2343824 | F46: 2343824 | G46: 2343824 | H46: 3235079 | I46: 2566487 | J46: 2566487 | K46: 2566487 | Q46: 17965411 | R46: 17966012 | S46: -601.25 | T46: -601.25 | AB46: Diferencia | AC46: =AC44-AC45 -> 415739.95
B47: Contabilidad | C47: 6413421 | D47: 534451.75 | E47: 488080 | F47: 488080 | G47: 627190 | H47: 534352 | I47: 534352 | J47: 534352 | K47: 534452 | Q47: 3741162.2 | R47: 3740858 | S47: 304.25 | T47: 304.25
B48: Informacion Exogena Y Niff | C48: 534465 | D48: 44538.75 | E48: 0 | F48: 0 | G48: 0 | H48: 0 | I48: 0 | J48: 534565 | K48: 0 | Q48: 311771.25 | R48: 534565 | S48: -222793.75 | T48: -222793.75 | AB48: Convivencia ppto | AC48: =Q33 -> 0
B49: Facturación | C49: 603903 | D49: 50325.25 | E49: 50344 | F49: 50344 | G49: 50344 | H49: 50344 | I49: 50344 | J49: 50344 | K49: 50344 | Q49: 352276.75 | R49: 352408 | S49: -131.25 | T49: -131.25 | AB49: Convivencia Ejec | AC49: =R33 -> 515365
B50: Útiles,Papelería -Comunicación | C50: 200000 | D50: 16666.667 | E50: 0 | F50: 0 | G50: 10000 | H50: 10000 | I50: 0 | J50: 0 | K50: 0 | Q50: 116666.67 | R50: 20000 | S50: 96666.667 | T50: 96666.667
B51: Cafeteria | C51: 360000 | D51: 30000 | E51: 0 | F51: 0 | G51: 26640 | H51: 4390 | I51: 27030 | J51: 0 | K51: 75550 | Q51: 210000 | R51: 133610 | S51: 76390 | T51: 76390 | AQ51: Mto
B52: Transporte Trámites | C52: 150000 | D52: 12500 | E52: 0 | F52: 0 | G52: 4500 | H52: 0 | I52: 0 | J52: 0 | K52: 0 | Q52: 87500 | R52: 4500 | S52: 83000 | T52: 83000
B53: Gastos Bancarios | C53: 2700000 | D53: 225000 | E53: 191152.44 | F53: 189522.6 | G53: 196603.1 | H53: 179705.1 | I53: 225057.48 | J53: 101784 | K53: 108924 | Q53: 1575000 | R53: 1192748.7 | S53: 382251.28 | T53: 382251.28 | AQ53: =Q34 -> 0
B54: Ajuste Al Peso | C54: 0 | D54: 0 | E54: 0 | F54: 0 | G54: 1227 | H54: 5 | I54: -1887 | K54: 1 | Q54: 0 | R54: -654 | S54: 654 | T54: 654 | BG54: ejecutado | BH54: Diferencia
B55: Impuestos Asumidos | C55: 0 | D55: 0 | K55: 0 | Q55: 0 | R55: 0 | S55: 0 | T55: 0 | AQ55: =R34 -> 694579
B56: Total Administrativos | C56: 41759636 | D56: 3479969.7 | E56: 3073400.4 | F56: 3071770.6 | G56: 3260328.1 | H56: 4013875.1 | I56: 3401383.5 | J56: 3787532 | K56: 3335758 | Q56: 24359788 | R56: 23944048 | S56: 415739.95 | T56: 415739.95
B57: Total Egresos Operacionales Mes | C57: 3.5684193e+08 | D57: 29736827 | E57: 29096206 | F57: 28666716 | G57: 29124953 | H57: 26968598 | I57: 29889745 | J57: 26648874 | K57: 29171361 | L57: 0 | M57: 0 | N57: 0 | O57: 0 | P57: 0 | Q57: 2.0815779e+08 | R57: 1.9956645e+08 | S57: 8283774.2 | T57: 8591337.3 | AC57: % ejecución | AH57: Distribución del gasto
K58: ='ESTAD RESUL JULIO 2025'!K58 -> 0 | AA58: Mantenimiento | AC58: =AC37/AC36 -> 0.9013891 | AD58: =R34 -> 694579 | AH58: Mantenimiento | AJ58: =R19/R8 -> 0.15580983
B59: OTROS INGRESOS MARGINALES | C59: =SUM(C60:C64) -> 0 | E59: =SUM(E60:E65) -> 451228.69 | F59: =SUM(F60:F64) -> 472103.34 | G59: =SUM(G60:G64) -> 455679.26 | H59: =SUM(H60:H64) -> 411197.13 | I59: =SUM(I60:I65) -> 713029.05 | J59: =SUM(J60:J65) -> 414671.36 | K59: ='ESTAD RESUL JULIO 2025'!K59 -> 602175.76 | L59: =SUM(L60:L64) -> 0 | M59: =SUM(M60:M64) -> 0 | N59: =SUM(N60:N64) -> 0 | O59: =SUM(O60:O64) -> 0 | P59: =SUM(P60:P64) -> 0 | Q59: =SUM(Q60:Q64) -> 0 | R59: =SUM(R60:R64) -> 3271631.9 | S59: =SUM(S60:S64) -> -3271631.9 | T59: =+R59 -> 3271631.9
B60: Interes de Mora | E60: 69013 | F60: 95407 | G60: 139518 | H60: 92495 | I60: 136086 | J60: 108094 | K60: ='ESTAD RESUL JULIO 2025'!K60 -> 249985 | Q60: 0 | R60: =SUM(E60:P60) -> 890598 | S60: =+Q60-R60 -> -890598 | AA60: Riesgos y Seguridad | AC60: =AC33/AC32 -> 0.97849529 | AH60: Riesgos y Seguridad | AJ60: =R29/R8 -> 0.0099154986
B61: Intereses Financieros | E61: =669.24+123715.45 -> 124384.69 | F61: =52094.04+1011.3 -> 53105.34 | G61: =57021.36+1056.9 -> 58078.26 | H61: =1143+59728.13 -> 60871.13 | I61: 67835.31 | J61: 48746.36 | K61: ='ESTAD RESUL JULIO 2025'!K61 -> 92232.76 | Q61: 0 | R61: =SUM(E61:P61) -> 505253.85 | S61: =+Q61-R61 -> -505253.85
B62: Salon social | F62: 0 | I62: 0 | J62: 0 | K62: ='ESTAD RESUL JULIO 2025'!K62 -> 0 | Q62: 0 | R62: =SUM(E62:P62) -> 0 | S62: =+Q62-R62 -> 0 | AA62: Ambiental | AC62: =AC41/AC40 -> 0.92033008 | AH62: Ambiental | AJ62: =R42/R8 -> 0.039035482
B63: Dto pronto Pago | E63: 257831 | F63: 323591 | G63: 257831 | H63: 257831 | I63: 257831 | J63: 257831 | K63: ='ESTAD RESUL JULIO 2025'!K63 -> 259958 | Q63: 0 | R63: =SUM(E63:P63) -> 1872704 | S63: =+Q63-R63 -> -1872704
B64: Aprovechamientos | G64: 252 | I64: =2321+503 -> 2824 | J64: 0 | K64: ='ESTAD RESUL JULIO 2025'!K64 -> 0 | Q64: 0 | R64: =SUM(E64:P64) -> 3076 | S64: =+Q64-R64 -> -3076
B65: Saldo reclamcion talud | I65: 248452.74 | J65: 0 | K65: ='ESTAD RESUL JULIO 2025'!K65 -> 0 | AA65: Administrativos | AC65: =AC45/AC44 -> 0.98293335 | AH65: Administrativos | AJ65: =R55/R8 -> 0
B66: RESULTADO PRESUPUESTAL MES/AÑO | C66: =+C8-C57 -> -0.21000004 | D66: =+D8-D57 -> -0.017500002 | E66: =+E8-E57+E59 -> 56589.37 | F66: =+F8-F57+F59 -> 506954.74 | G66: =+G8-G57+G59 -> 32293.16 | H66: =+H8-H57+H59 -> 6280234 | I66: =+I8-I57+I59 -> 558867.57 | J66: =+J8-J57+J59 -> 3501381.4 | K66: ='ESTAD RESUL JULIO 2025'!K66 -> 1166398.8 | M66: =+M8-M57+M59 -> 0 | N66: =+N8-N57+N59 -> 0 | O66: =+O8-O57+O59 -> 0 | P66: =+P8-P57+P59 -> 0 | Q66: 0 | R66: =+R8-R57+R59 -> 11854266 | S66: =+S8-S57+S59 -> -11546703 | T66: =+T57-T8+T59 -> 11854266
F67: =SUM(E66:F66) -> 563544.11 | G67: =SUM(E66:G66) -> 595837.27 | H67: =SUM(E66:H66) -> 6876071.3 | I67: =SUM(E66:I66) -> 7434938.9 | AA67: PPTO | AC67: =R56/Q56 -> 0.98293335
I68: =SUM(E66:I66) -> 7434938.9 | J68: =SUM(E66:J66) -> 10936320 | S68: =+R66+S66 -> 307562.96
B69: TANIA MARIA ANGULO | F69: GABRIELA MUÑOZ MOLINA | K69: GABRIELA MUÑOZ MOLINA | R69: -41875790
B70: Administradora | F70: Contadora | K70: Contadora | R70: =+R68-R69 -> 41875790
B73: Asamblea Aprobo Adicional
B74: Seguro Zonas Comunes | C74: 16288728 | D74: 16288728 | E74: =+D74/12 -> 1357394 | F74: 0 | G74: 0
B75: Vigilancia En Vacaciones | C75: 4784604 | D75: 4784604 | E75: =+D75/12 -> 398717 | F75: 1584693 | G75: 0
B76: Sistema De Seguridad Correctivo | C76: 3000000 | D76: 3000000 | E76: =+D76/12 -> 250000 | F76: 0 | G76: 0
B77: Total Agregado En Asamblea | C77: =SUM(C74:C76) -> 24073332 | D77: =SUM(D74:D76) -> 24073332 | E77: =SUM(E74:E76) -> 2006111 | F77: =SUM(F74:F76) -> 1584693 | G77: =SUM(G74:G76) -> 0
B80: ITEM | E80: 45658 | F80: 45689 | G80: 45717 | H80: 45748 | I80: 45778 | J80: 45809 | K80: 45839 | L80: 45870 | M80: 45901 | N80: 45931 | O80: 45962 | P80: 45992
B81: Ingresos operacionales pptados | E81: =E8 -> 28701567 | F81: =F8 -> 28701567 | G81: =G8 -> 28701567 | H81: =H8 -> 32837635 | I81: =I8 -> 29735584 | J81: =J8 -> 29735584 | K81: =K8 -> 29735584
B82: Ingresos operacionales reales | E82: =E81+E83 -> 29152796 | F82: =F81+F83 -> 29173670 | G82: =G81+G83 -> 29157246 | H82: =H81+H83 -> 33248832 | I82: =I81+I83 -> 30448613 | J82: =J81+J83 -> 30150255 | K82: =K81+K83 -> 30337760
B83: Ingresos marginales | E83: =E59 -> 451228.69 | F83: =F59 -> 472103.34 | G83: =G59 -> 455679.26 | H83: =H59 -> 411197.13 | I83: =I59 -> 713029.05 | J83: =J59 -> 414671.36 | K83: =K59 -> 602175.76
B85: Resultado presupuestal | E85: 45658 | F85: 45689 | G85: 45717 | H85: 45748 | I85: 45778 | J85: 45809 | K85: 45839
B86: Egresos presupuestados | E86: =D8 -> 29736827 | F86: =E8 -> 28701567 | G86: =F8 -> 28701567 | H86: =G8 -> 28701567 | I86: =H8 -> 32837635 | J86: =I8 -> 29735584 | K86: =J8 -> 29735584
B87: Egresos operacionales | E87: =E57 -> 29096206 | F87: =F57 -> 28666716 | G87: =G57 -> 29124953 | H87: =H57 -> 26968598 | I87: =I57 -> 29889745 | J87: =J57 -> 26648874 | K87: =K57 -> 29171361
B88: Resultados presupuestal | E88: =E82-E87 -> 56589.37 | F88: =F82-F87 -> 506954.74 | G88: =G82-G87 -> 32293.16 | H88: =H82-H87 -> 6280234 | I88: =I82-I87 -> 558867.57 | J88: =J82-J87 -> 3501381.4 | K88: =K82-K87 -> 1166398.8 | L88: =L82-L87 -> 0 | ... P88: =P82-P87 -> 0
B91: INGRESOS MARGINALES | E91: 45658 | F91: 45689 | G91: 45717 | H91: 45748 | I91: 45778 | J91: 45809 | K91: 45839
B92: Intereses de mora | E92: =E60 -> 69013 | F92: =F60 -> 95407 | G92: =G60 -> 139518 | H92: =H60 -> 92495 | I92: =I60 -> 136086 | J92: =J60 -> 108094 | K92: =K60 -> 249985
B93: Intereses financieros | E93: =E61 -> 124384.69 | F93: =F61 -> 53105.34 | G93: =G61 -> 58078.26 | H93: =H61 -> 60871.13 | I93: =I61 -> 67835.31 | J93: =J61 -> 48746.36 | K93: =K61 -> 92232.76
B94: Descuentos pronto pago | E94: =E63 -> 257831 | F94: =F63 -> 323591 | G94: =G63 -> 257831 | H94: =H63 -> 257831 | I94: =I63 -> 257831 | J94: =J63 -> 257831 | K94: =K63 -> 259958
B95: Aprovechamientos | E95: =E65 -> 0 | F95: =F65 -> 0 | G95: =G65 -> 0 | H95: =H65 -> 0 | I95: =I65 -> 248452.74 | J95: =J65 -> 0 | K95: =K65 -> 0
B96: Saldo indemnizacion talud
E98: 45658 | F98: 45689 | G98: 45717 | H98: 45748 | I98: 45778 | J98: 45809 | K98: 45839
B99: pptoejecutado | E99: =E87 -> 29096206 | F99: =F87 -> 28666716 | G99: =G87 -> 29124953 | H99: =H87 -> 26968598 | I99: =I87 -> 29889745 | J99: =J87 -> 26648874 | K99: =K87 -> 29171361
B100: Ppto aprobado | E100: =E86 -> 29736827 | F100: =F86 -> 28701567 | G100: =G86 -> 28701567 | H100: =H86 -> 28701567 | I100: =I86 -> 32837635 | J100: =J86 -> 29735584 | K100: =K86 -> 29735584 | AB100: Cuota extra anteriores | AC100: =3454978+664608 -> 4119586
B101: minimo | E101: 0.95 | F101: 0.95 | G101: 0.95 | H101: 0.95 | I101: 0.95 | J101: 0.95 | K101: 0.95
B102: Indicador pptal | E102: =E99/E100 -> 0.97845698 | F102: =F99/F100 -> 0.99878573 | G102: =G99/G100 -> 1.0147513 | H102: =H99/H100 -> 0.93962111 | I102: =I99/I100 -> 0.91022832 | J102: =J99/J100 -> 0.89619474 | K102: =K99/K100 -> 0.98102533
B103: maximo | E103: 1.05 | F103: 1.05 | G103: 1.05 | H103: 1.05 | I103: 1.05 | J103: 1.05 | K103: 1.05
AB104: Aprovechamientos | AC104: =Q20
B105: Seguridad ppptada | E105: =D30 -> 15852593 | F105: 15852593 | G105: 15852593 | H105: 15852593 | I105: 15852593 | J105: 15852593 | K105: 15852593
B106: Seguridad Ejecutada | E106: =E30 -> 15421012 | F106: =F30 -> 16330219 | G106: =G30 -> 15266574 | H106: =H30 -> 15112897 | I106: =I30 -> 15878337 | J106: =J30 -> 15128782 | K106: =K30 -> 15443992 | AB106: Cuota extra 2023 | AC106: =5896446 -> 5896446
B107: %ejec Seguridad | E107: =E106/E105 -> 0.97277537 | F107: =F106/F105 -> 1.0301292 | G107: =G106/G105 -> 0.96303324 | H107: =H106/H105 -> 0.95333912 | I107: =I106/I105 -> 1.001624 | J107: =J106/J105 -> 0.95434116 | K107: =K106/K105 -> 0.97422498 | AC107: =SUM(AC90:AC106) -> 10016032
B109: Mantenimiento Ppto | E109: 5139951.5 | F109: 5139951.5 | G109: 5139951.5 | H109: 5139951.5 | I109: 5139951.5 | J109: 5139951.5 | K109: 5139951.5 | AB109: =AU50 -> 0
B110: Mantenimiento Ejecutado | E110: =E19 -> 5790522 | F110: =F19 -> 4897597 | G110: =G19 -> 5238649 | H110: =H19 -> 3483963 | I110: =I19 -> 4352282 | J110: =J19 -> 4238142 | K110: =K19 -> 4430519 | AB110: Cuotas de administración | AJ110: =AH58 -> Mantenimiento
B111: % ejecuc seguuridad | E111: =E110/E109 -> 1.1265713 | F111: =F110/F109 -> 0.95284887 | G111: =G110/G109 -> 1.019202 | H111: =H110/H109 -> 0.67782021 | I111: =I110/I109 -> 0.84675546 | J111: =J110/J109 -> 0.82454902 | K111: =K110/K109 -> 0.86197681 | AJ111: Total mantenimiento
...

Sheet TABLA ESTAD RESUL 2025
B1: URBANIZACION MONTEVERDI P.H. NIT 900.317.187.5
B3: ESTADO INTEGRAL DE RESULTADOS A 31 DE AGOSTO DE 2025
A5: 12 | B5: 8 | C5: PPTO ANUAL2025 | D5: PTTO.2025 | E5: REAL ENE. | F5: REAL FEB | G5: REAL MARZO | H5: REAL ABR | I5: REAL MAY | J5: REAL JUN | K5: REAL JUL | L5: REAL AGO | M5: REAL SEP | N5: REAL OCT | O5: REAL NOV | P5: REAL DIC | Q5: PTTO. ACUMUL. | R5: EJECUTADO ACUMUL. | S5: SOBRE O SUBEJECUCION | T5: VARIACION
B6: CUOTAS DE ADMINISTRACION | C6: 353308839 | D6: =+C6/12 -> 29442403 | E6: =-287015+28701567 -> 28414552 | F6: 28414552 | G6: 28414552 | H6: =+H8-H7 -> 32509259 | I6: =29735584-I7 -> 29438226 | J6: =+J8-J7 -> 29438226 | K6: ='ESTAD RESUL JULIO 2025'!K6 -> 29438226 | L6: ='ESTAD RESULT AGOS 2025'!L6 -> 29438226 | Q6: =+D6*$B$5 -> 235539226 | R6: =SUM(E6:P6) -> 235505819 | S6: =+Q6-R6 -> 33407 | T6: =+Q6-R6 -> 33407
B7: Ing x Fondo imprevistos | C7: 3533088 | D7: =+C7/12 -> 294424 | E7: 287015 | F7: 287015 | G7: 287015 | H7: 328376 | I7: 297358 | J7: 297358 | K7: ='ESTAD RESUL JULIO 2025'!K7 -> 297358 | L7: ='ESTAD RESULT AGOS 2025'!L7 -> 297358 | Q7: =+D7*$B$5 -> 2355392 | R7: =SUM(E7:P7) -> 2378853 | S7: =+Q7-R7 -> -23461 | T7: =+Q7-R7 -> -23461 | AB7: Presupuesto ordinario acumulado
B8: TOTAL INGRESO OPERACIONAL | C8: =+C6+C7 -> 356841927 | D8: =SUM(D6:D7) -> 29736827 | E8: =SUM(E6:E7) -> 28701567 | F8: =SUM(F6:F7) -> 28701567 | G8: =SUM(G6:G7) -> 28701567 | H8: 32837635 | I8: =+I6+I7 -> 29735584 | J8: 29735584 | K8: ='ESTAD RESUL JULIO 2025'!K8 -> 29735584 | L8: ='ESTAD RESULT AGOS 2025'!L8 -> 29735584 | M8: =SUM(M6:M7) -> 0 | N8: =SUM(N6:N7) -> 0 | O8: =SUM(O6:O7) -> 0 | P8: =SUM(P6:P7) -> 0 | Q8: =+D8*$B$5 -> 237894618 | R8: =SUM(R6:R7) -> 237884672 | S8: =+Q8-R8 -> 9946 | T8: =+Q8-R8 -> 9946 | AG8: =281797442-AD10 -> 43902824
B9: Gastos Operacionales
B10: Mantenimiento (Infraestructura) | AB10: Ingresos presupuestados | AD10: =Q8 -> 237894618 | AI10: Egresos operacionales presupuestados | AL10: =Q57 -> 2.3789462e+08
B11: Aseo Y Piscina (Personal) | C11: 33199438 | D11: =+C11/12 -> 2766619.9 | E11: 2766619 | F11: 2766619 | G11: 2766619 | H11: 2766619 | I11: 2827988 | J11: 2766620 | K11: ='ESTAD RESUL JULIO 2025'!K11 -> 2766620 | L11: ='ESTAD RESULT AGOS 2025'!L11 -> 2766620 | Q11: =+D11*$B$5 -> 22132959 | R11: =SUM(E11:P11) -> 22194324 | S11: =+Q11-R11 -> -61365.12 | T11: =+Q11-R11 -> -61365.12 | AB11: Ingresos ejecutados | AD11: =R8 -> 237884672 | AI11: Egresos operacionales reales | AL11: =R57 -> 2.2994275e+08
B12: Aseo (Insumos) | C12: 1260000 | D12: =+C12/12 -> 105000 | E12: 143550 | F12: 235199 | G12: 220474 | H12: 175110 | I12: 120400 | J12: 95350 | K12: ='ESTAD RESUL JULIO 2025'!K12 -> 115100 | L12: ='ESTAD RESULT AGOS 2025'!L12 -> 77500 | Q12: =+D12*$B$5 -> 840000 | R12: =SUM(E12:P12) -> 1182683 | S12: =+Q12-R12 -> -342683 | T12: =+Q12-R12 -> -342683 | AB12: Ingresos marginales | AD12: =AD10-AD11 -> 9946 | AI12: Diferencia | AL12: =AL10-AL11 -> 7951870.9
B13: Zonas Comunes General | C13: 10500000 | D13: =+C13/12 -> 875000 | E13: 1581421 | F13: 0 | G13: =196100+277737+50000 -> 523837 | H13: 338825 | I13: =-111750+278850 -> 167100 | J13: 1050763 | K13: ='ESTAD RESUL JULIO 2025'!K13 -> 1107390 | L13: ='ESTAD RESULT AGOS 2025'!L13 -> 1519560 | Q13: =+D13*$B$5 -> 7000000 | R13: =SUM(E13:P13) -> 6288896 | S13: =+Q13-R13 -> 711104 | T13: =+Q13-R13 -> 711104
B14: Mantenimento Electrico | C14: 1800000 | D14: =+C14/12 -> 150000 | E14: 229300 | F14: 104000 | G14: 366738 | I14: 6000 | J14: 122000 | K14: ='ESTAD RESUL JULIO 2025'!K14 -> 0 | L14: ='ESTAD RESULT AGOS 2025'!L14 -> 80000 | Q14: =+D14*$B$5 -> 1200000 | R14: =SUM(E14:P14) -> 908038 | S14: =+Q14-R14 -> 291962 | T14: =+Q14-R14 -> 291962
B15: Piscina-Zona Húmeda-Turco | C15: 11900000 | D15: =+C15/12 -> 991666.67 | E15: 823302 | F15: 1301779 | G15: 611281 | H15: 203409 | I15: 984464 | J15: 203409 | K15: ='ESTAD RESUL JULIO 2025'!K15 -> 203409 | L15: ='ESTAD RESULT AGOS 2025'!L15 -> 801889 | Q15: =+D15*$B$5 -> 7933333.3 | R15: =SUM(E15:P15) -> 5132942 | S15: =+Q15-R15 -> 2800391.3 | T15: =+Q15-R15 -> 2800391.3 | AA15: 1 | AI15: 2
B16: Puerta Vehicular Y Peatonal | C16: 590000 | D16: =+C16/12 -> 49166.667 | E16: 0 | F16: 140000 | G16: 0 | K16: ='ESTAD RESUL JULIO 2025'!K16 -> 0 | L16: ='ESTAD RESULT AGOS 2025'!L16 -> 140000 | Q16: =+D16*$B$5 -> 393333.33 | R16: =SUM(E16:P16) -> 280000 | S16: =+Q16-R16 -> 113333.33 | T16: =+Q16-R16 -> 113333.33
B17: Gimnasio | C17: 2429980 | D17: =+C17/12 -> 202498.33 | E17: 246330 | F17: 0 | G17: 749700 | I17: 246330 | J17: 0 | K17: ='ESTAD RESUL JULIO 2025'!K17 -> 238000 | L17: ='ESTAD RESULT AGOS 2025'!L17 -> 0 | Q17: =+D17*$B$5 -> 1619986.7 | R17: =SUM(E17:P17) -> 1480360 | S17: =+Q17-R17 -> 139626.67 | T17: =+Q17-R17 -> 139626.67
B18: Dotacion | C18: 0 | D18: =+C18/12 -> 0 | E18: 0 | F18: 350000 | K18: ='ESTAD RESUL JULIO 2025'!K18 -> 0 | L18: ='ESTAD RESULT AGOS 2025'!L18 -> 0 | Q18: =+D18*$B$5 -> 0 | R18: =SUM(E18:P18) -> 350000 | S18: =+Q18-R18 -> -350000 | T18: =+Q18-R18 -> -350000
B19: Total Mantenimiento Y Mejoras | C19: =SUM(C11:C18) -> 61679418 | D19: =SUM(D11:D18) -> 5139951.5 | E19: =SUM(E11:E18) -> 5790522 | F19: =SUM(F11:F18) -> 4897597 | G19: =SUM(G11:G18) -> 5238649 | H19: =SUM(H11:H18) -> 3483963 | I19: =SUM(I11:I18) -> 4352282 | J19: =SUM(J11:J17) -> 4238142 | K19: ='ESTAD RESUL JULIO 2025'!K19 -> 4430519 | L19: =SUM(L11:L17) -> 5385569 | M19: =SUM(M11:M17) -> 0 | N19: =SUM(N11:N17) -> 0 | O19: =SUM(O11:O17) -> 0 | P19: =SUM(P11:P17) -> 0 | Q19: =+D19*$B$5 -> 41119612 | R19: =SUM(R11:R18) -> 37817243 | S19: =SUM(S11:S17) -> 3652369.2 | T19: =+Q19-R19 -> 3302369.2
B20: Seguridad | D20: =+C20/12 -> 0 | K20: ='ESTAD RESUL JULIO 2025'!K20 -> 0
B21: Vigilancia Privada | C21: 1.5883039e+08 | D21: =+C21/12 -> 13235866 | E21: 13136493 | F21: 13136493 | G21: 13136494 | H21: 13136494 | I21: 13136494 | J21: 13136493 | K21: ='ESTAD RESUL JULIO 2025'!K21 -> 13244869 | L21: ='ESTAD RESULT AGOS 2025'!L21 -> 13354140 | Q21: =+D21*$B$5 -> 1.0588693e+08 | R21: =SUM(E21:P21) -> 105417970 | S21: =+Q21-R21 -> 468958.1 | T21: =+Q21-R21 -> 468958.1
B22: Refuerzo Vigilancia | C22: =1751531+2225540 -> 3977071 | D22: =+C22/12 -> 331422.58 | F22: 1751531 | K22: ='ESTAD RESUL JULIO 2025'!K22 -> 0 | L22: ='ESTAD RESULT AGOS 2025'!L22 -> 0 | Q22: =+D22*$B$5 -> 2651380.7 | R22: =SUM(E22:P22) -> 1751531 | T22: =+Q22-R22 -> 899849.67
B23: Seguro Zonas Comunes | C23: 17577558 | D23: =+C23/12 -> 1464796.5 | E23: 1357394 | F23: 904930 | G23: 1443315 | H23: 1486277 | I23: 1486277 | J23: 1443315 | K23: ='ESTAD RESUL JULIO 2025'!K23 -> 1443315 | L23: ='ESTAD RESULT AGOS 2025'!L23 -> 1443315 | Q23: =+D23*$B$5 -> 11718372 | R23: =SUM(E23:P23) -> 11008138 | S23: =+Q23-R23 -> 710234 | T23: =+Q23-R23 -> 710234
B24: Sistema De Seguridad Prev | C24: 1341006.2 | D24: =+C24/12 -> 111750.52 | E24: 640110 | F24: 111750 | G24: 111750 | H24: 111750 | I24: 111750 | J24: 111750 | K24: ='ESTAD RESUL JULIO 2025'!K24 -> 111750 | L24: ='ESTAD RESULT AGOS 2025'!L24 -> 111750 | Q24: =+D24*$B$5 -> 894004.16 | R24: =SUM(E24:P24) -> 1422360 | S24: =+Q24-R24 -> -528355.84 | T24: =+Q24-R24 -> -528355.84
B25: Sistema De Seg.Repuestos | C25: 1950000 | D25: =+C25/12 -> 162500 | E25: 0 | F25: 0 | G25: 0 | I25: 555730 | J25: 142800 | K25: ='ESTAD RESUL JULIO 2025'!K25 -> 0 | L25: ='ESTAD RESULT AGOS 2025'!L25 -> 0 | Q25: =+D25*$B$5 -> 1300000 | R25: =SUM(E25:P25) -> 698530 | T25: =+Q25-R25 -> 601470
B26: Sg-Sst, Requisto De Ley | C26: 1910000 | D26: =+C26/12 -> 159166.67 | E26: 0 | F26: 0 | G26: 288000 | H26: 50000 | I26: 305387 | K26: ='ESTAD RESUL JULIO 2025'!K26 -> 346700 | L26: ='ESTAD RESULT AGOS 2025'!L26 -> 200687 | Q26: =+D26*$B$5 -> 1273333.3 | R26: =SUM(E26:P26) -> 1190774 | S26: =+Q26-R26 -> 82559.333 | T26: =+Q26-R26 -> 82559.333
B27: Extintores (Recarga) | C27: 372000 | D27: =+C27/12 -> 31000 | E27: 0 | F27: 0 | G27: 0 | K27: ='ESTAD RESUL JULIO 2025'!K27 -> 0 | L27: ='ESTAD RESULT AGOS 2025'!L27 -> 0 | Q27: =+D27*$B$5 -> 248000 | R27: =SUM(E27:P27) -> 0 | S27: =+Q27-R27 -> 248000 | T27: =+Q27-R27 -> 248000
B28: Planes De Ley Emerg, Trat Datos | C28: 740000 | D28: =+C28/12 -> 61666.667 | F28: 138500 | G28: 0 | K28: ='ESTAD RESUL JULIO 2025'!K28 -> 0 | L28: ='ESTAD RESULT AGOS 2025'!L28 -> 0 | Q28: =+D28*$B$5 -> 493333.33 | R28: =SUM(E28:P28) -> 138500 | S28: =+Q28-R28 -> 354833.33 | T28: =+Q28-R28 -> 354833.33
B29: Reserva Estatutaria 1% Del Ppto (De Ley) | C29: 3533088 | D29: =+C29/12 -> 294424 | E29: =+E7 -> 287015 | F29: 287015 | G29: 287015 | H29: 328376 | I29: =-14659+297358 -> 282699 | J29: =11725+282699 -> 294424 | K29: ='ESTAD RESUL JULIO 2025'!K29 -> 297358 | L29: ='ESTAD RESULT AGOS 2025'!L29 -> 297356 | Q29: =+D29*$B$5 -> 2355392 | R29: =SUM(E29:P29) -> 2361258 | S29: =+Q29-R29 -> -5866 | T29: =+Q29-R29 -> -5866
B30: Total Riesgos Y Seguridad | C30: =SUM(C21:C29) -> 1.9023112e+08 | D30: =+C30/12 -> 15852593 | E30: =SUM(E21:E29) -> 15421012 | F30: =SUM(F21:F29) -> 16330219 | G30: =SUM(G21:G29) -> 15266574 | H30: =SUM(H21:H29) -> 15112897 | I30: =SUM(I21:I29) -> 15878337 | J30: =SUM(J21:J29) -> 15128782 | K30: ='ESTAD RESUL JULIO 2025'!K30 -> 15443992 | L30: =SUM(L21:L29) -> 15407248 | M30: =SUM(M21:M29) -> 0 | N30: =SUM(N21:N29) -> 0 | O30: =SUM(O21:O29) -> 0 | P30: =SUM(P21:P29) -> 0 | Q30: =+D30*$B$5 -> 1.2682074e+08 | R30: =SUM(R21:R29) -> 123989061 | S30: =SUM(S21:S29) -> 1330362.9 | T30: =+Q30-R30 -> 2831682.6
B31: Convivencia | D31: =+C31/12 -> 0 | K31: ='ESTAD RESUL JULIO 2025'!K31 -> 0 | L31: ='ESTAD RESULT AGOS 2025'!L32 -> 0
B32: Celebraciones -Navidad | C32: 0 | D32: =+C32/12 -> 0 | E32: =+D32/12 -> 0 | F32: 0 | G32: 0 | H32: 0 | I32: 0 | J32: 179214 | K32: ='ESTAD RESUL JULIO 2025'!K32 -> 0 | L32: ='ESTAD RESULT AGOS 2025'!L33 -> 0 | Q32: =+D32*$B$5 -> 0 | R32: =SUM(E32:P32) -> 179214 | S32: =+Q32-R32 -> -179214 | T32: =+Q32-R32 -> -179214 | AA32: 3 | AB32: Seguridad | AC32: =Q30 -> 1.2682074e+08
B33: Asamblea (Ley) | C33: 0 | D33: =+C33/12 -> 0 | E33: =+D33/12 -> 0 | F33: 0 | G33: =46000+17700+274950 -> 338650 | H33: 0 | I33: 176715 | J33: 0 | K33: ='ESTAD RESUL JULIO 2025'!K33 -> 0 | L33: 0 | M33: 0 | N33: 0 | O33: 0 | P33: 0 | Q33: =+D33*$B$5 -> 0 | R33: =SUM(E33:P33) -> 515365 | S33: =+Q33-R33 -> -515365 | T33: =+Q33-R33 -> -515365 | AB33: Seguridad Ejecutada | AC33: =R30 -> 123989061
B34: Total Convivencia | C34: =SUM(C32:C33) -> 0 | D34: =+C34/12 -> 0 | E34: =SUM(E32:E33) -> 0 | F34: =SUM(F32:F33) -> 0 | G34: =SUM(G32:G33) -> 338650 | H34: =SUM(H32:H33) -> 0 | I34: =SUM(I32:I33) -> 176715 | J34: =SUM(J32:J33) -> 179214 | K34: ='ESTAD RESUL JULIO 2025'!K34 -> 0 | L34: =SUM(L32:L33) -> 0 | M34: =SUM(M32:M33) -> 0 | N34: =SUM(N32:N33) -> 0 | O34: =SUM(O32:O33) -> 0 | P34: =SUM(P32:P33) -> 0 | Q34: =SUM(Q32:Q33) -> 0 | R34: =SUM(E34:P34) -> 694579 | S34: =SUM(S32:S33) -> -694579 | T34: =+Q34-R34 -> -694579 | AB34: Diferencia | AC34: =AC32-AC33 -> 2831682.6
B35: Ambiental | D35: =+C35/12 -> 0 | K35: ='ESTAD RESUL JULIO 2025'!K35 -> 0
B36: Fumigación | C36: 2568001.5 | D36: =+C36/12 -> 214000.12 | E36: 0 | F36: 0 | G36: 595450 | H36: 0 | I36: 781652 | K36: ='ESTAD RESUL JULIO 2025'!K36 -> 0 | L36: ='ESTAD RESULT AGOS 2025'!L36 -> 781652 | Q36: =+D36*$B$5 -> 1712001 | R36: =SUM(E36:P36) -> 2158754 | S36: =+Q36-R36 -> -446753 | T36: =+Q36-R36 -> -446753 | AB36: Mantenimiento Ppto | AC36: =Q19 -> 41119612
B37: Energía | C37: =33250000*1.15 -> 38237500 | D37: =+C37/12 -> 3186458.3 | E37: 3189683.9 | F37: 2628727 | G37: 2554892 | H37: 2640861 | I37: 3098024 | J37: 2908845 | K37: ='ESTAD RESUL JULIO 2025'!K37 -> 2964954 | L37: ='ESTAD RESULT AGOS 2025'!L37 -> 2551875 | Q37: =+D37*$B$5 -> 25491667 | R37: =SUM(E37:P37) -> 22537862 | S37: =+Q37-R37 -> 2953804.8 | T37: =+Q37-R37 -> 2953804.8 | AB37: Mantenimiento Ejecutado | AC37: =R19 -> 37817243
B38: Acueducto Y Alcantarillado | C38: 3500000 | D38: =+C38/12 -> 291666.67 | E38: 129706 | F38: 233099 | G38: 303870 | H38: 205744 | I38: 217588 | J38: 249565 | K38: ='ESTAD RESUL JULIO 2025'!K38 -> 956190 | L38: ='ESTAD RESULT AGOS 2025'!L38 -> 380094 | Q38: =+D38*$B$5 -> 2333333.3 | R38: =SUM(E38:P38) -> 2675856 | S38: =+Q38-R38 -> -342522.67 | T38: =+Q38-R38 -> -342522.67 | AB38: Diferencia | AC38: =AC36-AC37 -> 3302369.2
B39: Tasa De Aseo | C39: 604000 | D39: =+C39/12 -> 50333.333 | E39: 50100 | F39: 50115 | G39: 56102 | H39: 56070 | I39: 56076 | J39: 55806 | K39: ='ESTAD RESUL JULIO 2025'!K39 -> 55760 | L39: ='ESTAD RESULT AGOS 2025'!L39 -> 56144 | Q39: =+D39*$B$5 -> 402666.67 | R39: =SUM(E39:P39) -> 436173 | S39: =+Q39-R39 -> -33506.333 | T39: =+Q39-R39 -> -33506.333
B40: SGIRS Pemirs Ley | C40: =100988*12 -> 1211856 | D40: =+C40/12 -> 100988 | E40: 0 | F40: 0 | G40: 55250 | H40: 0 | I40: 0 | K40: ='ESTAD RESUL JULIO 2025'!K40 -> 0 | L40: ='ESTAD RESULT AGOS 2025'!L40 -> 0 | Q40: =+D40*$B$5 -> 807904 | R40: =SUM(E40:P40) -> 55250 | T40: =+Q40-R40 -> 752654 | AB40: Ambiental Ppto | AC40: =Q44 -> 42114505
B41: Telefonía E Internet | C41: 800000 | D41: =+C41/12 -> 66666.667 | E41: 87582 | F41: 100988 | G41: 100988 | H41: 100988 | I41: 100988 | J41: 100988 | K41: ='ESTAD RESUL JULIO 2025'!K41 -> 100988 | L41: ='ESTAD RESULT AGOS 2025'!L41 -> 100988 | Q41: =+D41*$B$5 -> 533333.33 | R41: =SUM(E41:P41) -> 794498 | S41: =+Q41-R41 -> -261164.67 | T41: =+Q41-R41 -> -261164.67 | AB41: Ambiental Ejecutada | AC41: =R44 -> 40064193
B42: Corte cesped y mto jardines Z. Comun | C42: =(1187000+167200)*12 -> 16250400 | D42: =+C42/12 -> 1354200 | E42: 1354200 | F42: 1354200 | G42: 1354200 | H42: 1354200 | I42: 1354200 | K42: ='ESTAD RESUL JULIO 2025'!K42 -> 1354200 | L42: ='ESTAD RESULT AGOS 2025'!L42 -> 2279100 | Q42: =+D42*$B$5 -> 10833600 | R42: =SUM(E42:P42) -> 10404300 | S42: =+Q42-R42 -> 429300 | T42: =+Q42-R42 -> 429300 | AB42: Diferencia | AC42: =AC40-AC41 -> 2050312.1
B43: Tasa de seguridad | I43: 472500 | K43: ='ESTAD RESUL JULIO 2025'!K43 -> 529000 | L43: ='ESTAD RESULT AGOS 2025'!L43 -> 0 | Q43: =+D43*$B$5 -> 0 | R43: =SUM(E43:P43) -> 1001500 | T43: =+Q43-R43 -> -1001500
B44: Total Ambiental | C44: =SUM(C36:C42) -> 63171758 | D44: =+C44/12 -> 5264313.1 | E44: =SUM(E36:E42) -> 4811271.9 | F44: =SUM(F36:F42) -> 4367129 | G44: =SUM(G36:G42) -> 5020752 | H44: =SUM(H36:H42) -> 4357863 | I44: =SUM(I36:I43) -> 6081028 | J44: =SUM(J36:J42) -> 3315204 | K44: ='ESTAD RESUL JULIO 2025'!K44 -> 5961092 | L44: =SUM(L36:L42) -> 6149853 | M44: =SUM(M36:M42) -> 0 | N44: =SUM(N36:N42) -> 0 | O44: =SUM(O36:O42) -> 0 | P44: =SUM(P36:P42) -> 0 | Q44: =+D44*$B$5 -> 42114505 | R44: =SUM(R36:R43) -> 40064193 | S44: =SUM(S36:S42) -> 2299158.1 | T44: =+Q44-R44 -> 2050312.1 | AB44: Administrativos Ppto | AC44: =Q56 -> 27839757
B45: Administrativos | K45: ='ESTAD RESUL JULIO 2025'!K45 -> 0 | S45: =+F45+G45+E45 -> 0 | AB45: Administrativo Ejectutado | AC45: =R56 -> 27377671
B46: Administración | C46: 30797847 | D46: =+C46/12 -> 2566487.2 | E46: 2343824 | F46: 2343824 | G46: 2343824 | H46: 3235079 | I46: 2566487 | J46: 2566487 | K46: ='ESTAD RESUL JULIO 2025'!K46 -> 2566487 | L46: ='ESTAD RESULT AGOS 2025'!L46 -> 2566487 | Q46: =+D46*$B$5 -> 20531898 | R46: =SUM(E46:P46) -> 20532499 | S46: =+Q46-R46 -> -601 | T46: =+Q46-R46 -> -601 | AB46: Diferencia | AC46: =AC44-AC45 -> 462086.01
B47: Contabilidad | C47: 6413421 | D47: =+C47/12 -> 534451.75 | E47: 488080 | F47: 488080 | G47: 627190 | H47: 534352 | I47: 534352 | J47: 534352 | K47: ='ESTAD RESUL JULIO 2025'!K47 -> 534452 | L47: ='ESTAD RESULT AGOS 2025'!L47 -> 534452 | Q47: =+D47*$B$5 -> 4275614 | R47: =SUM(E47:P47) -> 4275310 | S47: =+Q47-R47 -> 304 | T47: =+Q47-R47 -> 304
B48: Informacion Exogena Y Niff | C48: 534465 | D48: =+C48/12 -> 44538.75 | E48: 0 | F48: 0 | G48: 0 | H48: 0 | I48: 0 | J48: 534565 | K48: ='ESTAD RESUL JULIO 2025'!K48 -> 0 | L48: ='ESTAD RESULT AGOS 2025'!K48 -> 0 | Q48: =+D48*$B$5 -> 356310 | R48: =SUM(E48:P48) -> 534565 | S48: =+Q48-R48 -> -178255 | T48: =+Q48-R48 -> -178255 | AB48: Convivencia ppto | AC48: =Q33 -> 0
B49: Facturación | C49: 603903 | D49: =+C49/12 -> 50325.25 | E49: 50344 | F49: 50344 | G49: 50344 | H49: 50344 | I49: 50344 | J49: 50344 | K49: ='ESTAD RESUL JULIO 2025'!K49 -> 50344 | L49: ='ESTAD RESULT AGOS 2025'!L49 -> 50344 | Q49: =+D49*$B$5 -> 402602 | R49: =SUM(E49:P49) -> 402752 | S49: =+Q49-R49 -> -150 | T49: =+Q49-R49 -> -150 | AB49: Convivencia Ejec | AC49: =R33 -> 515365
B50: Útiles,Papelería -Comunicación | C50: 200000 | D50: =+C50/12 -> 16666.667 | E50: 0 | F50: 0 | G50: 10000 | H50: 10000 | I50: 0 | J50: 0 | K50: ='ESTAD RESUL JULIO 2025'!K50 -> 0 | L50: ='ESTAD RESULT AGOS 2025'!L50 -> 0 | Q50: =+D50*$B$5 -> 133333.33 | R50: =SUM(E50:P50) -> 20000 | S50: =+Q50-R50 -> 113333.33 | T50: =+Q50-R50 -> 113333.33
B51: Cafeteria | C51: 360000 | D51: =+C51/12 -> 30000 | E51: 0 | F51: 0 | G51: 26640 | H51: 4390 | I51: 27030 | J51: 0 | K51: ='ESTAD RESUL JULIO 2025'!K51 -> 75550 | L51: ='ESTAD RESULT AGOS 2025'!K51 -> 75550 | Q51: =+D51*$B$5 -> 240000 | R51: =SUM(E51:P51) -> 209160 | S51: =+Q51-R51 -> 30840 | T51: =+Q51-R51 -> 30840 | AQ51: Mto
B52: Transporte Trámites | C52: 150000 | D52: =+C52/12 -> 12500 | E52: 0 | F52: 0 | G52: 4500 | H52: 0 | I52: 0 | J52: 0 | K52: ='ESTAD RESUL JULIO 2025'!K52 -> 0 | L52: ='ESTAD RESULT AGOS 2025'!L52 -> 0 | Q52: =+D52*$B$5 -> 100000 | R52: =SUM(E52:P52) -> 4500 | S52: =+Q52-R52 -> 95500 | T52: =+Q52-R52 -> 95500
B53: Gastos Bancarios | C53: 2700000 | D53: =+C53/12 -> 225000 | E53: 191152.44 | F53: 189522.6 | G53: 196603.1 | H53: 179705.1 | I53: 225057.48 | J53: 101784 | K53: ='ESTAD RESUL JULIO 2025'!K53 -> 108924 | L53: ='ESTAD RESULT AGOS 2025'!L53 -> 206789.6 | Q53: =+D53*$B$5 -> 1800000 | R53: =SUM(E53:P53) -> 1399538.3 | S53: =+Q53-R53 -> 400461.68 | T53: =+Q53-R53 -> 400461.68 | AQ53: =Q34 -> 0
B54: Ajuste Al Peso | C54: 0 | D54: =+C54/12 -> 0 | E54: 0 | F54: 0 | G54: 1227 | H54: 5 | I54: -1887 | K54: ='ESTAD RESUL JULIO 2025'!K54 -> 1 | L54: ='ESTAD RESULT AGOS 2025'!L54 -> 1 | Q54: =+D54*$B$5 -> 0 | R54: =SUM(E54:P54) -> -653 | S54: =+Q54-R54 -> 653 | T54: =+Q54-R54 -> 653 | BG54: ejecutado | BH54: Diferencia
B55: Impuestos Asumidos | C55: 0 | D55: =+C55/12 -> 0 | K55: ='ESTAD RESUL JULIO 2025'!K55 -> 0 | Q55: =+D55*$B$5 -> 0 | R55: =SUM(E55:P55) -> 0 | S55: =+Q55-R55 -> 0 | T55: =+Q55-R55 -> 0 | AQ55: =R34 -> 694579
B56: Total Administrativos | C56: =SUM(C46:C55) -> 41759636 | D56: =SUM(D46:D55) -> 3479969.7 | E56: =SUM(E46:E55) -> 3073400.4 | F56: =SUM(F46:F55) -> 3071770.6 | G56: =SUM(G46:G55) -> 3260328.1 | H56: =SUM(H46:H55) -> 4013875.1 | I56: =SUM(I46:I55) -> 3401383.5 | J56: =SUM(J46:J55) -> 3787532 | K56: ='ESTAD RESUL JULIO 2025'!K56 -> 3335758 | L56: ='ESTAD RESULT AGOS 2025'!L56 -> 3358073.6 | Q56: =+D56*$B$5 -> 27839757 | R56: =SUM(R46:R55) -> 27377671 | S56: =SUM(S46:S55) -> 462086.01 | T56: =+Q56-R56 -> 462086.01
B57: Total Egresos Operacionales Mes | C57: =+C56+C44+C30+C34+C19 -> 3.5684193e+08 | D57: =+D56+D44+D30+D19 -> 29736827 | E57: =+E56+E44+E30+E34+E19 -> 29096206 | F57: =+F56+F44+F30+F34+F19 -> 28666716 | G57: =+G56+G44+G30+G34+G19 -> 29124953 | H57: =+H56+H44+H30+H34+H19 -> 26968598 | I57: =+I56+I44+I30+I34+I19 -> 29889745 | J57: =+J56+J44+J30+J34+J19 -> 26648874 | K57: ='ESTAD RESUL JULIO 2025'!K57 -> 29171361 | L57: =+L56+L44+L30+L34+L19 -> 30300744 | M57: =+M56+M44+M30+M34+M19 -> 0 | N57: =+N56+N44+N30+N34+N19 -> 0 | O57: =+O56+O44+O30+O34+O19 -> 0 | P57: =+P56+P44+P30+P34+P19 -> 0 | Q57: =+D57*$B$5 -> 2.3789462e+08 | R57: =+R56+R44+R30+R34+R19 -> 2.2994275e+08 | S57: =+S56+S44+S30+S34+S19 -> 7049397.3 | T57: =+T56+T44+T30+T34+T19 -> 7951870.9 | AC57: % ejecución | AH57: Distribución del gasto
K58: ='ESTAD RESUL JULIO 2025'!K58 -> 0 | AA58: Mantenimiento | AC58: =AC37/AC36 -> 0.91968871 | AD58: =R34 -> 694579 | AH58: Mantenimiento | AJ58: =R19/R8 -> 0.15897301
B59: OTROS INGRESOS MARGINALES | C59: =SUM(C60:C64) -> 0 | E59: =SUM(E60:E65) -> 451228.69 | F59: =SUM(F60:F64) -> 472103.34 | G59: =SUM(G60:G64) -> 455679.26 | H59: =SUM(H60:H64) -> 411197.13 | I59: =SUM(I60:I65) -> 713029.05 | J59: =SUM(J60:J65) -> 414671.36 | K59: ='ESTAD RESUL JULIO 2025'!K59 -> 602175.76 | L59: =SUM(L60:L64) -> 519706.7 | M59: =SUM(M60:M64) -> 0 | N59: =SUM(N60:N64) -> 0 | O59: =SUM(O60:O64) -> 0 | P59: =SUM(P60:P64) -> 0 | Q59: =SUM(Q60:Q64) -> 0 | R59: =SUM(R60:R64) -> 3791338.5 | S59: =SUM(S60:S64) -> -3791338.5 | T59: =+R59 -> 3791338.5
B60: Interes de Mora | E60: 69013 | F60: 95407 | G60: 139518 | H60: 92495 | I60: 136086 | J60: 108094 | K60: ='ESTAD RESUL JULIO 2025'!K60 -> 249985 | L60: ='ESTAD RESULT AGOS 2025'!L60 -> 188163 | Q60: 0 | R60: =SUM(E60:P60) -> 1078761 | S60: =+Q60-R60 -> -1078761 | AA60: Riesgos y Seguridad | AC60: =AC33/AC32 -> 0.97767177 | AH60: Riesgos y Seguridad | AJ60: =R29/R8 -> 0.009926062
B61: Intereses Financieros | E61: =669.24+123715.45 -> 124384.69 | F61: =52094.04+1011.3 -> 53105.34 | G61: =57021.36+1056.9 -> 58078.26 | H61: =1143+59728.13 -> 60871.13 | I61: 67835.31 | J61: 48746.36 | K61: ='ESTAD RESUL JULIO 2025'!K61 -> 92232.76 | L61: ='ESTAD RESULT AGOS 2025'!L61 -> 69440.7 | Q61: 0 | R61: =SUM(E61:P61) -> 574694.55 | S61: =+Q61-R61 -> -574694.55
B62: Salon social | F62: 0 | I62: 0 | J62: 0 | K62: ='ESTAD RESUL JULIO 2025'!K62 -> 0 | Q62: 0 | R62: =SUM(E62:P62) -> 0 | S62: =+Q62-R62 -> 0 | AA62: Ambiental | AC62: =AC41/AC40 -> 0.95131577 | AH62: Ambiental | AJ62: =R42/R8 -> 0.04373674
B63: Dto pronto Pago | E63: 257831 | F63: 323591 | G63: 257831 | H63: 257831 | I63: 257831 | J63: 257831 | K63: ='ESTAD RESUL JULIO 2025'!K63 -> 259958 | L63: ='ESTAD RESULT AGOS 2025'!L63 -> 262103 | Q63: 0 | R63: =SUM(E63:P63) -> 2134807 | S63: =+Q63-R63 -> -2134807
B64: Aprovechamientos | G64: 252 | I64: =2321+503 -> 2824 | J64: 0 | K64: ='ESTAD RESUL JULIO 2025'!K64 -> 0 | Q64: 0 | R64: =SUM(E64:P64) -> 3076 | S64: =+Q64-R64 -> -3076 | AA64: Administrativos | AC64: =AC45/AC44 -> 0.98340194
B65: Saldo reclamcion talud | I65: 248452.74 | J65: 0 | K65: ='ESTAD RESUL JULIO 2025'!K65 -> 0 | AH65: Administrativos | AJ65: =R55/R8 -> 0
B66: RESULTADO PRESUPUESTAL MES/AÑO | C66: =+C8-C57 -> -0.21000004 | D66: =+D8-D57 -> -0.017500002 | E66: =+E8-E57+E59 -> 56589.37 | F66: =+F8-F57+F59 -> 506954.74 | G66: =+G8-G57+G59 -> 32293.16 | H66: =+H8-H57+H59 -> 6280234 | I66: =+I8-I57+I59 -> 558867.57 | J66: =+J8-J57+J59 -> 3501381.4 | K66: ='ESTAD RESUL JULIO 2025'!K66 -> 1166398.8 | L66: ='ESTAD RESULT AGOS 2025'!L66 -> -45452.9 | M66: =+M8-M57+M59 -> 0 | N66: =+N8-N57+N59 -> 0 | O66: =+O8-O57+O59 -> 0 | P66: =+P8-P57+P59 -> 0 | Q66: 0 | R66: =+R8-R57+R59 -> 11733263 | S66: =+S8-S57+S59 -> -10830790 | T66: =+T57-T8+T59 -> 11733263 | AA66: PPTO acumulado | AC66: =R56/Q56 -> 0.98340194
F67: =SUM(E66:F66) -> 563544.11 | G67: =SUM(E66:G66) -> 595837.27 | H67: =SUM(E66:H66) -> 6876071.3 | I67: =SUM(E66:I66) -> 7434938.9
I68: =SUM(E66:I66) -> 7434938.9 | J68: =SUM(E66:J66) -> 10936320 | S68: =+R66+S66 -> 902473.53
B69: TANIA MARIA ANGULO | F69: GABRIELA MUÑOZ MOLINA | K69: GABRIELA MUÑOZ MOLINA | R69: -41875790
B70: Administradora | F70: Contadora | K70: Contadora | R70: =+R68-R69 -> 41875790
B73: Asamblea Aprobo Adicional
B74: Seguro Zonas Comunes | C74: 16288728 | D74: 16288728 | E74: =+D74/12 -> 1357394 | F74: 0 | G74: 0
B75: Vigilancia En Vacaciones | C75: 4784604 | D75: 4784604 | E75: =+D75/12 -> 398717 | F75: 1584693 | G75: 0
B76: Sistema De Seguridad Correctivo | C76: 3000000 | D76: 3000000 | E76: =+D76/12 -> 250000 | F76: 0 | G76: 0
B77: Total Agregado En Asamblea | C77: =SUM(C74:C76) -> 24073332 | D77: =SUM(D74:D76) -> 24073332 | E77: =SUM(E74:E76) -> 2006111 | F77: =SUM(F74:F76) -> 1584693 | G77: =SUM(G74:G76) -> 0
B80: ITEM | E80: 45658 | F80: 45689 | G80: 45717 | H80: 45748 | I80: 45778 | J80: 45809 | K80: 45839 | L80: 45870 | M80: 45901 | N80: 45931 | O80: 45962 | P80: 45992
B81: Ingresos operacionales pptados | E81: =E8 -> 28701567 | F81: =F8 -> 28701567 | G81: =G8 -> 28701567 | H81: =H8 -> 32837635 | I81: =I8 -> 29735584 | J81: =J8 -> 29735584 | K81: =K8 -> 29735584 | L81: =L8 -> 29735584
B82: Ingresos operacionales reales | E82: =E81+E83 -> 29152796 | F82: =F81+F83 -> 29173670 | G82: =G81+G83 -> 29157246 | H82: =H81+H83 -> 33248832 | I82: =I81+I83 -> 30448613 | J82: =J81+J83 -> 30150255 | K82: =K81+K83 -> 30337760 | L82: =L81+L83 -> 30255291
B83: Ingresos marginales | E83: =E59 -> 451228.69 | F83: =F59 -> 472103.34 | G83: =G59 -> 455679.26 | H83: =H59 -> 411197.13 | I83: =I59 -> 713029.05 | J83: =J59 -> 414671.36 | K83: =K59 -> 602175.76 | L83: =L59 -> 519706.7
B85: Resultado presupuestal | E85: 45658 | F85: 45689 | G85: 45717 | H85: 45748 | I85: 45778 | J85: 45809 | K85: 45839 | L85: 45870
B86: Egresos presupuestados | E86: =D8 -> 29736827 | F86: =E8 -> 28701567 | G86: =F8 -> 28701567 | H86: =G8 -> 28701567 | I86: =H8 -> 32837635 | J86: =I8 -> 29735584 | K86: =J8 -> 29735584 | L86: =K8 -> 29735584
B87: Egresos operacionales | E87: =E57 -> 29096206 | F87: =F57 -> 28666716 | G87: =G57 -> 29124953 | H87: =H57 -> 26968598 | I87: =I57 -> 29889745 | J87: =J57 -> 26648874 | K87: =K57 -> 29171361 | L87: =L57 -> 30300744
B88: Resultados presupuestal | E88: =E82-E87 -> 56589.37 | F88: =F82-F87 -> 506954.74 | G88: =G82-G87 -> 32293.16 | H88: =H82-H87 -> 6280234 | I88: =I82-I87 -> 558867.57 | J88: =J82-J87 -> 3501381.4 | K88: =K82-K87 -> 1166398.8 | L88: =L82-L87 -> -45452.9 | ... P88: =P82-P87 -> 0
B91: INGRESOS MARGINALES | E91: 45658 | F91: 45689 | G91: 45717 | H91: 45748 | I91: 45778 | J91: 45809 | K91: 45839 | L91: 45870
B92: Intereses de mora | E92: =E60 -> 69013 | F92: =F60 -> 95407 | G92: =G60 -> 139518 | H92: =H60 -> 92495 | I92: =I60 -> 136086 | J92: =J60 -> 108094 | K92: =K60 -> 249985 | L92: =L60 -> 188163
B93: Intereses financieros | E93: =E61 -> 124384.69 | F93: =F61 -> 53105.34 | G93: =G61 -> 58078.26 | H93: =H61 -> 60871.13 | I93: =I61 -> 67835.31 | J93: =J61 -> 48746.36 | K93: =K61 -> 92232.76 | L93: =L61 -> 69440.7
B94: Descuentos pronto pago | E94: =E63 -> 257831 | F94: =F63 -> 323591 | G94: =G63 -> 257831 | H94: =H63 -> 257831 | I94: =I63 -> 257831 | J94: =J63 -> 257831 | K94: =K63 -> 259958 | L94: =L63 -> 262103
B95: Aprovechamientos | E95: =E65 -> 0 | F95: =F65 -> 0 | G95: =G65 -> 0 | H95: =H65 -> 0 | I95: =I65 -> 248452.74 | J95: =J65 -> 0 | K95: =K65 -> 0 | L95: =L65 -> 0
B96: Saldo indemnizacion talud
E98: 45658 | F98: 45689 | G98: 45717 | H98: 45748 | I98: 45778 | J98: 45809 | K98: 45839 | L98: 45870
B99: pptoejecutado | E99: =E87 -> 29096206 | F99: =F87 -> 28666716 | G99: =G87 -> 29124953 | H99: =H87 -> 26968598 | I99: =I87 -> 29889745 | J99: =J87 -> 26648874 | K99: =K87 -> 29171361 | L99: =L87 -> 30300744
B100: Ppto aprobado | E100: =E86 -> 29736827 | F100: =F86 -> 28701567 | G100: =G86 -> 28701567 | H100: =H86 -> 28701567 | I100: =I86 -> 32837635 | J100: =J86 -> 29735584 | K100: =K86 -> 29735584 | L100: =L86 -> 29735584 | AB100: Cuota extra anteriores | AC100: =3454978+664608 -> 4119586
B101: minimo | E101: 0.95 | F101: 0.95 | G101: 0.95 | H101: 0.95 | I101: 0.95 | J101: 0.95 | K101: 0.95 | L101: 0.95
B102: Indicador pptal | E102: =E99/E100 -> 0.97845698 | F102: =F99/F100 -> 0.99878573 | G102: =G99/G100 -> 1.0147513 | H102: =H99/H100 -> 0.93962111 | I102: =I99/I100 -> 0.91022832 | J102: =J99/J100 -> 0.89619474 | K102: =K99/K100 -> 0.98102533 | L102: =L99/L100 -> 1.0190062
B103: maximo | E103: 1.05 | F103: 1.05 | G103: 1.05 | H103: 1.05 | I103: 1.05 | J103: 1.05 | K103: 1.05 | L103: 1.05
AB104: Aprovechamientos | AC104: =Q20
B105: Seguridad ppptada | E105: =D30 -> 15852593 | F105: 15852593 | G105: 15852593 | H105: 15852593 | I105: 15852593 | J105: 15852593 | K105: 15852593 | L105: =K105 -> 15852593
B106: Seguridad Ejecutada | E106: =E30 -> 15421012 | F106: =F30 -> 16330219 | G106: =G30 -> 15266574 | H106: =H30 -> 15112897 | I106: =I30 -> 15878337 | J106: =J30 -> 15128782 | K106: =K30 -> 15443992 | L106: =L30 -> 15407248 | AB106: Cuota extra 2023 | AC106: =5896446 -> 5896446
B107: %ejec Seguridad | E107: =E106/E105 -> 0.97277537 | F107: =F106/F105 -> 1.0301292 | G107: =G106/G105 -> 0.96303324 | H107: =H106/H105 -> 0.95333912 | I107: =I106/I105 -> 1.001624 | J107: =J106/J105 -> 0.95434116 | K107: =K106/K105 -> 0.97422498 | L107: =L106/L105 -> 0.97190712 | AC107: =SUM(AC90:AC106) -> 10016032
B109: Mantenimiento Ppto | E109: 5139951.5 | F109: 5139951.5 | G109: 5139951.5 | H109: 5139951.5 | I109: 5139951.5 | J109: 5139951.5 | K109: 5139951.5 | L109: =K109 -> 5139951.5 | AB109: =AU50 -> 0
B110: Mantenimiento Ejecutado | E110: =E19 -> 5790522 | F110: =F19 -> 4897597 | G110: =G19 -> 5238649 | H110: =H19 -> 3483963 | I110: =I19 -> 4352282 | J110: =J19 -> 4238142 | K110: =K19 -> 4430519 | L110: =L19 -> 5385569 | AB110: Cuotas de administración | AJ110: =AH58 -> Mantenimiento
B111: % ejecuc seguuridad | E111: =E110/E109 -> 1.1265713 | F111: =F110/F109 -> 0.95284887 | G111: =G110/G109 -> 1.019202 | H111: =H110/H109 -> 0.67782021 | I111: =I110/I109 -> 0.84675546 | J111: =J110/J109 -> 0.82454902 | K111: =K110/K109 -> 0.86197681 | L111: =L110/L109 -> 1.047786 | AJ111: Total mantenimiento
...

Sheet ESTAD RESULT AGOS 2025
B1: URBANIZACION MONTEVERDI P.H. NIT 900.317.187.5
B3: ESTADO INTEGRAL DE RESULTADOS A 31 DEAGOSTO DE 2025
A5: 1 | B5: 8 | C5: PPTO ANUAL2025 | D5: PTTO.2025 | E5: REAL ENE. | F5: REAL FEB | G5: REAL MARZO | H5: REAL ABR | I5: REAL MAY | J5: REAL JUN | K5: REAL JUL | L5: REAL AGO | M5: REAL SEP | N5: REAL OCT | O5: REAL NOV | P5: REAL DIC | Q5: EJECUTADO ACUMUL. | R5: PTTO. ACUMUL. | S5: SOBRE O SUBEJECUCION | T5: VARIACION
B6: CUOTAS DE ADMINISTRACION | C6: 353308839 | D6: =+C6/12 -> 29442403 | E6: =-287015+28701567 -> 28414552 | F6: 28414552 | G6: 28414552 | H6: =+H8-H7 -> 32509259 | I6: =29735584-I7 -> 29438226 | J6: =+J8-J7 -> 29438226 | K6: =+K8-K7 -> 29438226 | L6: =+Z11-L7 -> 29438226 | Q6: =SUM(E6:P6) -> 235505819 | R6: =+D6*$B$5 -> 235539226 | S6: =+R6-Q6 -> 33407 | T6: =+R6-Q6 -> 33407
B7: Ing x Fondo imprevistos | C7: 3533088 | D7: =+C7/12 -> 294424 | E7: 287015 | F7: 287015 | G7: 287015 | H7: 328376 | I7: 297358 | J7: 297358 | K7: 297358 | L7: 297358 | Q7: =SUM(E7:P7) -> 2378853 | R7: =+D7*$B$5 -> 2355392 | S7: =+R7-Q7 -> -23461 | T7: =+R7-Q7 -> -23461 | V7: 4 | W7: INGRESOS | X7: -2.1166917e+08 | Y7: 0 | Z7: 30255291 | AA7: -2.4192446e+08
B8: TOTAL INGRESO OPERACIONAL | C8: =+C6+C7 -> 356841927 | D8: =SUM(D6:D7) -> 29736827 | E8: =SUM(E6:E7) -> 28701567 | F8: =SUM(F6:F7) -> 28701567 | G8: =SUM(G6:G7) -> 28701567 | H8: 32837635 | I8: =+I6+I7 -> 29735584 | J8: 29735584 | K8: 29735584 | L8: 29735584 | M8: =SUM(M6:M7) -> 0 | N8: =SUM(N6:N7) -> 0 | O8: =SUM(O6:O7) -> 0 | P8: =SUM(P6:P7) -> 0 | Q8: =SUM(Q6:Q7) -> 237884672 | R8: =+D8*$B$5 -> 237894618 | S8: =+R8-Q8 -> 9946 | T8: =+R8-Q8 -> 9946 | V8: 41 | W8: OPERACIONALES | X8: -208149088 | Y8: 0 | Z8: 29735584 | AA8: -237884672
B9: Gastos Operacionales | V9: 4170 | W9: ACTIV SERVIC COMUNIT SOC Y PER | X9: -208149088 | Y9: 0 | Z9: 29735584 | AA9: -237884672
B10: Mantenimiento (Infraestructura) | V10: 417010 | W10: ACTIVIDADES DE ASOCIACION | X10: -208149088 | Y10: 0 | Z10: 29735584 | AA10: -237884672
B11: Aseo Y Piscina (Personal) | C11: 33199438 | D11: =+C11/12 -> 2766619.9 | E11: 2766619 | F11: 2766619 | G11: 2766619 | H11: 2766619 | I11: 2827988 | J11: 2766620 | K11: 2766620 | L11: 2766620 | Q11: =SUM(E11:P11) -> 22194324 | R11: =+D11*$B$5 -> 22132959 | S11: =+R11-Q11 -> -61365.12 | T11: =+R11-Q11 -> -61365.12 | V11: 41701001 | W11: CUOTAS DE ADMINISTRACION | X11: -208149088 | Y11: 0 | Z11: 29735584 | AA11: -237884672
B12: Aseo (Insumos) | C12: 1260000 | D12: =+C12/12 -> 105000 | E12: 143550 | F12: 235199 | G12: 220474 | H12: 175110 | I12: 120400 | J12: 95350 | K12: 115100 | L12: =+Y69 -> 77500 | Q12: =SUM(E12:P12) -> 1182683 | R12: =+D12*$B$5 -> 840000 | S12: =+R12-Q12 -> -342683 | T12: =+R12-Q12 -> -342683 | V12: 42 | W12: NO OPERACIONALES | X12: -3520084.6 | Y12: 0 | Z12: 519706.7 | AA12: -4039791.3
B13: Zonas Comunes General | C13: 10500000 | D13: =+C13/12 -> 875000 | E13: 1581421 | F13: 0 | G13: =196100+277737+50000 -> 523837 | H13: 338825 | I13: =-111750+278850 -> 167100 | J13: 1050763 | K13: 1107390 | L13: =+Y58 -> 1519560 | Q13: =SUM(E13:P13) -> 6288896 | R13: =+D13*$B$5 -> 7000000 | S13: =+R13-Q13 -> 711104 | T13: =+R13-Q13 -> 711104 | V13: 4210 | W13: FINANCIEROS | X13: -3268555.9 | Y13: 0 | Z13: 519706.7 | AA13: -3788262.5 | AB13: =+Z12-L59 -> 0
B14: Mantenimento Electrico | C14: 1800000 | D14: =+C14/12 -> 150000 | E14: 229300 | F14: 104000 | G14: 366738 | I14: 6000 | J14: 122000 | K14: 0 | L14: =+Y60 -> 80000 | Q14: =SUM(E14:P14) -> 908038 | R14: =+D14*$B$5 -> 1200000 | S14: =+R14-Q14 -> 291962 | T14: =+R14-Q14 -> 291962 | V14: 421005 | W14: INTERESES | X14: -505253.85 | Y14: 0 | Z14: 69440.7 | AA14: -574694.55
B15: Piscina-Zona Húmeda-Turco | C15: 11900000 | D15: =+C15/12 -> 991666.67 | E15: 823302 | F15: 1301779 | G15: 611281 | H15: 203409 | I15: 984464 | J15: 203409 | K15: 203409 | L15: =+Y63 -> 801889 | Q15: =SUM(E15:P15) -> 5132942 | R15: =+D15*$B$5 -> 7933333.3 | S15: =+R15-Q15 -> 2800391.3 | T15: =+R15-Q15 -> 2800391.3 | V15: 42100501 | W15: INTERESES CORRIENTES | X15: -15522.73 | Y15: 0 | Z15: 4978.68 | AA15: -20501.41
B16: Puerta Vehicular Y Peatonal | C16: 590000 | D16: =+C16/12 -> 49166.667 | E16: 0 | F16: 140000 | G16: 0 | L16: =+Y65 -> 140000 | Q16: =SUM(E16:P16) -> 280000 | R16: =+D16*$B$5 -> 393333.33 | S16: =+R16-Q16 -> 113333.33 | T16: =+R16-Q16 -> 113333.33 | V16: 42100502 | W16: INTERESES FIDUCIA | X16: -489731.12 | Y16: 0 | Z16: 64462.02 | AA16: -554193.14
B17: Gimnasio | C17: 2429980 | D17: =+C17/12 -> 202498.33 | E17: 246330 | F17: 0 | G17: 749700 | I17: 246330 | J17: 0 | K17: 238000 | L17: 0 | Q17: =SUM(E17:P17) -> 1480360 | R17: =+D17*$B$5 -> 1619986.7 | S17: =+R17-Q17 -> 139626.67 | T17: =+R17-Q17 -> 139626.67 | V17: 421040 | W17: DESCUENTO CCIAL CONDICIONADO | X17: -1872704 | Y17: 0 | Z17: 262103 | AA17: -2134807
B18: Dotacion | C18: 0 | D18: =+C18/12 -> 0 | E18: 0 | F18: 350000 | Q18: =SUM(E18:P18) -> 350000 | R18: =+D18*$B$5 -> 0 | S18: =+R18-Q18 -> -350000 | T18: =+R18-Q18 -> -350000 | V18: 42104001 | W18: DESCUENTO POR PRONTO PAGO | X18: -1872704 | Y18: 0 | Z18: 262103 | AA18: -2134807
B19: Total Mantenimiento Y Mejoras | C19: =SUM(C11:C18) -> 61679418 | D19: =SUM(D11:D18) -> 5139951.5 | E19: =SUM(E11:E18) -> 5790522 | F19: =SUM(F11:F18) -> 4897597 | G19: =SUM(G11:G18) -> 5238649 | H19: =SUM(H11:H18) -> 3483963 | I19: =SUM(I11:I18) -> 4352282 | J19: =SUM(J11:J17) -> 4238142 | K19: =SUM(K11:K17) -> 4430519 | L19: =SUM(L11:L17) -> 5385569 | M19: =SUM(M11:M17) -> 0 | N19: =SUM(N11:N17) -> 0 | O19: =SUM(O11:O17) -> 0 | P19: =SUM(P11:P17) -> 0 | Q19: =SUM(Q11:Q18) -> 37817243 | R19: =+D19*$B$5 -> 41119612 | S19: =SUM(S11:S17) -> 3652369.2 | T19: =+R19-Q19 -> 3302369.2 | V19: 421095 | W19: OTROS | X19: -890598 | Y19: 0 | Z19: 188163 | AA19: -1078761
B20: Seguridad | D20: =+C20/12 -> 0 | V20: 42109501 | W20: INTERESES POR MORA | X20: -890598 | Y20: 0 | Z20: 188163 | AA20: -1078761
B21: Vigilancia Privada | C21: 1.5883039e+08 | D21: =+C21/12 -> 13235866 | E21: 13136493 | F21: 13136493 | G21: 13136494 | H21: 13136494 | I21: 13136494 | J21: 13136493 | K21: 13244869 | L21: 13354140 | Q21: =SUM(E21:P21) -> 105417970 | R21: =+D21*$B$5 -> 1.0588693e+08 | S21: =+R21-Q21 -> 468958.1 | T21: =+R21-Q21 -> 468958.1 | V21: 4295 | W21: DIVERSOS | X21: -251528.74 | Y21: 0 | Z21: 0 | AA21: -251528.74
B22: Refuerzo Vigilancia | C22: =1751531+2225540 -> 3977071 | D22: =+C22/12 -> 331422.58 | F22: 1751531 | Q22: =SUM(E22:P22) -> 1751531 | R22: =+D22*$B$5 -> 2651380.7 | T22: =+R22-Q22 -> 899849.67 | V22: 429505 | W22: APROVECHAMIENTOS | X22: -251528.74 | Y22: 0 | Z22: 0 | AA22: -251528.74
B23: Seguro Zonas Comunes | C23: 17577558 | D23: =+C23/12 -> 1464796.5 | E23: 1357394 | F23: 904930 | G23: 1443315 | H23: 1486277 | I23: 1486277 | J23: 1443315 | K23: 1443315 | L23: 1443315 | Q23: =SUM(E23:P23) -> 11008138 | R23: =+D23*$B$5 -> 11718372 | S23: =+R23-Q23 -> 710234 | T23: =+R23-Q23 -> 710234 | V23: 42950501 | W23: APROVECHAMIENTOS | X23: -2321 | Y23: 0 | Z23: 0 | AA23: -2321
B24: Sistema De Seguridad Prev | C24: 1341006.2 | D24: =+C24/12 -> 111750.52 | E24: 640110 | F24: 111750 | G24: 111750 | H24: 111750 | I24: 111750 | J24: 111750 | K24: 111750 | L24: 111750 | Q24: =SUM(E24:P24) -> 1422360 | R24: =+D24*$B$5 -> 894004.16 | S24: =+R24-Q24 -> -528355.84 | T24: =+R24-Q24 -> -528355.84 | V24: 42950502 | W24: AJUSTE AL PESO | X24: -755 | Y24: 0 | Z24: 0 | AA24: -755
B25: Sistema De Seg.Repuestos | C25: 1950000 | D25: =+C25/12 -> 162500 | E25: 0 | F25: 0 | G25: 0 | I25: 555730 | J25: 142800 | K25: 0 | L25: 0 | Q25: =SUM(E25:P25) -> 698530 | R25: =+D25*$B$5 -> 1300000 | T25: =+R25-Q25 -> 601470 | V25: 42950504 | W25: INDEMIZACION ASEGURADORA | X25: -248452.74 | Y25: 0 | Z25: 0 | AA25: -248452.74
B26: Sg-Sst, Requisto De Ley | C26: 1910000 | D26: =+C26/12 -> 159166.67 | E26: 0 | F26: 0 | G26: 288000 | H26: 50000 | I26: 305387 | K26: =-529000+875700 -> 346700 | L26: =+Y74 -> 200687 | Q26: =SUM(E26:P26) -> 1190774 | R26: =+D26*$B$5 -> 1273333.3 | S26: =+R26-Q26 -> 82559.333 | T26: =+R26-Q26 -> 82559.333 | V26: 5 | W26: GASTOS | X26: 1.9956645e+08 | Y26: 30300743 | Z26: 0 | AA26: 2.298672e+08
B27: Extintores (Recarga) | C27: 372000 | D27: =+C27/12 -> 31000 | E27: 0 | F27: 0 | G27: 0 | K27: 0 | L27: 0 | Q27: =SUM(E27:P27) -> 0 | R27: =+D27*$B$5 -> 248000 | S27: =+#REF!-#REF! -> #REF! | T27: =+R27-Q27 -> 248000 | V27: 51 | W27: GASTOS OPERATIVOS | X27: 1.9837248e+08 | Y27: 30093953 | Z27: 0 | AA27: 2.2846643e+08
B28: Planes De Ley Emerg, Trat Datos | C28: 740000 | D28: =+C28/12 -> 61666.667 | F28: 138500 | G28: 0 | L28: 0 | Q28: =SUM(E28:P28) -> 138500 | R28: =+D28*$B$5 -> 493333.33 | S28: =+R28-Q28 -> 354833.33 | T28: =+R28-Q28 -> 354833.33 | V28: 5110 | W28: HONORARIOS | X28: 4275423 | Y28: 534452 | Z28: 0 | AA28: 4809875
B29: Reserva Estatutaria 1% Del Ppto (De Ley) | C29: 3533088 | D29: =+C29/12 -> 294424 | E29: =+E7 -> 287015 | F29: 287015 | G29: 287015 | H29: 328376 | I29: =-14659+297358 -> 282699 | J29: =11725+282699 -> 294424 | K29: 297358 | L29: 297356 | Q29: =SUM(E29:P29) -> 2361258 | R29: =+D29*$B$5 -> 2355392 | S29: =+R29-Q29 -> -5866 | T29: =+R29-Q29 -> -5866 | V29: 511030 | W29: ASESORIA FINANCIERA | X29: 4275423 | Y29: 534452 | Z29: 0 | AA29: 4809875
B30: Total Riesgos Y Seguridad | C30: =SUM(C21:C29) -> 1.9023112e+08 | D30: =+C30/12 -> 15852593 | E30: =SUM(E21:E29) -> 15421012 | F30: =SUM(F21:F29) -> 16330219 | G30: =SUM(G21:G29) -> 15266574 | H30: =SUM(H21:H29) -> 15112897 | I30: =SUM(I21:I29) -> 15878337 | J30: =SUM(J21:J29) -> 15128782 | K30: =SUM(K21:K29) -> 15443992 | L30: =SUM(L21:L29) -> 15407248 | ... Q30: =SUM(Q21:Q29) -> 123989061 | R30: =+D30*$B$5 -> 1.2682074e+08 | S30: =SUM(S21:S29) -> #REF! | T30: =+R30-Q30 -> 2831682.6 | V30: 51103001 | W30: ASESORIA FINANCIERA CONTAB | X30: 4275423 | Y30: 534452 | Z30: 0 | AA30: 4809875
B31: Convivencia | D31: =+C31/12 -> 0 | V31: 5115 | W31: IMPUESTOS | X31: 1001500 | Y31: 0 | Z31: 0 | AA31: 1001500
B32: Celebraciones -Navidad | C32: 0 | D32: =+C32/12 -> 0 | E32: =+D32/12 -> 0 | F32: 0 | G32: 0 | H32: 0 | I32: 0 | J32: 179214 | K32: 0 | L32: 0 | Q32: =SUM(E32:P32) -> 179214 | R32: =+D32*$B$5 -> 0 | S32: =+R32-Q32 -> -179214 | T32: =+R32-Q32 -> -179214 | V32: 511515 | W32: A LA PROPIEDAD RAIZ | X32: 1001500 | Y32: 0 | Z32: 0 | AA32: 1001500
B33: Asamblea (Ley) | C33: 0 | D33: =+C33/12 -> 0 | E33: =+D33/12 -> 0 | F33: 0 | G33: =46000+17700+274950 -> 338650 | H33: 0 | I33: 176715 | J33: 0 | K33: 0 | L33: 0 | M33: 0 | N33: 0 | O33: 0 | P33: 0 | Q33: =SUM(E33:P33) -> 515365 | R33: =+D33*$B$5 -> 0 | S33: =+R33-Q33 -> -515365 | T33: =+R33-Q33 -> -515365 | V33: 51151502 | W33: TASA SEGURIDAD | X33: 1001500 | Y33: 0 | Z33: 0 | AA33: 1001500
B34: Total Convivencia | C34: =SUM(C32:C33) -> 0 | D34: =+C34/12 -> 0 | E34: =SUM(E32:E33) -> 0 | F34: =SUM(F32:F33) -> 0 | G34: =SUM(G32:G33) -> 338650 | H34: =SUM(H32:H33) -> 0 | I34: =SUM(I32:I33) -> 176715 | J34: =SUM(J32:J33) -> 179214 | K34: =SUM(K32:K33) -> 0 | L34: 0 | M34: =SUM(M32:M33) -> 0 | N34: =SUM(N32:N33) -> 0 | O34: =SUM(O32:O33) -> 0 | P34: =SUM(P32:P33) -> 0 | Q34: =SUM(E34:P34) -> 694579 | R34: =SUM(R32:R33) -> 0 | S34: =SUM(S32:S33) -> -694579 | T34: =+R34-Q34 -> -694579 | V34: 5130 | W34: SEGUROS | X34: 9564823 | Y34: 1443315 | Z34: 0 | AA34: 11008138
B35: Ambiental | D35: =+C35/12 -> 0 | V35: 513025 | W35: INCENDIO | X35: 9564823 | Y35: 1443315 | Z35: 0 | AA35: 11008138
B36: Fumigación | C36: 2568001.5 | D36: =+C36/12 -> 214000.12 | E36: 0 | F36: 0 | G36: 595450 | H36: 0 | I36: 781652 | L36: =+Y56 -> 781652 | Q36: =SUM(E36:P36) -> 2158754 | R36: =+D36*$B$5 -> 1712001 | S36: =+R36-Q36 -> -446753 | T36: =+R36-Q36 -> -446753 | V36: 51302501 | W36: SEGURO ZONAS COMUNES | X36: 9564823 | Y36: 1443315 | Z36: 0 | AA36: 11008138
B37: Energía | C37: =33250000*1.15 -> 38237500 | D37: =+C37/12 -> 3186458.3 | E37: 3189683.9 | F37: 2628727 | G37: 2554892 | H37: 2640861 | I37: 3098024 | J37: 2908845 | K37: =2964954 -> 2964954 | L37: =+Y50 -> 2551875 | Q37: =SUM(E37:P37) -> 22537862 | R37: =+D37*$B$5 -> 25491667 | S37: =+R37-Q37 -> 2953804.8 | T37: =+R37-Q37 -> 2953804.8 | V37: 5135 | W37: SERVICIOS | X37: 1.5526347e+08 | Y37: 21826692 | Z37: 0 | AA37: 1.7709016e+08
B38: Acueducto Y Alcantarillado | C38: 3500000 | D38: =+C38/12 -> 291666.67 | E38: 129706 | F38: 233099 | G38: 303870 | H38: 205744 | I38: 217588 | J38: 249565 | K38: =956190 -> 956190 | L38: =+Y48 -> 380094 | Q38: =SUM(E38:P38) -> 2675856 | R38: =+D38*$B$5 -> 2333333.3 | S38: =+R38-Q38 -> -342522.67 | T38: =+R38-Q38 -> -342522.67 | V38: 513505 | W38: ASEO Y VIGILANCIA | X38: 113623094 | Y38: 16176904 | Z38: 0 | AA38: 129799998
B39: Tasa De Aseo | C39: 604000 | D39: =+C39/12 -> 50333.333 | E39: 50100 | F39: 50115 | G39: 56102 | H39: 56070 | I39: 56076 | J39: 55806 | K39: 55760 | L39: =+Y41 -> 56144 | Q39: =SUM(E39:P39) -> 436173 | R39: =+D39*$B$5 -> 402666.67 | S39: =+R39-Q39 -> -33506.333 | T39: =+R39-Q39 -> -33506.333 | V39: 51350501 | W39: SERVICIOS DE VIGILANCIA | X39: 93815361 | Y39: 13354140 | Z39: 0 | AA39: 107169501
B40: SGIRS Pemirs Ley | C40: =100988*12 -> 1211856 | D40: =+C40/12 -> 100988 | E40: 0 | F40: 0 | G40: 55250 | H40: 0 | I40: 0 | Q40: =SUM(E40:P40) -> 55250 | R40: =+D40*$B$5 -> 807904 | T40: =+R40-Q40 -> 752654 | V40: 51350502 | W40: SERVICIOS DE ASEO | X40: 19427704 | Y40: 2766620 | Z40: 0 | AA40: 22194324
B41: Telefonía E Internet | C41: 800000 | D41: =+C41/12 -> 66666.667 | E41: 87582 | F41: 100988 | G41: 100988 | H41: 100988 | I41: 100988 | J41: 100988 | K41: 100988 | L41: 100988 | Q41: =SUM(E41:P41) -> 794498 | R41: =+D41*$B$5 -> 533333.33 | S41: =+R41-Q41 -> -261164.67 | T41: =+R41-Q41 -> -261164.67 | V41: 51350503 | W41: RECOLECCION DE BASURAS | X41: 380029 | Y41: 56144 | Z41: 0 | AA41: 436173
B42: Corte Cesped Y Mto Jardines Z. Comun | C42: =(1187000+167200)*12 -> 16250400 | D42: =+C42/12 -> 1354200 | E42: 1354200 | F42: 1354200 | G42: 1354200 | H42: 1354200 | I42: 1354200 | K42: 1354200 | L42: =+Y62 -> 2279100 | Q42: =SUM(E42:P42) -> 10404300 | R42: =+D42*$B$5 -> 10833600 | S42: =+R42-Q42 -> 429300 | T42: =+R42-Q42 -> 429300 | V42: 513515 | W42: ASISTENCIA ADMINISTRATIVA | X42: 17966012 | Y42: 2566487 | Z42: 0 | AA42: 20532499
B43: Tasa de seguridad | I43: 472500 | K43: 529000 | L43: 0 | Q43: =SUM(E43:P43) -> 1001500 | R43: =+D43*$B$5 -> 0 | T43: =+R43-Q43 -> -1001500 | V43: 51351501 | W43: SERVICIOS DE ADMINISTRACION | X43: 17966012 | Y43: 2566487 | Z43: 0 | AA43: 20532499
B44: Total Ambiental | C44: =SUM(C36:C42) -> 63171758 | D44: =+C44/12 -> 5264313.1 | E44: =SUM(E36:E42) -> 4811271.9 | F44: =SUM(F36:F42) -> 4367129 | G44: =SUM(G36:G42) -> 5020752 | H44: =SUM(H36:H42) -> 4357863 | I44: =SUM(I36:I43) -> 6081028 | J44: =SUM(J36:J42) -> 3315204 | K44: =SUM(K36:K43) -> 5961092 | L44: =SUM(L36:L43) -> 6149853 | M44: =SUM(M36:M42) -> 0 | N44: =SUM(N36:N42) -> 0 | O44: =SUM(O36:O42) -> 0 | P44: =SUM(P36:P42) -> 0 | Q44: =SUM(Q36:Q43) -> 40064193 | R44: =+D44*$B$5 -> 42114505 | S44: =SUM(S36:S42) -> 2299158.1 | T44: =+R44-Q44 -> 2050312.1 | V44: 513520 | W44: PROCES ELECTRON DE DATOS | X44: 352408 | Y44: 50344 | Z44: 0 | AA44: 402752
B45: Administrativos | S45: =+F45+G45+E45 -> 0 | V45: 51352001 | W45: FACTURACION | X45: 352408 | Y45: 50344 | Z45: 0 | AA45: 402752
B46: Administración | C46: 30797847 | D46: =+C46/12 -> 2566487.2 | E46: 2343824 | F46: 2343824 | G46: 2343824 | H46: 3235079 | I46: 2566487 | J46: 2566487 | K46: 2566487 | L46: =+Y43 -> 2566487 | Q46: =SUM(E46:P46) -> 20532499 | R46: =+D46*$B$5 -> 20531898 | S46: =+R46-Q46 -> -601 | T46: =+R46-Q46 -> -601 | V46: 513521 | W46: SISTEMA SS-SGT | X46: 346700 | Y46: 0 | Z46: 0 | AA46: 346700
B47: Contabilidad | C47: 6413421 | D47: =+C47/12 -> 534451.75 | E47: 488080 | F47: 488080 | G47: 627190 | H47: 534352 | I47: 534352 | J47: 534352 | K47: 534452 | L47: 534452 | Q47: =SUM(E47:P47) -> 4275310 | R47: =+D47*$B$5 -> 4275614 | S47: =+R47-Q47 -> 304 | T47: =+R47-Q47 -> 304 | V47: 51352101 | W47: SISTEMA SS-SGT | X47: 346700 | Y47: 0 | Z47: 0 | AA47: 346700
B48: Informacion Exogena Y Niff | C48: 534465 | D48: =+C48/12 -> 44538.75 | E48: 0 | F48: 0 | G48: 0 | H48: 0 | I48: 0 | J48: 534565 | K48: 0 | L48: 0 | Q48: =SUM(E48:P48) -> 534565 | R48: =+D48*$B$5 -> 356310 | S48: =+R48-Q48 -> -178255 | T48: =+R48-Q48 -> -178255 | V48: 513525 | W48: ACUEDUCTO Y ALCANTARILLADO | X48: 2296612 | Y48: 380094 | Z48: 0 | AA48: 2676706
B49: Facturación | C49: 603903 | D49: =+C49/12 -> 50325.25 | E49: 50344 | F49: 50344 | G49: 50344 | H49: 50344 | I49: 50344 | J49: 50344 | K49: 50344 | L49: 50344 | Q49: =SUM(E49:P49) -> 402752 | R49: =+D49*$B$5 -> 402602 | S49: =+R49-Q49 -> -150 | T49: =+R49-Q49 -> -150 | V49: 51352501 | W49: ACUEDUCTO Y ALCANTARILLADO | X49: 2296612 | Y49: 380094 | Z49: 0 | AA49: 2676706
B50: Útiles,Papelería -Comunicación | C50: 200000 | D50: =+C50/12 -> 16666.667 | E50: 0 | F50: 0 | G50: 10000 | H50: 10000 | I50: 0 | J50: 0 | K50: 0 | L50: 0 | Q50: =SUM(E50:P50) -> 20000 | R50: =+D50*$B$5 -> 133333.33 | S50: =+R50-Q50 -> 113333.33 | T50: =+R50-Q50 -> 113333.33 | V50: 513530 | W50: ENERGIA ELECTRICA | X50: 19985137 | Y50: 2551875 | Z50: 0 | AA50: 22537012
B51: Cafeteria | C51: 360000 | D51: =+C51/12 -> 30000 | E51: 0 | F51: 0 | G51: 26640 | H51: 4390 | I51: 27030 | J51: 0 | K51: 75550 | L51: 0 | Q51: =SUM(E51:P51) -> 133610 | R51: =+D51*$B$5 -> 240000 | S51: =+R51-Q51 -> 106390 | T51: =+R51-Q51 -> 106390 | V51: 51353001 | W51: ENERGIA ELECTRICA | X51: 19985137 | Y51: 2551875 | Z51: 0 | AA51: 22537012
B52: Transporte Trámites | C52: 150000 | D52: =+C52/12 -> 12500 | E52: 0 | F52: 0 | G52: 4500 | H52: 0 | I52: 0 | J52: 0 | K52: 0 | L52: 0 | Q52: =SUM(E52:P52) -> 4500 | R52: =+D52*$B$5 -> 100000 | S52: =+R52-Q52 -> 95500 | T52: =+R52-Q52 -> 95500 | V52: 513535 | W52: TELEFONO | X52: 693510 | Y52: 100988 | Z52: 0 | AA52: 794498
B53: Gastos Bancarios | C53: 2700000 | D53: =+C53/12 -> 225000 | E53: 191152.44 | F53: 189522.6 | G53: 196603.1 | H53: 179705.1 | I53: 225057.48 | J53: 101784 | K53: 108924 | L53: =+Y84 -> 206789.6 | Q53: =SUM(E53:P53) -> 1399538.3 | R53: =+D53*$B$5 -> 1800000 | S53: =+R53-Q53 -> 400461.68 | T53: =+R53-Q53 -> 400461.68 | V53: 51353501 | W53: TELEFONO | X53: 693510 | Y53: 100988 | Z53: 0 | AA53: 794498
B54: Ajuste Al Peso | C54: 0 | D54: =+C54/12 -> 0 | E54: 0 | F54: 0 | G54: 1227 | H54: 5 | I54: -1887 | K54: 1 | L54: 1 | Q54: =SUM(E54:P54) -> -653 | R54: =+D54*$B$5 -> 0 | S54: =+#REF!-#REF! -> #REF! | T54: =+R54-Q54 -> 653 | V54: 5145 | W54: MANTTO Y REPARACIONES | X54: 23060229 | Y54: 5713951 | Z54: 0 | AA54: 28774180
B55: Impuestos Asumidos | C55: 0 | D55: =+C55/12 -> 0 | Q55: =SUM(E55:P55) -> 0 | R55: =+D55*$B$5 -> 0 | S55: =+R55-Q55 -> 0 | T55: =+R55-Q55 -> 0 | V55: 514510 | W55: CONSTRUC Y EDIFICACIONES | X55: 1377102 | Y55: 781652 | Z55: 0 | AA55: 2158754
B56: Total Administrativos | C56: =SUM(C46:C55) -> 41759636 | D56: =SUM(D46:D55) -> 3479969.7 | E56: =SUM(E46:E55) -> 3073400.4 | F56: =SUM(F46:F55) -> 3071770.6 | G56: =SUM(G46:G55) -> 3260328.1 | H56: =SUM(H46:H55) -> 4013875.1 | I56: =SUM(I46:I55) -> 3401383.5 | J56: =SUM(J46:J55) -> 3787532 | ... L56: =SUM(L46:L55) -> 3358073.6 | Q56: =SUM(Q46:Q55) -> 27302121 | R56: =+D56*$B$5 -> 27839757 | S56: =SUM(S46:S55) -> #REF! | T56: =+R56-Q56 -> 537636.01 | V56: 51451003 | W56: FUMIGACION | X56: 1377102 | Y56: 781652 | Z56: 0 | AA56: 2158754
B57: Total Egresos Operacionales Mes | C57: =+C56+C44+C30+C34+C19 -> 3.5684193e+08 | D57: =+D56+D44+D30+D19 -> 29736827 | E57: =+E56+E44+E30+E34+E19 -> 29096206 | F57: =+F56+F44+F30+F34+F19 -> 28666716 | G57: =+G56+G44+G30+G34+G19 -> 29124953 | H57: =+H56+H44+H30+H34+H19 -> 26968598 | I57: =+I56+I44+I30+I34+I19 -> 29889745 | J57: =+J56+J44+J30+J34+J19 -> 26648874 | K57: =+K56+K44+K30+K34+K19 -> 29171361 | L57: =+L56+L44+L30+L34+L19 -> 30300744 | ... Q57: =+Q56+Q44+Q30+Q34+Q19 -> 2.298672e+08 | R57: =+D57*$B$5 -> 2.3789462e+08 | S57: =+S56+S44+S30+S34+S19 -> #REF! | T57: =+T56+T44+T30+T34+T19 -> 8027420.9 | V57: 514595 | W57: MANTENIMIENTO OTROS | X57: 21683127 | Y57: 4932299 | Z57: 0 | AA57: 26615426
V58: 51459501 | W58: ZONAS COMUNES | X58: 4769336 | Y58: 1519560 | Z58: 0 | AA58: 6288896
B59: OTROS INGRESOS MARGINALES | C59: =SUM(C60:C64) -> 0 | E59: =SUM(E60:E65) -> 451228.69 | F59: =SUM(F60:F64) -> 472103.34 | G59: =SUM(G60:G64) -> 455679.26 | H59: =SUM(H60:H64) -> 411197.13 | I59: =SUM(I60:I65) -> 713029.05 | J59: =SUM(J60:J65) -> 414671.36 | K59: =SUM(K60:K65) -> 602175.76 | L59: =SUM(L60:L65) -> 519706.7 | M59: =SUM(M60:M64) -> 0 | N59: =SUM(N60:N64) -> 0 | O59: =SUM(O60:O64) -> 0 | P59: =SUM(P60:P64) -> 0 | Q59: =SUM(Q60:Q65) -> 4039791.3 | R59: =SUM(R60:R64) -> 0 | S59: =SUM(S60:S64) -> -3791338.5 | T59: =+Q59 -> 4039791.3 | V59: 51459502 | W59: MANTENIMIENTO PREVENTIVO | X59: 1310610 | Y59: 111750 | Z59: 0 | AA59: 1422360
B60: Interes de Mora | E60: 69013 | F60: 95407 | G60: 139518 | H60: 92495 | I60: 136086 | J60: 108094 | K60: 249985 | L60: =+Z20 -> 188163 | Q60: =SUM(E60:P60) -> 1078761 | R60: 0 | S60: =+R60-Q60 -> -1078761 | V60: 51459504 | W60: REPARACIONES ELECTRICAS | X60: 828038 | Y60: 80000 | Z60: 0 | AA60: 908038
B61: Intereses Financieros | E61: =669.24+123715.45 -> 124384.69 | F61: =52094.04+1011.3 -> 53105.34 | G61: =57021.36+1056.9 -> 58078.26 | H61: =1143+59728.13 -> 60871.13 | I61: 67835.31 | J61: 48746.36 | K61: =4108.41+88124.35 -> 92232.76 | L61: =+Z14 -> 69440.7 | Q61: =SUM(E61:P61) -> 574694.55 | R61: 0 | S61: =+R61-Q61 -> -574694.55 | V61: 51459505 | W61: MTTO GIMNASIO | X61: 1480360 | Y61: 0 | Z61: 0 | AA61: 1480360
B62: Salon social | F62: 0 | I62: 0 | J62: 0 | K62: 0 | L62: 0 | Q62: =SUM(E62:P62) -> 0 | R62: 0 | S62: =+R62-Q62 -> 0 | V62: 51459506 | W62: MANTENIMIENTO JARDIN | X62: 8125200 | Y62: 2279100 | Z62: 0 | AA62: 10404300
B63: Dto pronto Pago | E63: 257831 | F63: 323591 | G63: 257831 | H63: 257831 | I63: 257831 | J63: 257831 | K63: 259958 | L63: 262103 | Q63: =SUM(E63:P63) -> 2134807 | R63: 0 | S63: =+R63-Q63 -> -2134807 | V63: 51459507 | W63: MANTENIMIENTO PISCINA | X63: 4331053 | Y63: 801889 | Z63: 0 | AA63: 5132942
B64: Aprovechamientos | G64: 252 | I64: =2321+503 -> 2824 | J64: 0 | K64: 0 | L64: 0 | Q64: =SUM(E64:P64) -> 3076 | R64: 0 | S64: =+R64-Q64 -> -3076 | V64: 51459508 | W64: MANTEN CORREC.CAMARAS CCTV | X64: 698530 | Y64: 0 | Z64: 0 | AA64: 698530
B65: Saldo reclamcion talud | I65: 248452.74 | J65: 0 | K65: 0 | L65: 0 | Q65: =SUM(E65:P65) -> 248452.74 | V65: 51459510 | W65: MMTO PUERTA VEHICULAR | X65: 140000 | Y65: 140000 | Z65: 0 | AA65: 280000
B66: RESULTADO PRESUPUESTAL MES/AÑO | C66: =+C8-C57 -> -0.21000004 | D66: =+D8-D57 -> -0.017500002 | E66: =+E8-E57+E59 -> 56589.37 | F66: =+F8-F57+F59 -> 506954.74 | G66: =+G8-G57+G59 -> 32293.16 | H66: =+H8-H57+H59 -> 6280234 | I66: =+I8-I57+I59 -> 558867.57 | J66: =+J8-J57+J59 -> 3501381.4 | K66: =+K8-K57+K59 -> 1166398.8 | L66: =+L8-L57+L59 -> -45452.9 | ... Q66: =+Q8-Q57+Q59 -> 12057266 | R66: 0 | S66: =+S8-S57+S59 -> #REF! | T66: =+T57-T8+T59 -> 12057266 | V66: 5150 | W66: ADECUACION E INSTALACIONES | X66: 350000 | Y66: 0 | Z66: 0 | AA66: 350000
F67: =SUM(E66:F66) -> 563544.11 | G67: =SUM(E66:G66) -> 595837.27 | H67: =SUM(E66:H66) -> 6876071.3 | I67: =SUM(E66:I66) -> 7434938.9 | V67: 515010 | W67: DOTACION UNIDAD | X67: 350000 | Y67: 0 | Z67: 0 | AA67: 350000
I68: =SUM(E66:I66) -> 7434938.9 | J68: =SUM(E66:J66) -> 10936320 | K68: =SUM(E66:K66) -> 12102719 | L68: =SUM(E66:L66) -> 12057266 | S68: =+Q66+S66 -> #REF! | V68: 5195 | W68: DIVERSOS | X68: 2793128.9 | Y68: 278187 | Z68: 0 | AA68: 3071315.9
B69: TANIA MARIA ANGULO | F69: GABRIELA MUÑOZ MOLINA | K69: GABRIELA MUÑOZ MOLINA | V69: 519525 | W69: ELEMENTOS DE ASEO Y CAFETERIA | X69: 1238793 | Y69: 77500 | Z69: 0 | AA69: 1316293
B70: Administradora | F70: Contadora | K70: Contadora | V70: 51952501 | W70: ELEMENTOS DE ASEO | X70: 1105183 | Y70: 77500 | Z70: 0 | AA70: 1182683
V71: 51952502 | W71: IMPLEMENTOS CAFETERIA | X71: 133610 | Y71: 0 | Z71: 0 | AA71: 133610
V72: 519530 | W72: UTILES PAPELERIA Y FOTOCOPIAS | X72: 20000 | Y72: 0 | Z72: 0 | AA72: 20000
B73: DECISIONES ASAMBLEA | V73: 519550 | W73: IMPLEMENTACION | X73: 837137 | Y73: 200687 | Z73: 0 | AA73: 1037824
B74: GASTOS NO PRESUPUESTADOS X DEFINIR TALUD | C74: =-49920464 -> -49920464 | V74: 51955001 | W74: IMPLEMENTACION SS-SSGT | X74: 781887 | Y74: 200687 | Z74: 0 | AA74: 982574
B75: DEFICIT PPTAL 2023 | C75: -893269.33 | V75: 51955003 | W75: PEMIRS | X75: 55250 | Y75: 0 | Z75: 0 | AA75: 55250
B76: TOTAL A CUBRIR | C76: =SUM(C74:C75) -> -50813733 | V76: 519595 | W76: OTROS | X76: 692698.88 | Y76: 0 | Z76: 0 | AA76: 692698.88
B77: CUBRIR ASI SEGÚN DECISIÓN ASAMBLEA | V77: 51959503 | W77: GASTOS ASAMBLEA | X77: 338650 | Y77: 0 | Z77: 0 | AA77: 338650
B78: CUOTA EXTRA 2022-RECONOCIMIENTO SEGURO | C78: 7425682 | V78: 51959504 | W78: CELEBRACIONES ESPECIALES | X78: 355929 | Y78: 0 | Z78: 0 | AA78: 355929
B79: CUOTA EXTRA 2023 | C79: 8550122 | V79: 51959590 | W79: AJUSTE AL PESO | X79: -1880.12 | Y79: 0 | Z79: 0 | AA79: -1880.12
B80: REINVERSIÓN 2023 | C80: 3837291 | V80: 5199 | W80: PROVISIONES | X80: 2063902 | Y80: 297356 | Z80: 0 | AA80: 2361258
B81: CUOTA EXTRA 2024 | C81: 23006464 | V81: 519920 | W81: FONDO DE IMPREVISTOS | X81: 2063902 | Y81: 297356 | Z81: 0 | AA81: 2361258
B82: RESULTADOS DE 2024 | C82: 7994163.1 | V82: 51992001 | W82: FONDO IMPREV LEY 675 | X82: 2063902 | Y82: 297356 | Z82: 0 | AA82: 2361258
B83: total disposicion de fondos para cubrir | C83: =SUM(C78:C82) -> 50813722 | V83: 53 | W83: NO OPERACIONALES | X83: 1193975.7 | Y83: 206789.6 | Z83: 0 | AA83: 1400765.3
V84: 5305 | W84: FINANCIEROS | X84: 1187594.5 | Y84: 206789.6 | Z84: 0 | AA84: 1394384.1
V85: 530505 | W85: GASTOS BANCARIOS | X85: 1187594.5 | Y85: 206789.6 | Z85: 0 | AA85: 1394384.1
B86: DECISIONES ASAMBLEA | V86: 53050501 | W86: COBRO SERVICIOS DE RECAUDO | X86: 658414.54 | Y86: 22193.5 | Z86: 0 | AA86: 680608.04
B87: GASTOS NO PRESUPUESTADOS X DEFINIR TALUD | C87: =-49920464 -> -49920464 | V87: 53050502 | W87: COMISION PAGO A PROVEEDORES | X87: 0 | Y87: 83538 | Z87: 0 | AA87: 83538
B88: DEFICIT PPTAL 2023 | C88: -893269.33 | V88: 53050503 | W88: MANEJO SUCURSAL VIRTUAL | X88: 529180 | Y88: 101058.1 | Z88: 0 | AA88: 630238.1
B89: TOTAL A CUBRIR | C89: =SUM(C87:C88) -> -50813733 | V89: 5315 | W89: GASTOS EXTRAORDINARIOS | X89: 6381.18 | Y89: 0 | Z89: 0 | AA89: 6381.18
B90: CUBRIR ASI SEGÚN DECISIÓN ASAMBLEA | V90: 531520 | W90: IMPUESTOS ASUMIDOS | X90: 6381.18 | Y90: 0 | Z90: 0 | AA90: 6381.18
B91: CUOTA EXTRA 2022-RECONOCIMIENTO SEGURO | C91: 7425682
B92: CUOTA EXTRA 2023 | C92: 0
B93: REINVERSIÓN 2023 | C93: 3837291
B94: CUOTA EXTRA 2024 | C94: 0
B95: RESULTADOS DE 2024 | C95: 7994163.1
B96: total disposicion de fondos para cubrir | C96: =SUM(C91:C95) -> 19257136
B98: RECIBIDO | C98: 31805050

Sheet Graf Cartera 2025 Contab
C1: 45992 | H1: 45962 | M1: 45931 | R1: 45901 | W1: 45870 | AB1: 45839 | AG1: 45809 | AL1: 45778 | AQ1: 45383 | AV1: 45352 | AZ1: 45689 | BC1: 45658 | BF1: 45261
A2: DETALLE CARTERA CONTABILIDAD VS FACTURACIÓN DIC 2025 | F2: DETALLE CARTERA CONTABILIDAD VS FACTURACIÓN NOV 2025 | K2: DETALLE CARTERA CONTABILIDAD VS FACTURACIÓN OCT 2025 | Q2: DETALLE CARTERA CONTABILIDAD VS FACTURACIÓN SEP2024 | V2: DETALLE CARTERA CONTABILIDAD VS FACTURACIÓN | AA2: DETALLE CARTERA CONTABILIDAD VS FACTURACIÓN jul 2024 | AF2: DETALLE CARTERA CONTABILIDAD VS FACTURACIÓN jun 2025 | AK2: DETALLE CARTERA CONTABILIDAD VS FACTURACIÓN may 2025 | AP2: DETALLE CARTERA CONTABILIDAD VS FACTURACIÓN abril 2024 | AU2: DETALLE CARTERA CONTABILIDAD VS FACTURACION mar 2025 | AY2: DETALLE CARTERA CONTABILIDAD VS FACTURACIÓN feb 2025 | BC2: DETALLE CARTERA CONTABILIDAD VS FACTURACIÓN may 2024
A3: INMUEBLE | B3: PROPIETARIO | C3: SALDO CONTABILIDAD | D3: FACTURACIÓN | E3: DIFER. | F3: INMUEBLE | G3: PROPIETARIO | H3: SALDO CONTABILIDAD | I3: FACTURACIÓN | J3: DIFER. | K3: INMUEBLE | L3: PROPIETARIO | M3: SALDO CONTABILIDAD | N3: FACTURACIÓN | O3: DIFER. | P3: INMUEBLE | Q3: PROPIETARIO | R3: SALDO CONTABILIDAD | S3: FACTURACIÓN | T3: DIFER. | U3: INMUEBLE | V3: PROPIETARIO | W3: SALDO CONTABILIDAD | X3: FACTURACIÓN | Y3: DIFER. | Z3: INMUEBLE | AA3: PROPIETARIO | AB3: SALDO CONTABILIDAD | AC3: FACTURACIÓN | AD3: DIFER. | AE3: INMUEBLE | AF3: PROPIETARIO | AG3: SALDO CONTABILIDAD | AH3: FACTURACIÓN | AI3: DIFER. | AJ3: INMUEBLE | AK3: PROPIETARIO | AL3: SALDO CONTABILIDAD | AM3: FACTURACIÓN | AN3: DIFER. | AO3: INMUEBLE | AP3: PROPIETARIO | AQ3: SALDO CONTABILIDAD | AR3: FACTURACIÓN | AS3: DIFER. | AT3: INMUEBLE | AU3: PROPIETARIO | AV3: SALDO CONTABILIDAD | AW3: FACTURACON | AX3: DIFER. | AY3: CASA | AZ3: CONTABILIDAD | BA3: FACTURACION | BB3: DIFERENCIA | BC3: CONTABILIDAD | BD3: FACTURACION | BE3: DIFERENCIA
A4: 101-6 | B4: OLGA DEL SOCORRO ALVAREZ | E4: =+C4-D4 -> 0 | F4: 101-6 | G4: OLGA DEL SOCORRO ALVAREZ | J4: =+H4-I4 -> 0 | K4: 101-6 | L4: OLGA DEL SOCORRO ARBELAEZ | O4: =+M4-N4 -> 0 | P4: 101-6 | Q4: Olga Del Socorro Álvarez | T4: =+R4-S4 -> 0 | U4: 101-6 | V4: Olga Del Socorro Álvarez | W4: ='Notas agost 2025'!D12 -> 3065812 | X4: 3065812 | Y4: =+W4-X4 -> 0 | Z4: 101-6 | AA4: Olga Del Socorro Álvarez | AB4: 1747986 | AC4: 1747986 | AD4: =+AB4-AC4 -> 0 | AE4: 101-6 | AF4: Olga Del Socorro Álvarez | AG4: 2649758 | AH4: 2649758 | AI4: =+AG4-AH4 -> 0 | AJ4: 101-6 | AK4: Olga Del Socorro Álvarez | AL4: 1593320 | AM4: 1593320 | AN4: 0 | AO4: 101-6 | AP4: Olga Del Socorro Álvarez | AQ4: 1274603 | AR4: 1274603 | AS4: =+AQ4-AR4 -> 0 | AT4: 101-6 | AU4: Olga Del Socorro Alvarez | AV4: 1110627 | AW4: 1110627 | AX4: =+AV4-AW4 -> 0 | AY4: 101-6 | AZ4: 2069141 | BA4: 2069141 | BB4: =+AZ4-BA4 -> 0 | BC4: 2028481 | BD4: 2028481 | BE4: =+BC4-BD4 -> 0
A5: 102-3 | B5: DIEGO GOMEZ | E5: =+C5-D5 -> 0 | F5: 102-3 | G5: DIEGO GOMEZ | J5: =+H5-I5 -> 0 | K5: 102-3 | L5: DIEGO GÓMEZ | O5: =+M5-N5 -> 0 | P5: 102-3 | Q5: Diego Gómez | T5: =+R5-S5 -> 0 | U5: 102-3 | V5: Diego Gómez | W5: ='Notas agost 2025'!D13 -> 0 | X5: 0 | Y5: =+W5-X5 -> 0 | Z5: 102-3 | AA5: Diego Gómez | AB5: 0 | AC5: 0 | AD5: =+AB5-AC5 -> 0 | AE5: 102-3 | AF5: Diego Gómez | AG5: 0 | AH5: 0 | AI5: =+AG5-AH5 -> 0 | AJ5: 102-3 | AK5: Diego Gómez | AL5: 0 | AM5: 0 | AN5: 0 | AO5: 102-3 | AP5: Diego Gómez | AQ5: 0 | AS5: =+AQ5-AR5 -> 0 | AT5: 102-3 | AU5: Diego Gomez | AV5: 0 | AX5: =+AV5-AW5 -> 0 | AY5: 102-3 | AZ5: 0 | BB5: =+AZ5-BA5 -> 0 | BC5: 924765 | BD5: 924765 | BE5: =+BC5-BD5 -> 0
A6: 103-0 | B6: JUAN CAMILO SOTO | E6: =+C6-D6 -> 0 | F6: 103-0 | G6: JUAN CAMILO SOTO | J6: =+H6-I6 -> 0 | K6: 103-0 | L6: JUAN CAMILO SOTO | O6: =+M6-N6 -> 0 | P6: 103-0 | Q6: Juan Camilo Soto | T6: =+R6-S6 -> 0 | U6: 103-0 | V6: Juan Camilo Soto | W6: ='Notas agost 2025'!D14 -> 0 | X6: 0 | Y6: =+W6-X6 -> 0 | Z6: 103-0 | AA6: Juan Camilo Soto | AB6: 0 | AC6: 0 | AD6: =+AB6-AC6 -> 0 | AE6: 103-0 | AF6: Juan Camilo Soto | AG6: 0 | AH6: 0 | AI6: =+AG6-AH6 -> 0 | AJ6: 103-0 | AK6: Juan Camilo Soto | AL6: 0 | AM6: 0 | AN6: 0 | AO6: 103-0 | AP6: Juan Camilo Soto | AQ6: 0 | AS6: =+AQ6-AR6 -> 0 | AT6: 103-0 | AU6: Juan Camilo Soto | AV6: 0 | AX6: =+AV6-AW6 -> 0 | AY6: 103-0 | AZ6: 0 | BB6: =+AZ6-BA6 -> 0 | BC6: 0 | BD6: 0 | BE6: =+BC6-BD6 -> 0
A7: 104-8 | B7: ALVARO GOMEZ - GLORIA ZULUAGA | E7: =+C7-D7 -> 0 | F7: 104-8 | G7: ALVARO GOMEZ - GLORIA ZULUAGA | J7: =+H7-I7 -> 0 | K7: 104-8 | L7: ALVARO GOMEZ | O7: =+M7-N7 -> 0 | P7: 104-8 | Q7: Álvaro Gómez - Gloria Zuluaga | T7: =+R7-S7 -> 0 | U7: 104-8 | V7: Álvaro Gómez - Gloria Zuluaga | W7: ='Notas agost 2025'!D15 -> 0 | X7: 0 | Y7: =+W7-X7 -> 0 | Z7: 104-8 | AA7: Álvaro Gómez - Gloria Zuluaga | AB7: 930723 | AC7: 930723 | AD7: =+AB7-AC7 -> 0 | AE7: 104-8 | AF7: Álvaro Gómez - Gloria Zuluaga | AG7: 0 | AH7: 0 | AI7: =+AG7-AH7 -> 0 | AJ7: 104-8 | AK7: Álvaro Gómez - Gloria Zuluaga | AL7: 0 | AM7: 0 | AN7: 0 | AO7: 104-8 | AP7: Álvaro Gómez - Gloria Zuluaga | AQ7: 1027815 | AR7: 1027815 | AS7: =+AQ7-AR7 -> 0 | AT7: 104-8 | AU7: Alvaro Gomez - Gloria Zuluaga | AV7: 0 | AX7: =+AV7-AW7 -> 0 | AY7: 104-8 | AZ7: 0 | BB7: =+AZ7-BA7 -> 0 | BC7: 0 | BD7: 0 | BE7: =+BC7-BD7 -> 0
A8: 105-5 | B8: VICTOR ALFONSO CARDONA | E8: =+C8-D8 -> 0 | F8: 105-5 | G8: VICTOR ALFONSO CARDONA | J8: =+H8-I8 -> 0 | K8: 105-5 | L8: VICTOR ALFONSO CARDONA | O8: =+M8-N8 -> 0 | P8: 105-5 | Q8: Víctor Alfonso Cardona | T8: =+R8-S8 -> 0 | U8: 105-5 | V8: Víctor Alfonso Cardona | W8: ='Notas agost 2025'!D16 -> 1291585 | X8: =1291585+5000 -> 1296585 | Y8: 5000 | Z8: 105-5 | AA8: Víctor Alfonso Cardona | AB8: 1033633 | AC8: 1033633 | AD8: =+AB8-AC8 -> 0 | AE8: 105-5 | AF8: Víctor Alfonso Cardona | AG8: =-78357+1200000 -> 1121643 | AH8: -78357 | AI8: =+AG8-AH8 -> 1200000 | AJ8: 105-5 | AK8: Víctor Alfonso Cardona | AL8: 9461 | AM8: 9461 | AN8: 0 | AO8: 105-5 | AP8: Víctor Alfonso Cardona | AQ8: 1242367 | AR8: 1242367 | AS8: =+AQ8-AR8 -> 0 | AT8: 105-5 | AU8: Victor Alfonso Cardona | AV8: 230558 | AW8: 230558 | AX8: =+AV8-AW8 -> 0 | AY8: 105-5 | AZ8: 196296 | BA8: 196296 | BB8: =+AZ8-BA8 -> 0 | BC8: 162716 | BD8: 162716 | BE8: =+BC8-BD8 -> 0
A9: 106-2 | B9: ZOILA MARGARITA MARTINEZ | E9: =+C9-D9 -> 0 | F9: 106-2 | G9: ZOILA MARGARITA MARTINEZ | J9: =+H9-I9 -> 0 | K9: 106-2 | L9: ZOILA MARGARITA INSIGNARES | O9: =+M9-N9 -> 0 | P9: 106-2 | Q9: Zoila Margarita Martínez | T9: =+R9-S9 -> 0 | U9: 106-2 | V9: Zoila Margarita Martínez | W9: ='Notas agost 2025'!D17 -> 0 | X9: 0 | Y9: =+W9-X9 -> 0 | Z9: 106-2 | AA9: Zoila Margarita Martínez | AB9: 0 | AC9: 0 | AD9: =+AB9-AC9 -> 0 | AE9: 106-2 | AF9: Zoila Margarita Martínez | AG9: 0 | AH9: 0 | AI9: =+AG9-AH9 -> 0 | AJ9: 106-2 | AK9: Zoila Margarita Martínez | AL9: 0 | AM9: 0 | AN9: 0 | AO9: 106-2 | AP9: Zoila Margarita Martínez | AQ9: 0 | AS9: =+AQ9-AR9 -> 0 | AT9: 106-2 | AU9: Zoila Margarita Martinez | AV9: 0 | AX9: =+AV9-AW9 -> 0 | AY9: 106-2 | AZ9: 0 | BB9: =+AZ9-BA9 -> 0 | BC9: 0 | BD9: 0 | BE9: =+BC9-BD9 -> 0
A10: 107-1 | B10: WILLIAM CASTELLANOS- LISET GUE | E10: =+C10-D10 -> 0 | F10: 107-1 | G10: WILLIAM CASTELLANOS- LISET GUE | J10: =+H10-I10 -> 0 | K10: 107-1 | L10: WILLIAM CASTELLANOS | O10: =+M10-N10 -> 0 | P10: 107-1 | Q10: William Castellanos- Lizet Gue | T10: =+R10-S10 -> 0 | U10: 107-1 | V10: William Castellanos- Lizet Gue | W10: ='Notas agost 2025'!D18 -> 0 | X10: 0 | Y10: =+W10-X10 -> 0 | Z10: 107-1 | AA10: William Castellanos- Lizet Gue | AB10: 0 | AC10: 0 | AD10: =+AB10-AC10 -> 0 | AE10: 107-1 | AF10: William Castellanos- Lizet Gue | AG10: 0 | AH10: 0 | AI10: =+AG10-AH10 -> 0 | AJ10: 107-1 | AK10: William Castellanos- Lizet Gue | AL10: -39735 | AM10: -39735 | AN10: 0 | AO10: 107-1 | AP10: William Castellanos- Lizet Gue | AQ10: -39735 | AR10: 60 | AS10: =+AQ10-AR10 -> -39795 | AT10: 107-1 | AU10: William Castellanos- Liset Gue | AV10: -39795 | AX10: =+AV10-AW10 -> -39795 | AY10: 107-1 | AZ10: -39795 | BB10: =+AZ10-BA10 -> -39795 | BC10: 1140 | BD10: 56138 | BE10: =+BC10-BD10 -> -54998
A11: 108-7 | B11: JUAN JOSE PELAEZ-LILIANA GALLE | E11: =+C11-D11 -> 0 | F11: 108-7 | G11: JUAN JOSE PELAEZ-LILIANA GALLE | J11: =+H11-I11 -> 0 | K11: 108-7 | L11: LILIANA GALLEGO/JUAN P. PELAEZ | O11: =+M11-N11 -> 0 | P11: 108-7 | Q11: Juan José Peláez-Liliana Galle | T11: =+R11-S11 -> 0 | U11: 108-7 | V11: Juan José Peláez-Liliana Galle | W11: ='Notas agost 2025'!D19 -> -2367 | X11: -2367 | Y11: =+W11-X11 -> 0 | Z11: 108-7 | AA11: Juan José Peláez-Liliana Galle | AB11: 0 | AC11: 0 | AD11: =+AB11-AC11 -> 0 | AE11: 108-7 | AF11: Juan José Peláez-Liliana Galle | AG11: -817432 | AH11: -817432 | AI11: =+AG11-AH11 -> 0 | AJ11: 108-7 | AK11: Juan José Peláez-Liliana Galle | AL11: -1634864 | AM11: -1634864 | AN11: 0 | AO11: 108-7 | AP11: Juan José Peláez-Liliana Galle | AQ11: 0 | AR11: 0 | AS11: =+AQ11-AR11 -> 0 | AT11: 108-7 | AU11: Juan Jose Pelaez-Liliana Galle | AV11: 802 | AW11: 802 | AX11: =+AV11-AW11 -> 0 | AY11: 108-7 | AZ11: 792 | BA11: 792 | BB11: =+AZ11-BA11 -> 0 | BC11: 39006 | BD11: 39006 | BE11: =+BC11-BD11 -> 0
A12: 109-4 | B12: HUMBERTO GUEVARA CORRE | E12: =+C12-D12 -> 0 | F12: 109-4 | G12: HUMBERTO GUEVARA CORRE | J12: =+H12-I12 -> 0 | K12: 109-4 | L12: HUMBERTO GUEVARA CORREA | O12: =+M12-N12 -> 0 | P12: 109-4 | Q12: Marlent Giraldo | T12: =+R12-S12 -> 0 | U12: 109-4 | V12: Marlent Giraldo | W12: ='Notas agost 2025'!D20 -> 0 | X12: 0 | Y12: =+W12-X12 -> 0 | Z12: 109-4 | AA12: Marlent Giraldo | AB12: -99800 | AC12: -99800 | AD12: =+AB12-AC12 -> 0 | AE12: 109-4 | AF12: Marlent Giraldo | AG12: -99900 | AH12: -99900 | AI12: =+AG12-AH12 -> 0 | AJ12: 109-4 | AK12: Marlent Giraldo | AL12: 0 | AM12: 0 | AN12: 0 | AO12: 109-4 | AP12: Marlent Giraldo | AQ12: 121144 | AR12: 121144 | AS12: =+AQ12-AR12 -> 0 | AT12: 109-4 | AU12: Marlent Giraldo | AV12: 0 | AX12: =+AV12-AW12 -> 0 | AY12: 109-4 | AZ12: 0 | BA12: 6 | BB12: =+AZ12-BA12 -> -6 | BC12: 41314 | BD12: 41314 | BE12: =+BC12-BD12 -> 0
A13: 110-2 | B13: JIM PABEL ROMERO | E13: =+C13-D13 -> 0 | F13: 110-2 | G13: JIM PABEL ROMERO | J13: =+H13-I13 -> 0 | K13: 110-2 | L13: JIM PABEL ROMERO | O13: =+M13-N13 -> 0 | P13: 110-2 | Q13: Jim Pabel Romero | T13: =+R13-S13 -> 0 | U13: 110-2 | V13: Jim Pabel Romero | W13: ='Notas agost 2025'!D21 -> 240477 | X13: 240477 | Y13: =+W13-X13 -> 0 | Z13: 110-2 | AA13: Jim Pabel Romero | AB13: 0 | AC13: 0 | AD13: =+AB13-AC13 -> 0 | AE13: 110-2 | AF13: Jim Pabel Romero | AG13: 0 | AH13: 0 | AI13: =+AG13-AH13 -> 0 | AJ13: 110-2 | AK13: Jim Pabel Romero | AL13: 0 | AM13: 0 | AN13: 0 | AO13: 110-2 | AP13: Jim Pabel Romero | AQ13: 0 | AR13: 0 | AS13: =+AQ13-AR13 -> 0 | AT13: 110-2 | AU13: Jim Pabel Romero | AV13: 12 | AW13: 12 | AX13: =+AV13-AW13 -> 0 | AY13: 110-2 | AZ13: 6 | BB13: =+AZ13-BA13 -> 6 | BC13: 0 | BD13: 0 | BE13: =+BC13-BD13 -> 0
A14: 111-1 | B14: JUAN FELIPE MAYA | E14: =+C14-D14 -> 0 | F14: 111-1 | G14: JUAN FELIPE MAYA | J14: =+H14-I14 -> 0 | K14: 111-1 | L14: JUAN FELIPE MAYA | O14: =+M14-N14 -> 0 | P14: 111-1 | Q14: Juan Felipe Maya | T14: =+R14-S14 -> 0 | U14: 111-1 | V14: Juan Felipe Maya | W14: ='Notas agost 2025'!D22 -> 2160408 | X14: 2160408 | Y14: =+W14-X14 -> 0 | Z14: 111-1 | AA14: Juan Felipe Maya | AB14: 1000000 | AC14: 1000000 | AD14: =+AB14-AC14 -> 0 | AE14: 111-1 | AF14: Juan Felipe Maya | AG14: 1476264 | AH14: 1476264 | AI14: =+AG14-AH14 -> 0 | AJ14: 111-1 | AK14: Juan Felipe Maya | AL14: 554504 | AM14: 554504 | AN14: 0 | AO14: 111-1 | AP14: Juan Felipe Maya | AQ14: 602172 | AR14: 602172 | AS14: =+AQ14-AR14 -> 0 | AT14: 111-1 | AU14: Juan Felipe Maya | AV14: 878842 | AW14: 878842 | AX14: =+AV14-AW14 -> 0 | AY14: 111-1 | AZ14: 0 | BB14: =+AZ14-BA14 -> 0 | BC14: 0 | BD14: 0 | BE14: =+BC14-BD14 -> 0
A15: 112-7 | B15: JUAN CARLOS TAMAYO | E15: =+C15-D15 -> 0 | F15: 112-7 | G15: JUAN CARLOS TAMAYO | J15: =+H15-I15 -> 0 | K15: 112-7 | L15: Juan Carlos Tamayo | O15: =+M15-N15 -> 0 | P15: 112-7 | Q15: Juan carlos Tamayo | T15: =+R15-S15 -> 0 | U15: 112-7 | V15: Juan carlos Tamayo | W15: ='Notas agost 2025'!D23 -> -323473 | X15: -323473 | Y15: =+W15-X15 -> 0 | Z15: 112-7 | AA15: Juan carlos Tamayo | AB15: -411027 | AC15: -411027 | AD15: =+AB15-AC15 -> 0 | AE15: 112-7 | AF15: Juan carlos Tamayo | AG15: -339283 | AH15: -339283 | AI15: =+AG15-AH15 -> 0 | AJ15: 112-7 | AK15: Juan carlos Tamayo | AL15: -267539 | AM15: -267539 | AN15: 0 | AO15: 112-7 | AP15: Juan carlos Tamayo | AQ15: -455093 | AR15: -455093 | AS15: =+AQ15-AR15 -> 0 | AT15: 112-7 | AU15: Juan Carlos Tamayo | AV15: -390617 | AW15: -390617 | AX15: =+AV15-AW15 -> 0 | AY15: 112-7 | AZ15: 1094702 | BA15: 1094702 | BB15: =+AZ15-BA15 -> 0 | BC15: 100169 | BD15: 100169 | BE15: =+BC15-BD15 -> 0
A16: 113-4 | B16: JUAN CAMILO RENDON | E16: =+C16-D16 -> 0 | F16: 113-4 | G16: JUAN CAMILO RENDON | J16: =+H16-I16 -> 0 | K16: 113-4 | L16: JUAN CAMILO RENDON | O16: =+M16-N16 -> 0 | P16: 113-4 | Q16: Juan Camilo Rendon | T16: =+R16-S16 -> 0 | U16: 113-4 | V16: Juan Camilo Rendon | W16: ='Notas agost 2025'!D24 -> 0 | X16: 0 | Y16: =+W16-X16 -> 0 | Z16: 113-4 | AA16: Juan Camilo Rendon | AB16: 0 | AC16: 0 | AD16: =+AB16-AC16 -> 0 | AE16: 113-4 | AF16: Juan Camilo Rendon | AG16: 0 | AH16: 0 | AI16: =+AG16-AH16 -> 0 | AJ16: 113-4 | AK16: Juan Camilo Rendon | AL16: 0 | AM16: 0 | AN16: 0 | AO16: 113-4 | AP16: Juan Camilo Rendon | AQ16: 0 | AS16: =+AQ16-AR16 -> 0 | AT16: 113-4 | AU16: Juan Camilo Rendon | AV16: 0 | AX16: =+AV16-AW16 -> 0 | AY16: 113-4 | AZ16: 0 | BB16: =+AZ16-BA16 -> 0 | BC16: 0 | BD16: 0 | BE16: =+BC16-BD16 -> 0
A17: 114-1 | B17: MARIANA GOMEZ-MARGARITA GONZAL | E17: =+C17-D17 -> 0 | F17: 114-1 | G17: MARIANA GOMEZ-MARGARITA GONZAL | J17: =+H17-I17 -> 0 | K17: 114-1 | L17: MARIANA GOMEZ-MARGARITA GONZALEZ | O17: =+M17-N17 -> 0 | P17: 114-1 | Q17: Margarita Gonzales | T17: =+R17-S17 -> 0 | U17: 114-1 | V17: Margarita Gonzales | W17: ='Notas agost 2025'!D25 -> 0 | X17: 0 | Y17: =+W17-X17 -> 0 | Z17: 114-1 | AA17: Margarita Gonzales | AB17: 0 | AC17: 0 | AD17: =+AB17-AC17 -> 0 | AE17: 114-1 | AF17: Margarita Gonzales | AG17: 0 | AH17: 0 | AI17: =+AG17-AH17 -> 0 | AJ17: 114-1 | AK17: Margarita Gonzales | AL17: 0 | AM17: 0 | AN17: 0 | AO17: 114-1 | AP17: Margarita Gonzales | AQ17: 0 | AS17: =+AQ17-AR17 -> 0 | AT17: 114-1 | AU17: Andres Mejia | AV17: 0 | AX17: =+AV17-AW17 -> 0 | AY17: 114-1 | AZ17: 0 | BB17: =+AZ17-BA17 -> 0 | BC17: 0 | BD17: 0 | BE17: =+BC17-BD17 -> 0
A18: 115-9 | B18: ELENA ALVAREZ | E18: =+C18-D18 -> 0 | F18: 115-9 | G18: ELENA ALVAREZ | J18: =+H18-I18 -> 0 | K18: 115-9 | L18: ELENA ALVAREZ | O18: =+M18-N18 -> 0 | P18: 115-9 | Q18: Elena Álvarez | T18: =+R18-S18 -> 0 | U18: 115-9 | V18: Elena Álvarez | W18: ='Notas agost 2025'!D26 -> 0 | X18: 0 | Y18: =+W18-X18 -> 0 | Z18: 115-9 | AA18: Elena Álvarez | AB18: 608316 | AC18: 608316 | AD18: =+AB18-AC18 -> 0 | AE18: 115-9 | AF18: Elena Álvarez | AG18: 1548623 | AH18: 1548623 | AI18: =+AG18-AH18 -> 0 | AJ18: 115-9 | AK18: Elena Álvarez | AL18: 1490118 | AM18: 1490118 | AN18: 0 | AO18: 115-9 | AP18: Elena Álvarez | AQ18: 161290 | AR18: 161290 | AS18: =+AQ18-AR18 -> 0 | AT18: 115-9 | AU18: Elena Alvarez | AV18: 25253 | AW18: 25253 | AX18: =+AV18-AW18 -> 0 | AY18: 115-9 | AZ18: 32101 | BA18: 32101 | BB18: =+AZ18-BA18 -> 0 | BC18: 136823 | BD18: 136823 | BE18: =+BC18-BD18 -> 0
A19: 116-6 | B19: JUAN PABLO ARBELAEZ | E19: =+C19-D19 -> 0 | F19: 116-6 | G19: JUAN PABLO ARBELAEZ | J19: =+H19-I19 -> 0 | K19: 116-6 | L19: INVER ARBELAEZ ESCOBAR S.A.S. | O19: =+M19-N19 -> 0 | P19: 116-6 | Q19: Inversiones Arbeláez | T19: =+R19-S19 -> 0 | U19: 116-6 | V19: Inversiones Arbeláez | W19: ='Notas agost 2025'!D27 -> 0 | X19: 0 | Y19: =+W19-X19 -> 0 | Z19: 116-6 | AA19: Inversiones Arbeláez | AB19: 0 | AC19: 0 | AD19: =+AB19-AC19 -> 0 | AE19: 116-6 | AF19: Inversiones Arbeláez | AG19: 0 | AH19: 0 | AI19: =+AG19-AH19 -> 0 | AJ19: 116-6 | AK19: Inversiones Arbeláez | AL19: 0 | AM19: 0 | AN19: 0 | AO19: 116-6 | AP19: Inversiones Arbeláez | AQ19: 0 | AS19: =+AQ19-AR19 -> 0 | AT19: 116-6 | AU19: Juan Pablo Arbelaez | AV19: 0 | AX19: =+AV19-AW19 -> 0 | AY19: 116-6 | AZ19: 0 | BB19: =+AZ19-BA19 -> 0 | BC19: 0 | BD19: 0 | BE19: =+BC19-BD19 -> 0
A20: 117-3 | B20: JIOVANI JIMENEZ | E20: =+C20-D20 -> 0 | F20: 117-3 | G20: JIOVANI JIMENEZ | J20: =+H20-I20 -> 0 | K20: 117-3 | L20: JIOVANI JIMENEZ | O20: =+M20-N20 -> 0 | P20: 117-3 | Q20: Jovani Jiménez | T20: =+R20-S20 -> 0 | U20: 117-3 | V20: Jovani Jiménez | W20: ='Notas agost 2025'!D28 -> 0 | X20: 0 | Y20: =+W20-X20 -> 0 | Z20: 117-3 | AA20: Jovani Jiménez | AB20: 0 | AC20: 0 | AD20: =+AB20-AC20 -> 0 | AE20: 117-3 | AF20: Jovani Jiménez | AG20: 0 | AH20: 0 | AI20: =+AG20-AH20 -> 0 | AJ20: 117-3 | AK20: Jovani Jiménez | AL20: -37458 | AM20: -37458 | AN20: 0 | AO20: 117-3 | AP20: Jovani Jiménez | AQ20: -1242726 | AR20: -1242726 | AS20: =+AQ20-AR20 -> 0 | AT20: 117-3 | AU20: Gabriel Tamayo | AV20: 0 | AX20: =+AV20-AW20 -> 0 | AY20: 117-3 | AZ20: 0 | BB20: =+AZ20-BA20 -> 0 | BC20: 0 | BD20: 0 | BE20: =+BC20-BD20 -> 0
A21: 118-0 | B21: JULIO CESAR DAVID | E21: =+C21-D21 -> 0 | F21: 118-0 | G21: JULIO CESAR DAVID | J21: =+H21-I21 -> 0 | K21: 118-0 | L21: JULIO CESAR DAVID | O21: =+M21-N21 -> 0 | P21: 118-0 | Q21: Julio Cesar David | T21: =+R21-S21 -> 0 | U21: 118-0 | V21: Julio Cesar David | W21: ='Notas agost 2025'!D29 -> 2279924 | X21: 2279924 | Y21: =+W21-X21 -> 0 | Z21: 118-0 | AA21: Julio Cesar David | AB21: 1003279 | AC21: 1003279 | AD21: =+AB21-AC21 -> 0 | AE21: 118-0 | AF21: Julio Cesar David | AG21: 0 | AH21: 0 | AI21: =+AG21-AH21 -> 0 | AJ21: 118-0 | AK21: Julio Cesar David | AL21: 0 | AM21: 0 | AN21: 0 | AO21: 118-0 | AP21: Julio Cesar David | AQ21: 1026425 | AR21: 1026425 | AS21: =+AQ21-AR21 -> 0 | AT21: 118-0 | AU21: Julio Cesar David | AV21: 998218 | AW21: 998218 | AX21: =+AV21-AW21 -> 0 | AY21: 118-0 | AZ21: 1146852 | BA21: 1146552 | BB21: =+AZ21-BA21 -> 300 | BC21: 958699 | BD21: 958699 | BE21: =+BC21-BD21 -> 0
A22: 119-8 | B22: RUSBEL ESPINOZA | E22: =+C22-D22 -> 0 | F22: 119-8 | G22: RUSBEL ESPINOZA | J22: =+H22-I22 -> 0 | K22: 119-8 | L22: RUSBEL ESPINOZA | O22: =+M22-N22 -> 0 | P22: 119-8 | Q22: Rusbel Espinoza | T22: =+R22-S22 -> 0 | U22: 119-8 | V22: Rusbel Espinoza | W22: ='Notas agost 2025'!D30 -> 1670320 | X22: 1670320 | Y22: =+W22-X22 -> 0 | Z22: 119-8 | AA22: Rusbel Espinoza | AB22: 0 | AC22: 0 | AD22: =+AB22-AC22 -> 0 | AE22: 119-8 | AF22: Rusbel Espinoza | AG22: 2688126 | AH22: 2688126 | AI22: =+AG22-AH22 -> 0 | AJ22: 119-8 | AK22: Rusbel Espinoza | AL22: 1333938 | AM22: 1333938 | AN22: 0 | AO22: 119-8 | AP22: Rusbel Espinoza | AQ22: -336383 | AR22: -336383 | AS22: =+AQ22-AR22 -> 0 | AT22: 119-8 | AU22: Ferney Gautan - Rosiris Rueda | AV22: 0 | AX22: =+AV22-AW22 -> 0 | AY22: 119-8 | AZ22: 0 | BB22: =+AZ22-BA22 -> 0 | BC22: 0 | BD22: 0 | BE22: =+BC22-BD22 -> 0
A23: 120-6 | B23: PABLO MARQUEZ-ANGELA AGUIRRE | E23: =+C23-D23 -> 0 | F23: 120-6 | G23: PABLO MARQUEZ-ANGELA AGUIRRE | J23: =+H23-I23 -> 0 | K23: 120-6 | L23: PABLO MARQUEZ-ANGELA AGUIRRE | O23: =+M23-N23 -> 0 | P23: 120-6 | Q23: Pablo Márquez | T23: =+R23-S23 -> 0 | U23: 120-6 | V23: Pablo Márquez | W23: ='Notas agost 2025'!D31 -> 0 | X23: 0 | Y23: =+W23-X23 -> 0 | Z23: 120-6 | AA23: Pablo Márquez | AB23: 1184963 | AC23: 1184963 | AD23: =+AB23-AC23 -> 0 | AE23: 120-6 | AF23: Pablo Márquez | AG23: 0 | AH23: 0 | AI23: =+AG23-AH23 -> 0 | AJ23: 120-6 | AK23: Pablo Márquez | AL23: 292815 | AM23: 0 | AN23: 292815 | AO23: 120-6 | AP23: Pablo Márquez | AQ23: -6000 | AR23: -298815 | AS23: =+AQ23-AR23 -> 292815 | AT23: 120-6 | AU23: Laura Tobon | AV23: 0 | AX23: =+AV23-AW23 -> 0 | AY23: 120-6 | AZ23: 0 | BB23: =+AZ23-BA23 -> 0 | BC23: 0 | BD23: 0 | BE23: =+BC23-BD23 -> 0
A24: 121-3 | B24: DARIO POSADA | E24: =+C24-D24 -> 0 | F24: 121-3 | G24: DARIO POSADA | J24: =+H24-I24 -> 0 | K24: 121-3 | L24: DARIO POSADA | O24: =+M24-N24 -> 0 | P24: 121-3 | Q24: Darío Posada | T24: =+R24-S24 -> 0 | U24: 121-3 | V24: Darío Posada | W24: ='Notas agost 2025'!D32 -> -87545 | X24: -87545 | Y24: =+W24-X24 -> 0 | Z24: 121-3 | AA24: Darío Posada | AB24: -69145 | AC24: -69145 | AD24: =+AB24-AC24 -> 0 | AE24: 121-3 | AF24: Darío Posada | AG24: -50745 | AH24: -50745 | AI24: =+AG24-AH24 -> 0 | AJ24: 121-3 | AK24: Darío Posada | AL24: -32345 | AM24: -32345 | AN24: 0 | AO24: 121-3 | AP24: Darío Posada | AQ24: -13499 | AR24: -13508 | AS24: =+AQ24-AR24 -> 9 | AT24: 121-3 | AU24: Dario Posada | AV24: 9 | AX24: =+AV24-AW24 -> 9 | AY24: 121-3 | AZ24: 60152 | BA24: 60143 | BB24: =+AZ24-BA24 -> 9 | BC24: 58938 | BD24: 58938 | BE24: =+BC24-BD24 -> 0
A25: 122-0 | B25: Guadalupe R.M | E25: =+C25-D25 -> 0 | F25: 122-0 | G25: Guadalupe R.M | J25: =+H25-I25 -> 0 | K25: 122-0 | L25: Guadalupe R.M | O25: =+M25-N25 -> 0 | P25: 122-0 | Q25: Guadalupe RM SAS | T25: =+R25-S25 -> 0 | U25: 122-0 | V25: Guadalupe RM SAS | W25: ='Notas agost 2025'!D33 -> 1489736 | X25: 1489736 | Y25: =+W25-X25 -> 0 | Z25: 122-0 | AA25: Guadalupe RM SAS | AB25: 0 | AC25: 0 | AD25: =+AB25-AC25 -> 0 | AE25: 122-0 | AF25: Guadalupe RM SAS | AG25: 0 | AH25: 0 | AI25: =+AG25-AH25 -> 0 | AJ25: 122-0 | AK25: Guadalupe RM SAS | AL25: 0 | AM25: 0 | AN25: 0 | AO25: 122-0 | AP25: Guadalupe RM SAS | AQ25: 0 | AR25: -90000 | AS25: =+AQ25-AR25 -> 90000 | AT25: 122-0 | AU25: Ruben Villa | AV25: 90000 | AW25: 90000 | AX25: =+AV25-AW25 -> 0 | AY25: 122-0 | AZ25: 1148350 | BA25: 1148350 | BB25: =+AZ25-BA25 -> 0 | BC25: 0 | BD25: 0 | BE25: =+BC25-BD25 -> 0
A26: 123-8 | B26: GLORIA BETANCUR-RAMON HENAO | E26: =+C26-D26 -> 0 | F26: 123-8 | G26: GLORIA BETANCUR-RAMON HENAO | J26: =+H26-I26 -> 0 | K26: 123-8 | L26: RAMON HENAO GLORIA BETANCUR | O26: =+M26-N26 -> 0 | P26: 123-8 | Q26: Gloria Betancur-Ramon Henao | T26: =+R26-S26 -> 0 | U26: 123-8 | V26: Gloria Betancur-Ramon Henao | W26: ='Notas agost 2025'!D34 -> 0 | X26: 0 | Y26: =+W26-X26 -> 0 | Z26: 123-8 | AA26: Gloria Betancur-Ramon Henao | AB26: 0 | AC26: 0 | AD26: =+AB26-AC26 -> 0 | AE26: 123-8 | AF26: Gloria Betancur-Ramon Henao | AG26: 1115679 | AH26: 1115679 | AI26: =+AG26-AH26 -> 0 | AJ26: 123-8 | AK26: Gloria Betancur-Ramon Henao | AL26: 0 | AM26: 0 | AN26: 0 | AO26: 123-8 | AP26: Gloria Betancur-Ramon Henao | AQ26: 0 | AR26: -89510 | AS26: =+AQ26-AR26 -> 89510 | AT26: 123-8 | AU26: Gloria Betancur-Ramon Henao | AV26: 0 | AX26: =+AV26-AW26 -> 0 | AY26: 123-8 | AZ26: 0 | BB26: =+AZ26-BA26 -> 0 | BC26: 0 | BD26: 0 | BE26: =+BC26-BD26 -> 0
A27: 124-5 | B27: OLGA BEATRIZ VILLA | E27: =+C27-D27 -> 0 | F27: 124-5 | G27: OLGA BEATRIZ VILLA | J27: =+H27-I27 -> 0 | K27: 124-5 | L27: OLGA BEATRIZ VILLA | O27: =+M27-N27 -> 0 | P27: 124-5 | Q27: Gustavo Galán | T27: =+R27-S27 -> 0 | U27: 124-5 | V27: Gustavo Galán | W27: ='Notas agost 2025'!D35 -> 0 | X27: 0 | Y27: =+W27-X27 -> 0 | Z27: 124-5 | AA27: Gustavo Galán | AB27: 0 | AC27: 0 | AD27: =+AB27-AC27 -> 0 | AE27: 124-5 | AF27: Gustavo Galán | AG27: 0 | AH27: 0 | AI27: =+AG27-AH27 -> 0 | AJ27: 124-5 | AK27: Gustavo Galán | AL27: 0 | AM27: 0 | AN27: 0 | AO27: 124-5 | AP27: Gustavo Galán | AQ27: 0 | AS27: =+AQ27-AR27 -> 0 | AT27: 124-5 | AU27: Olga Beatriz Villa | AV27: 0 | AX27: =+AV27-AW27 -> 0 | AY27: 124-5 | AZ27: 89510 | BA27: 89510 | BB27: =+AZ27-BA27 -> 0 | BC27: 0 | BD27: 0 | BE27: =+BC27-BD27 -> 0
A28: 125-2 | B28: GLORIA IDARRAGA | E28: =+C28-D28 -> 0 | F28: 125-2 | G28: GLORIA IDARRAGA | J28: =+H28-I28 -> 0 | K28: 125-2 | L28: GLORIA IDARRAGA VALERIA GIRALDO | O28: =+M28-N28 -> 0 | P28: 125-2 | Q28: Gloria Idárraga | T28: =+R28-S28 -> 0 | U28: 125-2 | V28: Gloria Idárraga | W28: ='Notas agost 2025'!D36 -> 630524 | X28: =630524-260 -> 630264 | Y28: -260 | Z28: 125-2 | AA28: Gloria Idárraga | AB28: 470260 | AC28: 470260 | AD28: =+AB28-AC28 -> 0 | AE28: 125-2 | AF28: Gloria Idárraga | AG28: 2176048 | AH28: 2176048 | AI28: =+AG28-AH28 -> 0 | AJ28: 125-2 | AK28: Gloria Idárraga | AL28: 679927 | AM28: 679927 | AN28: 0 | AO28: 125-2 | AP28: Gloria Idárraga | AQ28: 240918 | AR28: 240918 | AS28: =+AQ28-AR28 -> 0 | AT28: 125-2 | AU28: Gloria Idarraga | AV28: 25448 | AW28: 25448 | AX28: =+AV28-AW28 -> 0 | AY28: 125-2 | AZ28: 16343 | BA28: 16343 | BB28: =+AZ28-BA28 -> 0 | BC28: 7419 | BD28: 7419 | BE28: =+BC28-BD28 -> 0
A29: 126-1 | B29: GABRIEL GOMEZ | E29: =+C29-D29 -> 0 | F29: 126-1 | G29: GABRIEL GOMEZ | J29: =+H29-I29 -> 0 | K29: 126-1 | L29: GABRIEL GOMEZ | O29: =+M29-N29 -> 0 | P29: 126-1 | Q29: Gabriel Gómez | T29: =+R29-S29 -> 0 | U29: 126-1 | V29: Gabriel Gómez | W29: ='Notas agost 2025'!D37 -> 860984 | X29: 860984 | Y29: =+W29-X29 -> 0 | Z29: 126-1 | AA29: Gabriel Gómez | AB29: 1289903 | AC29: 1289903 | AD29: =+AB29-AC29 -> 0 | AE29: 126-1 | AF29: Gabriel Gómez | AG29: 1074050 | AH29: 1074050 | AI29: =+AG29-AH29 -> 0 | AJ29: 126-1 | AK29: Gabriel Gómez | AL29: 0 | AM29: 0 | AN29: 0 | AO29: 126-1 | AP29: Gabriel Gómez | AQ29: -98916 | AR29: -98916 | AS29: =+AQ29-AR29 -> 0 | AT29: 126-1 | AU29: Gabriel Gomez | AV29: 1200679 | AW29: 1200679 | AX29: =+AV29-AW29 -> 0 | AY29: 126-1 | AZ29: 160715 | BA29: 160715 | BB29: =+AZ29-BA29 -> 0 | BC29: 170552 | BD29: 170552 | BE29: =+BC29-BD29 -> 0
A30: 127-7 | B30: EDWIN GONZALEZ | E30: =+C30-D30 -> 0 | F30: 127-7 | G30: EDWIN GONZALEZ | J30: =+H30-I30 -> 0 | K30: 127-7 | L30: EDWIN GONZALEZ | O30: =+M30-N30 -> 0 | P30: 127-7 | Q30: Edwin González | T30: =+R30-S30 -> 0 | U30: 127-7 | V30: Edwin González | W30: ='Notas agost 2025'!D38 -> 0 | X30: 0 | Y30: =+W30-X30 -> 0 | Z30: 127-7 | AA30: Edwin González | AB30: 0 | AC30: 0 | AD30: =+AB30-AC30 -> 0 | AE30: 127-7 | AF30: Edwin González | AG30: 0 | AH30: 0 | AI30: =+AG30-AH30 -> 0 | AJ30: 127-7 | AK30: Edwin González | AL30: 0 | AM30: 0 | AN30: 0 | AO30: 127-7 | AP30: Edwin González | AQ30: 0 | AR30: 0 | AS30: =+AQ30-AR30 -> 0 | AT30: 127-7 | AU30: Edwin Gonzalez | AV30: -584 | AW30: -584 | AX30: =+AV30-AW30 -> 0 | AY30: 127-7 | AZ30: 0 | BB30: =+AZ30-BA30 -> 0 | BC30: 0 | BD30: 0 | BE30: =+BC30-BD30 -> 0
A31: 128-4 | B31: ROBINSON VALDERRAMA | E31: =+C31-D31 -> 0 | F31: 128-4 | G31: ROBINSON VALDERRAMA | J31: =+H31-I31 -> 0 | K31: 128-4 | L31: ROBINSON VALDERRAMA | O31: =+M31-N31 -> 0 | P31: 128-4 | Q31: Robinson Valderrama | T31: =+R31-S31 -> 0 | U31: 128-4 | V31: Robinson Valderrama | W31: ='Notas agost 2025'!D39 -> 1147183 | X31: 1147183 | Y31: =+W31-X31 -> 0 | Z31: 128-4 | AA31: Robinson Valderrama | AB31: 0 | AC31: 0 | AD31: =+AB31-AC31 -> 0 | AE31: 128-4 | AF31: Robinson Valderrama | AG31: -846 | AH31: -846 | AI31: =+AG31-AH31 -> 0 | AJ31: 128-4 | AK31: Robinson Valderrama | AL31: 0 | AM31: 0 | AN31: 0 | AO31: 128-4 | AP31: Robinson Valderrama | AQ31: 1011731 | AR31: 1011731 | AS31: =+AQ31-AR31 -> 0 | AT31: 128-4 | AU31: Robinson Valderrama | AV31: 0 | AW31: 0 | AX31: =+AV31-AW31 -> 0 | AY31: 128-4 | AZ31: =-865705+874880 -> 9175 | BA31: =-874880+9175 -> -865705 | BB31: =+AZ31-BA31 -> 874880 | BC31: 0 | BD31: 0 | BE31: =+BC31-BD31 -> 0
A32: 129-1 | B32: CARLOS RESTREPO | F32: 129-1 | G32: CARLOS RESTREPO | J32: =+H32-I32 -> 0 | K32: 129-1 | L32: CARLOS ESTEBAN RESTREPO | O32: =+M32-N32 -> 0 | P32: 129-1 | Q32: Carlos Restrepo | T32: 0 | U32: 129-1 | V32: Carlos Restrepo | W32: ='Notas agost 2025'!D40 -> 0 | X32: 0 | Y32: 0 | Z32: 129-1 | AA32: Carlos Restrepo | AB32: 0 | AC32: 0 | AD32: =+AB32-AC32 -> 0 | AE32: 129-1 | AF32: Carlos Restrepo | AG32: 0 | AH32: 0 | AI32: 0 | AJ32: 129-1 | AK32: Carlos Restrepo | AL32: 0 | AM32: 0 | AN32: 0 | AO32: 129-1 | AP32: Carlos Restrepo | AQ32: -246401 | AR32: -246401 | AS32: 0 | AT32: 129-1 | AU32: Carlos Restrepo | AV32: 0 | AW32: 0 | AY32: 129-1 | AZ32: 0 | BA32: 0 | BB32: =+AZ32-BA32 -> 0 | BC32: 0 | BD32: 0 | BE32: =+BC32-BD32 -> 0
AB33: =SUM(AB4:AB32) -> 8689091 | AC33: 11341985 | AD33: =SUM(AD4:AD32) -> 0 | AF33: TOTAL CARTERA | AG33: =SUM(AG4:AG32) -> 12541985 | AH33: 11341985 | BE33: =SUM(BE4:BE32) -> -54998 | BF33: Prom
A34: Cartera | B34: TOTAL CARTERA | C34: =SUM(C4:C32) -> 0 | D34: =SUM(D4:D32) -> 0 | E34: =SUM(E4:E32) -> 0 | G34: TOTAL CARTERA | H34: =SUM(H4:H32) -> 0 | I34: =SUM(I4:I32) -> 0 | J34: =SUM(J4:J32) -> 0 | L34: TOTAL CARTERA | O34: =+M34-N34 -> 0 | Q34: TOTAL CARTERA | R34: =SUM(R4:R31) -> 0 | S34: =SUM(S4:S31) -> 0 | T34: =SUM(T4:T31) -> 0 | U34: =SUM(U4:U31) -> 0 | V34: =SUM(V4:V31) -> 0 | W34: =SUM(W4:W31) -> 14423568 | X34: =SUM(X4:X31) -> 14428308 | Y34: =SUM(Y4:Y31) -> 4740 | ... BC34: =SUM(BC4:BC31) -> 4630022 | BF34: =(C34+H34+M34+R34+W34+AB34+AG34+AL34+AQ34+AV34+AZ34+BC34)/12 -> 4904726.1
A35: Facturación | D35: 0 | W35: 46112831 | AB35: 42527554 | AG35: 33785820 | AL35: 42169112 | AQ35: 36919858 | AV35: 34865211 | AZ35: 33481694 | BC35: 32149530 | BF35: =(C35+H35+M35+R35+W35+AB35+AG35+AL35+AQ35+AV35+AZ35+BC35)/12 -> 25167634 | BG35: =SUM(C35:BC35) -> 302011610
A36: Recaudo | C36: =C35-C34 -> 0 | D36: =D35-D34 -> 0 | E36: =E35-E34 -> 0 | F36: =F35-F34 -> 0 | G36: =G35-G34 -> #VALUE! | H36: =H35-H34 -> 0 | I36: =I35-I34 -> 0 | J36: =J35-J34 -> 0 | ... AF36: =AF35-AF34 -> 0 | AG36: 22443835 | AH36: =AH35-AH34 -> -11341985 | AI36: =AI35-AI34 -> -1200000 | AJ36: =AJ35-AJ34 -> 0 | AK36: =AK35-AK34 -> 0 | AL36: 38519785 | AM36: =AM35-AM34 -> -3649327 | AN36: =AN35-AN34 -> -292815 | AO36: =AO35-AO34 -> 0 | AP36: =AP35-AP34 -> 0 | AQ36: =AQ35-AQ34 -> 32403745 | AR36: =AR35-AR34 -> -4083574 | AS36: =AS35-AS34 -> -432539 | AT36: =AT35-AT34 -> 0 | ... BE36: =BE35-BE34 -> 0
A37: %cartera | C37: =C34/C35 -> #DIV/0! | D37: =D34/D35 -> #DIV/0! | E37: =E34/E35 -> #DIV/0! | F37: =F34/F35 -> #DIV/0! | G37: =G34/G35 -> #VALUE! | H37: =H34/H35 -> #DIV/0! | I37: =I34/I35 -> #DIV/0! | J37: =J34/J35 -> #DIV/0! | ... AQ37: =AQ34/AQ35 -> 0.12232206 | AV37: =AV34/AV35 -> 0.11844047 | AZ37: =AZ34/AZ35 -> 0.17873468 | BC37: =BC34/BC35 -> 0.14401523
W38: agos | AB38: jul | AG38: jun | AL38: may | AQ38: abr | AV38: marz | AZ38: feb | BC38: ene
BF40: =BF34/BF35 -> 0.19488229

Sheet Tabla cartera
A1: INMUEBLE | B1: SALDO CONTABILIDAD | C1: FACTURACIÓN
A2: 101-6 | B2: 1747986 | C2: Se le enviò comunicado
A3: 102-3 | B3: 0
A4: 103-0 | B4: 0
A5: 104-8 | B5: 930723
A6: 105-5 | B6: 1033633 | C6: Se le enviò comunicado
A7: 106-2 | B7: 0
A8: 107-1 | B8: 0
A9: 108-7 | B9: 0
A10: 109-4 | B10: -99800
A11: 110-2 | B11: 0
A12: 111-1 | B12: 1000000 | C12: Se le enviò comunicado
A13: 112-7 | B13: -411027
A14: 113-4 | B14: 0
A15: 114-1 | B15: 0
A16: 115-9 | B16: 608316
A17: 116-6 | B17: 0
A18: 117-3 | B18: 0
A19: 118-0 | B19: 1003279 | C19: 1003279
A20: 119-8 | B20: 0 | C20: 0
A21: 120-6 | B21: 1184963 | C21: Se le enviò comunicado
A22: 121-3 | B22: -69145
A23: 122-0 | B23: 0
A24: 123-8 | B24: 0
A25: 124-5 | B25: 0
A26: 125-2 | B26: 470260
A27: 126-1 | B27: 1289903 | C27: 1289903
A28: 127-7 | B28: 0 | C28: 0
A29: 128-4 | B29: 0 | C29: 0
A30: 129-1 | B30: 0 | C30: 0
B31: =SUM(B2:B30) -> 8689091

Sheet Notas agost 2025
B2: RELACIÓN DE CUENTAS POR PAGAR - ACREEDORES VARIOS A 30/08/2025
C3: CONCEPTO | D3: BENEFICIARIO | E3: VALOR
C4: Gabiela Munoz | D4: Honorarios | E4: 534252
C5: Entrejardines | D5: saldo fra. Julio | E5: 496
C6: SERVIC TEC Y ELECTRONICOS S.A | D6: Fra mes | E6: =-142800+285600 -> 142800
C7: Dian | D7: Retenciones | E7: =+[3]ESFA!C38 -> 135159.06
C8: TOTAL CUENTAS POR PAGAR | E8: =SUM(E4:E7) -> 812707.06
C10: DETALLE CARTERA CONTABILIDAD VS FACTURACIÓN
B11: INMUEBLE | C11: PROPIETARIO | D11: SALDO CONTABILIDAD | E11: FACTURACIÓN | F11: DIFER.
B12: 101-6 | C12: OLGA DEL SOCORRO ARBELAEZ | D12: 3065812 | E12: 0
B13: 102-3 | C13: DIEGO GÓMEZ | D13: 0 | E13: 0
B14: 103-0 | C14: JUAN CAMILO SOTO | D14: 0 | E14: 0
B15: 104-8 | C15: ALVARO GOMEZ | D15: 0 | E15: 0
B16: 105-5 | C16: VICTOR ALFONSO CARDONA | D16: 1291585 | E16: 5000 | F16: RECIBO 5311 MAL ELABORADO
B17: 106-2 | C17: ZOILA MARGARITA INSIGNARES | D17: 0 | E17: 0
B18: 107-1 | C18: WILLIAM CASTELLANOS | D18: 0 | E18: 0
B19: 108-7 | C19: LILIANA GALLEGO/JUAN P. PELAEZ | D19: -2367 | E19: 0
B20: 109-4 | C20: HUMBERTO GUEVARA CORREA | D20: 0 | E20: 0
B21: 110-2 | C21: JIM PABEL ROMERO | D21: 240477 | E21: 0
B22: 111-1 | C22: JUAN FELIPE MAYA | D22: 2160408 | E22: 0
B23: 112-7 | C23: Juan Carlos Tamayo | D23: -323473 | E23: 0
B24: 113-4 | C24: JUAN CAMILO RENDON | D24: 0 | E24: 0
B25: 114-1 | C25: MARIANA GOMEZ-MARGARITA GONZALEZ | D25: 0 | E25: 0
B26: 115-9 | C26: ELENA ALVAREZ | D26: 0 | E26: 0
B27: 116-6 | C27: INVER ARBELAEZ ESCOBAR S.A.S. | D27: 0 | E27: 0
B28: 117-3 | C28: JIOVANI JIMENEZ | D28: 0 | E28: 0
